Workbook

Sheet 0. README
A1: Section | B1: Content
A2: Model Name | B2: LaunchPlan AI: 24-Month SaaS Operating Model
A3: Purpose | B3: This model helps founders evaluate ARR growth, burn, runway, hiring capacity, unit economics, and fundraising timing.
A4: Business Type | B4: AI SaaS startup
A5: Forecast Period | B5: 24 months
A6: Scenario Logic | B6: Bear, Base, and Bull cases are driven from the Assumptions tab.
A7: Key Outputs | B7: ARR, MRR growth, Gross Margin, CAC Payback, Monthly Burn, Runway, Headcount, and Fundraising Trigger
A8: Main Decision Questions | B8: When should the company hire? When should it preserve cash? When should it begin fundraising?
A9: How to Use | B9: Change assumptions only in the Assumptions tab. Review outputs in Scenarios, Budget vs Actual, and Dashboard.
A10: Dashboard Purpose | B10: The dashboard summarizes the full operating story in one screen for founder-level decision-making.
A12: LaunchPlan AI: 24-Month SaaS Operating Model This workbook is a founder-facing startup finance model built for an early-stage AI SaaS company. The model connects assumptions, revenue growth, churn, headcount planning, COGS, gross margin, unit economics, P&L, cash runway, scenario analysis, budget vs actual tracking, and an executive dashboard. The purpose of the model is not only to forecast financial performance, but to support operating decisions. It helps answer whether the company can afford its hiring plan, whether CAC payback supports GTM expansion, whether gross margin improves toward target, and when fundraising should begin based on runway and burn. The model is structured around a 24-month forecast period with Bear, Base, and Bull case logic. Inputs are managed in the Assumptions tab, while outputs are summarized through Scenarios, Budget vs Actual, and the Dashboard. Key dashboard outputs include ARR, MRR growth, monthly burn, cash runway, gross margin, CAC payback, headcount, and fundraising trigger status.

Sheet 1. Assumptions
A1: LaunchPlan AI — Master Assumptions Tab | FP&A Model | 24-Month Horizon
A2: YELLOW = Hardcoded Input | C2: BLUE = Formula | E2: GREEN = Dashboard Output | H2: RED = Check / Warning
A3: Category | B3: Assumption | C3: Unit | D3: Bear | E3: Base | F3: Bull | G3: Selected Value | H3: Logic / Reasoning | I3: Source / Benchmark | J3: Feeds Into
A4: § 1 CONTROL PANEL
A5: Control Panel | B5: Selected Scenario | C5: Text | G5: Base | H5: Dropdown drives the active model view. Use data validation. | I5: Model design best practice | J5: All tabs
A6: Control Panel | B6: Start Date | C6: Date | D6: 46023 | E6: 46023 | F6: 46023 | G6: =_xlfn.XLOOKUP($G$5,$D$3:$F$3,D6:F6) -> 46023 | H6: Every month offsets from this date via DATE() formulas. Never hardcode month names elsewhere. | I6: Model design best practice | J6: All tabs
A7: Control Panel | B7: Model Horizon | C7: Months | D7: 24 | E7: 24 | F7: 24 | G7: =_xlfn.XLOOKUP($G$5,$D$3:$F$3,D7:F7) -> 24 | H7: 24 months covers Seed-to-Series A without pretending to forecast too far out. | I7: Startup FP&A practice | J7: All tabs
A8: Control Panel | B8: Currency | C8: Text | D8: USD | E8: USD | F8: USD | G8: =_xlfn.XLOOKUP($G$5,$D$3:$F$3,D8:F8) -> USD | H8: Keeps model clean and consistent. | I8: Model design best practice | J8: All tabs
A9: Control Panel | B9: Company Type | C9: Text | D9: AI SaaS | E9: AI SaaS | F9: AI SaaS | G9: =_xlfn.XLOOKUP($G$5,$D$3:$F$3,D9:F9) -> AI SaaS | H9: LaunchPlan AI is an AI-native B2B SaaS company. | I9: Project setup | J9: All tabs
A10: Control Panel | B10: Business Model | C10: Text | D10: Freemium+SaaS+Usage | E10: Freemium+SaaS+Usage | F10: Freemium+SaaS+Usage | G10: =_xlfn.XLOOKUP($G$5,$D$3:$F$3,D10:F10) -> Freemium+SaaS+Usage | H10: Combines Product-led-growth (PLG) acquisition, subscription, and usage-based AI monetization. | I10: AI SaaS / PLG model | J10: Revenue, Unit Economics
A11: § 2 STARTING METRICS
A12: Starting Metrics | B12: Beginning Cash Balance ($) | C12: $ | D12: 1500000 | E12: 1500000 | F12: 1500000 | G12: =_xlfn.XLOOKUP($G$5,$D$3:$F$3,D12:F12) -> 1500000 | H12: Assumes LaunchPlan AI has closed a pre-seed or seed round of ~$1.5M (angel / pre-seed vehicle). | I12: Startup runway practice | J12: Cash, Runway
A13: Starting Metrics | B13: Seed Round Source | C13: Text | D13: Pre-seed/Angel | E13: Pre-seed/Angel | F13: Pre-seed/Angel | G13: =_xlfn.XLOOKUP($G$5,$D$3:$F$3,D13:F13) -> Pre-seed/Angel | H13: NEW: Provides context for starting cash balance. Avoids the cash balance appearing arbitrary. | I13: Startup funding context | J13: Cash, Memo
A14: Starting Metrics | B14: Starting Free Users | C14: Users | D14: 1500 | E14: 2000 | F14: 3000 | G14: =_xlfn.XLOOKUP($G$5,$D$3:$F$3,D14:F14) -> 2000 | H14: Free users create top-of-funnel for PLG conversion. | I14: Freemium SaaS model | J14: Revenue
A15: Starting Metrics | B15: Starting Starter Customers | C15: Customers | D15: 250 | E15: 300 | F15: 400 | G15: =_xlfn.XLOOKUP($G$5,$D$3:$F$3,D15:F15) -> 300 | H15: Starter is the first paid self-serve plan. | I15: Internal model assumption | J15: Revenue
A16: Starting Metrics | B16: Starting Growth Customers | C16: Customers | D16: 140 | E16: 180 | F16: 230 | G16: =_xlfn.XLOOKUP($G$5,$D$3:$F$3,D16:F16) -> 180 | H16: Growth plan is the core early paid customer segment. | I16: Internal model assumption | J16: Revenue
A17: Starting Metrics | B17: Starting Enterprise Customers | C17: Customers | D17: 0 | E17: 0 | F17: 0 | G17: =_xlfn.XLOOKUP($G$5,$D$3:$F$3,D17:F17) -> 0 | H17: Enterprise motion starts after product maturity and initial sales hiring. | I17: Startup GTM logic | J17: Revenue
A18: Starting Metrics | B18: Starting Headcount (FTE) | C18: FTE | D18: 2 | E18: 2 | F18: 2 | G18: =_xlfn.XLOOKUP($G$5,$D$3:$F$3,D18:F18) -> 2 | H18: Founder-led start: CEO and CTO only. | I18: Startup operating practice | J18: Headcount, OpEx
A19: Starting Metrics | B19: Starting MRR ($) | C19: $ | D19: =D15*D23+D16*D24+D17*D25 -> 33110 | E19: =E15*E23+E16*E24+E17*E25 -> 41520 | F19: =F15*F23+F16*F24+F17*F25 -> 53870 | G19: =_xlfn.XLOOKUP($G$5,$D$3:$F$3,D19:F19) -> 41520 | H19: Formula: Starting customers × plan pricing. | I19: Model design best practice | J19: Revenue, ARR
A20: Starting Metrics | B20: Starting ARR ($) | C20: $ | D20: =D19*12 -> 397320 | E20: =E19*12 -> 498240 | F20: =F19*12 -> 646440 | G20: =_xlfn.XLOOKUP($G$5,$D$3:$F$3,D20:F20) -> 498240 | H20: Formula: MRR × 12. | I20: SaaS metric standard | J20: Dashboard
A21: § 3 PRICING & PACKAGING
A22: Pricing | B22: Free Plan Price ($/mo) | C22: $/month | D22: 0 | E22: 0 | F22: 0 | G22: =_xlfn.XLOOKUP($G$5,$D$3:$F$3,D22:F22) -> 0 | H22: Free tier drives PLG top-of-funnel. No direct revenue; acquisition vehicle only. | I22: PLG / freemium practice | J22: Revenue
A23: Pricing | B23: Starter Plan Price ($/mo) | C23: $/month | D23: 49 | E23: 49 | F23: 49 | G23: =_xlfn.XLOOKUP($G$5,$D$3:$F$3,D23:F23) -> 49 | H23: Low-friction founder plan. Price fixed across scenarios ; self-serve pricing should be stable. | I23: SaaS pricing logic | J23: Revenue
A24: Pricing | B24: Growth Plan Price ($/mo) | C24: $/month | D24: 149 | E24: 149 | F24: 149 | G24: =_xlfn.XLOOKUP($G$5,$D$3:$F$3,D24:F24) -> 149 | H24: Core plan for Seed/Series A teams needing recurring FP&A workflows. | I24: SaaS pricing logic | J24: Revenue
A25: Pricing | B25: Enterprise Plan Price ($/mo) | C25: $/month | D25: 499 | E25: 599 | F25: 799 | G25: =_xlfn.XLOOKUP($G$5,$D$3:$F$3,D25:F25) -> 599 | H25: Enterprise flexes because negotiated contracts allow discounting (bear) or premium pricing (bull). | I25: FP&A pricing comps | J25: Revenue
A26: Pricing | B26: Enterprise Implementation Fee ($/logo) | C26: $/logo | D26: 2000 | E26: 3000 | F26: 5000 | G26: =_xlfn.XLOOKUP($G$5,$D$3:$F$3,D26:F26) -> 3000 | H26: One-time onboarding fee for Enterprise setup, integrations, and finance workflow configuration. | I26: FP&A software practice | J26: Other Revenue
A27: Pricing | B27: Implementation Fee Recognition Period | C27: Months | D27: 3 | E27: 3 | F27: 3 | G27: =_xlfn.XLOOKUP($G$5,$D$3:$F$3,D27:F27) -> 3 | H27: Recognize over service delivery period per revenue recognition logic. | I27: Revenue recognition logic | J27: Other Revenue
A28: Pricing | B28: Implementation Fee Included in ARR? | C28: Yes/No | D28: No | E28: No | F28: No | G28: =_xlfn.XLOOKUP($G$5,$D$3:$F$3,D28:F28) -> No | H28: ARR = recurring only. Implementation fees are non-recurring and must be excluded. | I28: SaaS ARR standard | J28: ARR Check
A29: Pricing | B29: Annual Billing Discount | C29: % off monthly | D29: 0.1 | E29: 0.1 | F29: 0.1 | G29: =_xlfn.XLOOKUP($G$5,$D$3:$F$3,D29:F29) -> 0.1 | H29: Annual prepay discount improves cash collection. Standard SaaS practice. | I29: SaaS pricing practice | J29: Cash
A30: Pricing | B30: Annual Billing Mix (% of paid customers) | C30: % of paid | D30: 0.1 | E30: 0.2 | F30: 0.35 | G30: =_xlfn.XLOOKUP($G$5,$D$3:$F$3,D30:F30) -> 0.2 | H30: Bull: more customers commit annually → stronger cash runway. Bear: mostly monthly billing. | I30: SaaS cash collection logic | J30: Cash, Runway
A31: Pricing | B31: Enterprise Payment Terms | C31: Days | D31: 45 | E31: 30 | F31: 30 | G31: =_xlfn.XLOOKUP($G$5,$D$3:$F$3,D31:F31) -> 30 | H31: Enterprise invoices paid slower than self-serve credit card. Bear = slower AR collection. | I31: B2B SaaS practice | J31: Cash
A32: Pricing | B32: Payment Failure / Bad Debt (% of self-serve rev) | C32: % of rev | D32: 0.02 | E32: 0.01 | F32: 0.005 | G32: =_xlfn.XLOOKUP($G$5,$D$3:$F$3,D32:F32) -> 0.01 | H32: Early-stage SMB customers carry payment failure risk. Bear case higher due to weaker ICP fit. | I32: SMB SaaS risk logic | J32: Revenue, Cash
A33: § 4 AI USAGE REVENUE
A34: AI Usage Revenue | B34: AI Overage Price Per Query ($/query) | C34: $/query | D34: 0.08 | E34: 0.1 | F34: 0.15 | G34: =_xlfn.XLOOKUP($G$5,$D$3:$F$3,D34:F34) -> 0.1 | H34: Usage-based pricing captures heavy AI usage above plan limits. Bull = premium pricing. | I34: AI usage pricing logic | J34: Revenue
A35: AI Usage Revenue | B35: Free Plan ; Included Queries/mo | C35: Queries/month | D35: 50 | E35: 50 | F35: 50 | G35: =_xlfn.XLOOKUP($G$5,$D$3:$F$3,D35:F35) -> 50 | H35: Free tier is useful but tightly capped to limit compute cost and push upgrades. | I35: AI cost control logic | J35: Usage Model
A36: AI Usage Revenue | B36: Starter ; Included Queries/mo | C36: Queries/month | D36: 500 | E36: 500 | F36: 500 | G36: =_xlfn.XLOOKUP($G$5,$D$3:$F$3,D36:F36) -> 500 | H36: Supports light founder usage while pushing heavier users to Growth. | I36: Product packaging logic | J36: Usage Model
A37: AI Usage Revenue | B37: Growth ; Included Queries/mo | C37: Queries/month | D37: 2000 | E37: 2000 | F37: 2000 | G37: =_xlfn.XLOOKUP($G$5,$D$3:$F$3,D37:F37) -> 2000 | H37: Core FP&A users need more modeling and reporting prompts. | I37: Product packaging logic | J37: Usage Model
A38: AI Usage Revenue | B38: Enterprise ; Included Queries/mo | C38: Queries/month | D38: 10000 | E38: 12000 | F38: 15000 | G38: =_xlfn.XLOOKUP($G$5,$D$3:$F$3,D38:F38) -> 12000 | H38: Larger teams receive higher usage allowance. Enterprise includes team-wide access. | I38: Enterprise SaaS logic | J38: Usage Model
A39: AI Usage Revenue | B39: AI Usage Revenue Start Month | C39: Month | D39: 14 | E39: 10 | F39: 7 | G39: =_xlfn.XLOOKUP($G$5,$D$3:$F$3,D39:F39) -> 10 | H39: Bull: users hit plan limits earlier due to deeper adoption. Bear: lighter usage depth. | I39: AI adoption logic | J39: Revenue
A40: AI Usage Revenue | B40: Avg Queries Per Active User ; M1 | C40: Queries/month | D40: 40 | E40: 50 | F40: 60 | G40: =_xlfn.XLOOKUP($G$5,$D$3:$F$3,D40:F40) -> 50 | H40: Early usage starts modestly while FP&A workflows are still forming. | I40: Internal usage assumption | J40: Usage Model
A41: AI Usage Revenue | B41: Avg Queries Per Active User ; M24 | C41: Queries/month | D41: 100 | E41: 150 | F41: 220 | G41: =_xlfn.XLOOKUP($G$5,$D$3:$F$3,D41:F41) -> 150 | H41: Usage grows as product embeds in budgeting, board reporting, and scenario planning. | I41: AI workflow adoption logic | J41: Usage Model
A42: AI Usage Revenue | B42: Active Users Per Starter Customer | C42: Users | D42: 1 | E42: 1 | F42: 2 | G42: =_xlfn.XLOOKUP($G$5,$D$3:$F$3,D42:F42) -> 1 | H42: Starter = founder-led or very small teams. Bull = slightly larger founding team. | I42: Customer segment logic | J42: Usage Model
A43: AI Usage Revenue | B43: Active Users Per Growth Customer | C43: Users | D43: 2 | E43: 3 | F43: 4 | G43: =_xlfn.XLOOKUP($G$5,$D$3:$F$3,D43:F43) -> 3 | H43: Growth customers have more operators using the tool. | I43: Customer segment logic | J43: Usage Model
A44: AI Usage Revenue | B44: Active Users Per Enterprise Customer | C44: Users | D44: 5 | E44: 8 | F44: 12 | G44: =_xlfn.XLOOKUP($G$5,$D$3:$F$3,D44:F44) -> 8 | H44: Enterprise usage spans finance, founders, and department leads. | I44: Customer segment logic | J44: Usage Model
A45: AI Usage Revenue | B45: % Customers Exceeding Query Limit ; M24 | C45: % | D45: 0.1 | E45: 0.2 | F45: 0.3 | G45: =_xlfn.XLOOKUP($G$5,$D$3:$F$3,D45:F45) -> 0.2 | H45: Heavy users generate overage revenue. Bull assumes deeper adoption. | I45: Usage-based SaaS logic | J45: Revenue
... A47: AI Usage Revenue | B47: AI Usage Revenue as % of MRR by M18 | C47: % | D47: 0.08 | E47: 0.15 | F47: 0.22 | G47: =_xlfn.XLOOKUP($G$5,$D$3:$F$3,D47:F47) -> 0.15 | H47: Keeps usage revenue meaningful but not dominant. Crosscheck against overage formula output. | I47: AI monetization logic | J47: Revenue
A48: § 5 CUSTOMER ACQUISITION
A49: Acquisition | B49: New Free Users ; M1 | C49: Users/month | D49: 250 | E49: 400 | F49: 700 | G49: =_xlfn.XLOOKUP($G$5,$D$3:$F$3,D49:F49) -> 400 | H49: Top-of-funnel from content, founder communities, templates, and referrals. | I49: PLG logic | J49: Revenue
A50: Acquisition | B50: Free User Monthly Growth Rate (MoM) | C50: % MoM | D50: 0.05 | E50: 0.1 | F50: 0.18 | G50: =_xlfn.XLOOKUP($G$5,$D$3:$F$3,D50:F50) -> 0.1 | H50: Free user acquisition must grow over time to support the free-to-paid funnel. Without this assumption, free users remain fixed at Month 1 levels, limiting paid customer growth. | I50: PLG funnel logic | J50: Revenue
A51: Acquisition | B51: Free User Activation Rate | C51: % of new free users | D51: 0.25 | E51: 0.4 | F51: 0.55 | G51: =_xlfn.XLOOKUP($G$5,$D$3:$F$3,D51:F51) -> 0.4 | H51: Only activated users are eligible to convert to paid | J51: Revenue
A52: Acquisition | B52: Free User Decay Rate (dormancy) | C52: % monthly | D52: 0.25 | E52: 0.18 | F52: 0.12 | G52: =_xlfn.XLOOKUP($G$5,$D$3:$F$3,D52:F52) -> 0.18 | H52: Non-converting free users become inactive over time; prevents inflated free-user base. | I52: Freemium lifecycle logic | J52: Revenue
A53: Acquisition | B53: New Starter Logos ; M1 | C53: Customers/month | D53: 5 | E53: 8 | F53: 12 | G53: =_xlfn.XLOOKUP($G$5,$D$3:$F$3,D53:F53) -> 8 | H53: Self-serve Starter grows through Product-Led Growth (PLG) adoption. | I53: Internal model assumption | J53: Revenue
A54: Acquisition | B54: New Growth Logos ; M1 | C54: Customers/month | D54: 2 | E54: 4 | F54: 6 | G54: =_xlfn.XLOOKUP($G$5,$D$3:$F$3,D54:F54) -> 4 | H54: Growth plan reflects startups willing to pay for recurring FP&A workflows. | I54: Internal model assumption | J54: Revenue
A55: Acquisition | B55: New Enterprise Logos ; M6+ | C55: Customers/month | D55: 0.5 | E55: 1 | F55: 2 | G55: =_xlfn.XLOOKUP($G$5,$D$3:$F$3,D55:F55) -> 1 | H55: Enterprise acquisition starts after product maturity. Cannot start M1. | I55: B2B sales logic | J55: Revenue
A56: Acquisition | B56: Monthly New Logo Growth Rate (MoM) | C56: % | D56: 0.03 | E56: 0.07 | F56: 0.12 | G56: =_xlfn.XLOOKUP($G$5,$D$3:$F$3,D56:F56) -> 0.07 | H56: Bear = slow product-led growth; Base = strong but reasonable adoption; Bull = strong product-market fit (PMF) plus effective distribution. Growth compounds monthly. | I56: SaaS growth benchmarks ; ChartMogul | J56: Revenue
A57: Acquisition | B57: Enterprise Motion Start Month | C57: Month | D57: 7 | E57: 6 | F57: 6 | G57: =_xlfn.XLOOKUP($G$5,$D$3:$F$3,D57:F57) -> 6 | H57: Enterprise selling needs credible onboarding, security posture, and integrations. Not before M6. | I57: Startup GTM logic | J57: Revenue
A58: Acquisition | B58: Growth Plan Sales Cycle | C58: Days | D58: 30 | E58: 21 | F58: 14 | G58: =_xlfn.XLOOKUP($G$5,$D$3:$F$3,D58:F58) -> 21 | H58: Growth plan has lighter buying process. Bull = strong brand and self-service demos. | I58: B2B SaaS logic | J58: Revenue
A59: Acquisition | B59: Enterprise Sales Cycle | C59: Days | D59: 90 | E59: 60 | F59: 45 | G59: =_xlfn.XLOOKUP($G$5,$D$3:$F$3,D59:F59) -> 60 | H59: Enterprise requires demos, approval, onboarding negotiation, and security review. | I59: B2B sales practice | J59: Revenue
A60: Acquisition | B60: Inbound Lead-to-Customer Conversion | C60: % | D60: 0.03 | E60: 0.05 | F60: 0.08 | G60: =_xlfn.XLOOKUP($G$5,$D$3:$F$3,D60:F60) -> 0.05 | H60: Improves as content, brand, and PMF strengthen over 24 months. | I60: SaaS funnel logic | J60: CAC, Revenue
A61: Acquisition | B61: Paid Lead-to-Customer Conversion | C61: % | D61: 0.01 | E61: 0.02 | F61: 0.03 | G61: =_xlfn.XLOOKUP($G$5,$D$3:$F$3,D61:F61) -> 0.02 | H61: Paid traffic is colder. Lowest conversion channel. | I61: SaaS funnel logic | J61: CAC, Revenue
A62: Acquisition | B62: Outbound Lead-to-Customer Conversion | C62: % | D62: 0.02 | E62: 0.04 | F62: 0.06 | G62: =_xlfn.XLOOKUP($G$5,$D$3:$F$3,D62:F62) -> 0.04 | H62: Improves with cleaner ICP and stronger AE productivity. | I62: Sales-led SaaS logic | J62: CAC, Revenue
A63: § 6 CONVERSION, EXPANSION & NRR
A64: Conversion & Expansion | B64: Free-to-Starter Conversion | C64: % | D64: 0.02 | E64: 0.04 | F64: 0.06 | G64: =_xlfn.XLOOKUP($G$5,$D$3:$F$3,D64:F64) -> 0.04 | H64: Base case within strong freemium conversion range. Bull assumes better activation and onboarding. | I64: ChartMogul: 3-5% good, 8-12% great | J64: Revenue
A65: Conversion & Expansion | B65: Starter-to-Growth Monthly Upgrade Rate | C65: % monthly | D65: 0.01 | E65: 0.02 | F65: 0.03 | G65: =_xlfn.XLOOKUP($G$5,$D$3:$F$3,D65:F65) -> 0.02 | H65: Small customers upgrade as they hire, raise funding, and need better planning capabilities. | I65: SaaS expansion logic | J65: Expansion MRR
A66: Conversion & Expansion | B66: Growth-to-Enterprise Monthly Upgrade Rate | C66: % monthly | D66: 0.001 | E66: 0.0025 | F66: 0.005 | G66: =_xlfn.XLOOKUP($G$5,$D$3:$F$3,D66:F66) -> 0.0025 | H66: Most Enterprise comes via outbound, but some Growth customers graduate. Keep rate low. | I66: SaaS expansion logic | J66: Expansion MRR
A67: Conversion & Expansion | B67: Expansion MRR Start Month | C67: Month | D67: 8 | E67: 6 | F67: 5 | G67: =_xlfn.XLOOKUP($G$5,$D$3:$F$3,D67:F67) -> 6 | H67: Expansion should only begin after customers experience recurring product value. | I67: SaaS lifecycle logic | J67: Revenue
A68: Conversion & Expansion | B68: Contraction MRR Rate (monthly) | C68: % monthly | D68: 0.02 | E68: 0.01 | F68: 0.005 | G68: =_xlfn.XLOOKUP($G$5,$D$3:$F$3,D68:F68) -> 0.01 | H68: Captures downgrades, seat reductions, and usage contractions. Separate from full churn. | I68: SaaS retention logic | J68: Revenue
A69: Conversion & Expansion | B69: Expansion MRR as % of Prior MRR ; M24 | C69: % | D69: 0.03 | E69: 0.06 | F69: 0.1 | G69: =_xlfn.XLOOKUP($G$5,$D$3:$F$3,D69:F69) -> 0.06 | H69: Bull case has stronger upsell and usage expansion. This crosschecks the NRR formula. | I69: NRR logic | J69: Revenue
A70: Conversion & Expansion | B70: Logo Churn vs. Revenue Churn Delta | C70: % points | D70: 0.015 | E70: 0.01 | F70: 0.005 | G70: =_xlfn.XLOOKUP($G$5,$D$3:$F$3,D70:F70) -> 0.01 | H70: Revenue churn is typically lower than logo churn because larger customers retain better. Model logo churn and revenue churn separately. Delta = revenue churn is this many points lower than logo churn. | I70: SaaS retention sophistication | J70: Unit Economics, Dashboard
A71: Conversion & Expansion | B71: NRR Target ; M24 | C71: % | D71: 0.85 | E71: 1.05 | F71: 1.2 | G71: =_xlfn.XLOOKUP($G$5,$D$3:$F$3,D71:F71) -> 1.05 | H71: Bear: expansion fails to offset churn. Base: healthy SaaS. Bull: best-in-class expansion revenue. | I71: ChartMogul NRR benchmarks | J71: Dashboard
A72: § 7 CHURN & RETENTION
A73: Churn & Retention | B73: Starter Monthly Churn | C73: % | D73: 0.06 | E73: 0.04 | F73: 0.025 | G73: =_xlfn.XLOOKUP($G$5,$D$3:$F$3,D73:F73) -> 0.04 | H73: Starter customers are small startups with high failure, pivot, and budget risk. | I73: ChartMogul churn benchmarks | J73: Revenue, LTV
A74: Churn & Retention | B74: Growth Monthly Churn | C74: % | D74: 0.04 | E74: 0.025 | F74: 0.015 | G74: =_xlfn.XLOOKUP($G$5,$D$3:$F$3,D74:F74) -> 0.025 | H74: Growth customers are more committed and have deeper workflow adoption. | I74: ChartMogul churn benchmarks | J74: Revenue, LTV
A75: Churn & Retention | B75: Enterprise Annual Churn | C75: % | D75: 0.25 | E75: 0.15 | F75: 0.08 | G75: =_xlfn.XLOOKUP($G$5,$D$3:$F$3,D75:F75) -> 0.15 | H75: Enterprise retains better but startup buyers still carry company-failure risk. | I75: SaaS retention logic | J75: Revenue
A76: Churn & Retention | B76: Enterprise Monthly Churn (converted) | C76: % monthly | D76: =1-(1-D75)^(1/12) -> 0.023688424 | E76: =1-(1-E75)^(1/12) -> 0.013451947 | F76: =1-(1-F75)^(1/12) -> 0.0069243826 | G76: =_xlfn.XLOOKUP($G$5,$D$3:$F$3,D76:F76) -> 0.013451947 | H76: Formula: =1-(1-Annual_Churn)^(1/12). | I76: SaaS formula | J76: Revenue
A77: Churn & Retention | B77: Blended Monthly Churn | C77: % | D77: 0.05 | E77: 0.03 | F77: 0.018 | G77: =_xlfn.XLOOKUP($G$5,$D$3:$F$3,D77:F77) -> 0.03 | H77: Weighted average across plans. Used for summary LTV and scenario-level checks. | I77: SaaS churn logic | J77: Unit Economics
A78: Churn & Retention | B78: Churn Start Month | C78: Month | D78: 2 | E78: 2 | F78: 2 | G78: =_xlfn.XLOOKUP($G$5,$D$3:$F$3,D78:F78) -> 2 | H78: Avoids unrealistic churn in month 1. First customers have grace period. | I78: Model design logic | J78: Revenue
A79: Churn & Retention | B79: Free User Dormancy Rate | C79: % monthly | D79: =+D52 -> 0.25 | E79: =+E52 -> 0.18 | F79: =+F52 -> 0.12 | G79: =_xlfn.XLOOKUP($G$5,$D$3:$F$3,D79:F79) -> 0.18 | H79: Free users who don't convert within 60-90 days go dormant. Already captured in Acquisition section. | I79: Freemium lifecycle logic | J79: Revenue
A80: § 8 COGS & GROSS MARGIN
A81: COGS & Gross Margin | B81: AI API Cost % of AI Revenue ; M1 | C81: % | D81: 0.45 | E81: 0.35 | F81: 0.28 | G81: =_xlfn.XLOOKUP($G$5,$D$3:$F$3,D81:F81) -> 0.35 | H81: Early AI costs are high: unoptimized prompts, low scale, no committed spend discounts. | I81: Bessemer AI margin research | J81: COGS
A82: COGS & Gross Margin | B82: AI API Cost % of AI Revenue ; M24 | C82: % | D82: 0.35 | E82: 0.25 | F82: 0.2 | G82: =_xlfn.XLOOKUP($G$5,$D$3:$F$3,D82:F82) -> 0.25 | H82: Improves via prompt engineering, caching, model routing, and volume pricing (Anthropic/OpenAI). | I82: Bessemer AI margin research | J82: COGS
A83: COGS & Gross Margin | B83: Cloud Hosting ; Per Customer/mo | C83: $/customer/month | D83: 8 | E83: 6 | F83: 5 | G83: =_xlfn.XLOOKUP($G$5,$D$3:$F$3,D83:F83) -> 6 | H83: Bear: weaker infrastructure efficiency. Bull: reserved instances and architecture optimization. | I83: SaaS infrastructure logic | J83: COGS
A84: COGS & Gross Margin | B84: Cloud Hosting ; Fixed Platform Cost/mo | C84: $/month | D84: 2500 | E84: 2000 | F84: 1500 | G84: =_xlfn.XLOOKUP($G$5,$D$3:$F$3,D84:F84) -> 2000 | H84: Base platform cost before customer-level scaling, including Content Delivery Network (CDN), databases, and baseline compute infrastructure. | I84: SaaS infrastructure logic | J84: COGS
A85: COGS & Gross Margin | B85: Payment Processing Fee (% of card revenue) | C85: % | D85: 0.029 | E85: 0.029 | F85: 0.029 | G85: =_xlfn.XLOOKUP($G$5,$D$3:$F$3,D85:F85) -> 0.029 | H85: Stripe / card processor fee. Fixed % of self-serve revenue. Always in COGS. | I85: Payments practice | J85: COGS
A86: COGS & Gross Margin | B86: Support Tool Cost ($/customer/mo) | C86: $/customer/month | D86: 4 | E86: 3 | F86: 2 | G86: =_xlfn.XLOOKUP($G$5,$D$3:$F$3,D86:F86) -> 3 | H86: Intercom/Zendesk tooling scales with customer count. | I86: SaaS support logic | J86: COGS
A87: COGS & Gross Margin | B87: CS Hire Trigger (customers per CS FTE) | C87: Customers | D87: 60 | E87: 80 | F87: 100 | G87: =_xlfn.XLOOKUP($G$5,$D$3:$F$3,D87:F87) -> 80 | H87: Bear: higher churn needs more hand-holding → hire CS earlier. Bull: product is self-sufficient. Customer Success (CS) hiring is triggered based on customers per CS employee. Bear case assumes more support needs; Bull case assumes a more self-serve product. | I87: SaaS support model | J87: COGS, Hiring
A88: COGS & Gross Margin | B88: CS Fully Loaded Salary (annual) | C88: $/year | D88: 90000 | E88: 85000 | F88: 80000 | G88: =_xlfn.XLOOKUP($G$5,$D$3:$F$3,D88:F88) -> 85000 | H88: CS is 100% COGS ; customer-facing, variable cost. Never put CS in OpEx. | I88: SaaS gross margin logic | J88: COGS
A89: COGS & Gross Margin | B89: Implementation Cost Per Enterprise Logo | C89: $/logo | D89: 1500 | E89: 1200 | F89: 1000 | G89: =_xlfn.XLOOKUP($G$5,$D$3:$F$3,D89:F89) -> 1200 | H89: Onboarding labor and setup burden. Bull: repeatable playbook lowers cost. | I89: Enterprise SaaS logic | J89: COGS
A90: COGS & Gross Margin | B90: Implementation Hours Per Enterprise Logo | C90: Hours | D90: 20 | E90: 15 | F90: 10 | G90: =_xlfn.XLOOKUP($G$5,$D$3:$F$3,D90:F90) -> 15 | H90: Bull: more repeatable implementation. Bear: custom work per customer. | I90: Enterprise SaaS logic | J90: COGS
A91: COGS & Gross Margin | B91: Target Gross Margin ; M6 | C91: % | D91: 0.58 | E91: 0.63 | F91: 0.68 | G91: =_xlfn.XLOOKUP($G$5,$D$3:$F$3,D91:F91) -> 0.63 | H91: AI SaaS starts lower due to early compute costs and underoptimized prompts. | I91: Bessemer AI SaaS benchmarks | J91: Dashboard
A92: COGS & Gross Margin | B92: Target Gross Margin ; M24 | C92: % | D92: 0.68 | E92: 0.74 | F92: 0.78 | G92: =_xlfn.XLOOKUP($G$5,$D$3:$F$3,D92:F92) -> 0.74 | H92: Margin expands as AI cost compresses. Traditional SaaS = 80-90%; AI SaaS closer to 70-80% at maturity. | I92: Bessemer AI SaaS benchmarks | J92: Dashboard
A93: § 9 CAC & GTM
A94: CAC & GTM | B94: Inbound / PLG CAC | C94: $/customer | D94: 600 | E94: 500 | F94: 400 | G94: =_xlfn.XLOOKUP($G$5,$D$3:$F$3,D94:F94) -> 500 | H94: PLG is lowest-cost channel. Users self-educate before any sales touch. | I94: SaaS GTM logic | J94: Unit Economics
A95: CAC & GTM | B95: Paid Marketing CAC | C95: $/customer | D95: 2000 | E95: 1600 | F95: 1200 | G95: =_xlfn.XLOOKUP($G$5,$D$3:$F$3,D95:F95) -> 1600 | H95: Paid marketing is scalable but less efficient than organic because higher ad costs and lower conversion rates increase customer acquisition cost. cost per 1,000 ad impressions | I95: SaaS GTM logic | J95: Unit Economics
A96: CAC & GTM | B96: Outbound / AE CAC | C96: $/customer | D96: 5000 | E96: 4500 | F96: 3000 | G96: =_xlfn.XLOOKUP($G$5,$D$3:$F$3,D96:F96) -> 4500 | H96: Outbound sales through Account Executives (AE) is expensive, but it can be justified because Enterprise customers generate higher average revenue and usually stay longer. The model also needs to account for how long new AEs take to become fully productive. | I96: Sales-led SaaS logic | J96: Unit Economics
A97: CAC & GTM | B97: Blended CAC ; M12 | C97: $/customer | D97: 2500 | E97: 1800 | F97: 1200 | G97: =_xlfn.XLOOKUP($G$5,$D$3:$F$3,D97:F97) -> 1800 | H97: Weighted average across channels. Base case ~$1,800 is the hiring gate reference point. | I97: CAC model logic | J97: Unit Economics
A98: CAC & GTM | B98: Paid Marketing Spend ; M1 | C98: $/month | D98: 3000 | E98: 5000 | F98: 8000 | G98: =_xlfn.XLOOKUP($G$5,$D$3:$F$3,D98:F98) -> 5000 | H98: Controlled early spend before proving channel efficiency. | I98: Startup GTM logic | J98: OpEx, CAC
A99: CAC & GTM | B99: Paid Marketing Spend ; M24 | C99: $/month | D99: 10000 | E99: 20000 | F99: 35000 | G99: =_xlfn.XLOOKUP($G$5,$D$3:$F$3,D99:F99) -> 20000 | H99: Scales with confidence in CAC and conversion quality. | I99: Startup GTM logic | J99: OpEx, CAC
A100: CAC & GTM | B100: Paid Marketing Multiplier (scenario lever) | C100: x | D100: 0.7 | E100: 1 | F100: 1.5 | G100: =_xlfn.XLOOKUP($G$5,$D$3:$F$3,D100:F100) -> 1 | H100: Single multiplier adjusts paid spend across scenarios without adding rows. | I100: Scenario logic | J100: Revenue
A101: CAC & GTM | B101: Sales Tools Cost Per Sales Rep/mo | C101: $/rep/month | D101: 250 | E101: 300 | F101: 350 | G101: =_xlfn.XLOOKUP($G$5,$D$3:$F$3,D101:F101) -> 300 | H101: CRM, enrichment, outbound sequencing tools (HubSpot, Apollo, etc.). | I101: SaaS sales stack logic | J101: OpEx
...

Sheet 2. Dashboard
J1: LaunchPlanAI Operating Dashboard
A3: Founder Recommendation: Base case supports disciplined GTM and product investment. CAC payback remains inside the hiring gate, gross margin trends toward the target, and runway remains manageable after planned financing. Management should continue hiring selectively, monitor burn and churn closely, and begin fundraising preparation before runway falls below the threshold.
A5: ARR | H5: MRR Growth | O5: Monthly Burn | V5: Cash & Runway
A6: Current ARR and MoM movement | H6: Net new MRR movement | O6: Net cash outflow per month | V6: Cash balance and runway months
A7: =(+'3. Revenue Model'!AA94)/10^6 -> 2.1785868 | H7: =+'3. Revenue Model'!AA97 -> 0.081935207 | L7: =(+'3. Revenue Model'!AA91-'3. Revenue Model'!Z91) -> 13748.741 | O7: =+'7. P&L + cash'!AA81 -> 36838.148 | V7: =+'7. P&L + cash'!AA84 -> 5026732 | Z7: =+'7. P&L + cash'!AA85 -> 136.45453
V10: Financing assumed in Month 23
A15: Gross Margin % | H15: CAC Payback | O15: Headcount by Dept | V15: Fundraising Trigger
A16: Revenue less COGS efficiency | H16: Blended payback in months | O16: Team composition by function | V16: Traffic-light financing signal
A17: =+'7. P&L + cash'!AA37 -> 0.73694968 | H17: =+'6. Unit Economics'!Y61 -> 10.547331 | O17: =+'4. Headcount'!AA64 -> 13 | V17: =IF(Z7<6,"RED",IF(Z7<=12,"AMBER","GREEN")) -> GREEN | Z17: {=_xlfn.SWITCH(V17,"GREEN","Safe: no fundraising action needed","AMBER","Start investor conversations","RED","Raise now","")} -> Safe: no fundraising action needed
O20: R&D | R20: =+'4. Headcount'!AA59 -> 5
O21: Sales & Marketing | R21: =+'4. Headcount'!AA60 -> 4
O22: G&A | R22: =+'4. Headcount'!AA61 -> 2
O23: COGS / Customer Success | R23: =+'4. Headcount'!AA62 -> 2
A26: ARR Movement Bridge | I26: Runway Burn-down | O26: CAC Payback Trend | V26: Gross Margin Expansion | BF26: ARR Movement Bridge | BN26: ARR Movement Bridge | BT26: CAC Payback Trend | CA26: Gross Margin Expansion
BF27: Monthly bridge: new logo MRR + expansion MRR less churn | BN27: Cash balance by scenario with financing threshold overlay | BT27: Blended CAC payback improving against hiring-gate threshold | CA27: Gross margin path showing AI cost leverage and optimization
BF28: Month | BG28: New Logo MRR | BH28: Expansion MRR | BI28: Churn | BJ28: Contraction | BK28: Net MRR Movement | BN28: Month | BO28: Ending Cash | BP28: 6-Month Cash Threshold | BU28: Month | BV28: CAC Payback | BW28: Target | CB28: Month | CC28: Gross Margin % | CD28: M24 Target
BF29: =ROWS($BF$29:BF29) -> 1 | BG29: {=(INDEX('7. P&L + cash'!$D$20:$AA$20,1,$BF29)+INDEX('3. Revenue Model'!$D$64:$AA$64,1,$BF29))*12} -> 30672 | BH29: {=INDEX('7. P&L + cash'!$D$21:$AA$21,1,$BF29)*12} -> 9630 | BI29: {=-INDEX('7. P&L + cash'!$D$23:$AA$23,1,$BF29)*12} -> 0 | BJ29: {=-INDEX('7. P&L + cash'!$D$22:$AA$22,1,$BF29)*12} -> -4982.4 | BK29: {=INDEX('7. P&L + cash'!$D$24:$AA$24,1,$BF29)*12} -> 35319.6 | BN29: =ROWS($BN$29:BN29) -> 1 | BO29: {=INDEX('7. P&L + cash'!$D$84:$AA$84,1,$BN29)} -> 1512335.5 | BP29: {=MAX(0,INDEX('7. P&L + cash'!$D$81:$AA$81,1,$BN29)*6)} -> 0 | BU29: =ROWS($BU$29:BU29) -> 1 | BV29: {=INDEX('6. Unit Economics'!$B$61:$Y$61,1,$BU29)} -> 8.624653 | BW29: ='1. Assumptions'!$G$109 -> 12 | CB29: =ROWS($CB$29:CB29) -> 1 | CC29: {=INDEX('7. P&L + cash'!$D$37:$AA$37,1,$CB29)} -> 0.81985908 | CD29: ='1. Assumptions'!$G$92 -> 0.74
BF30: =ROWS($BF$29:BF30) -> 2 | BG30: {=(INDEX('7. P&L + cash'!$D$20:$AA$20,1,$BF30)+INDEX('3. Revenue Model'!$D$64:$AA$64,1,$BF30))*12} -> 31125.6 | BH30: {=INDEX('7. P&L + cash'!$D$21:$AA$21,1,$BF30)*12} -> 10574.925 | BI30: {=-INDEX('7. P&L + cash'!$D$23:$AA$23,1,$BF30)*12} -> -16372.077 | BJ30: {=-INDEX('7. P&L + cash'!$D$22:$AA$22,1,$BF30)*12} -> -5335.596 | BK30: {=INDEX('7. P&L + cash'!$D$24:$AA$24,1,$BF30)*12} -> 19992.852 | BN30: =ROWS($BN$29:BN30) -> 2 | BO30: {=INDEX('7. P&L + cash'!$D$84:$AA$84,1,$BN30)} -> 1508196.7 | BP30: {=MAX(0,INDEX('7. P&L + cash'!$D$81:$AA$81,1,$BN30)*6)} -> 24832.427 | BU30: =ROWS($BU$29:BU30) -> 2 | BV30: {=INDEX('6. Unit Economics'!$B$61:$Y$61,1,$BU30)} -> 8.8190809 | BW30: ='1. Assumptions'!$G$109 -> 12 | CB30: =ROWS($CB$29:CB30) -> 2 | CC30: {=INDEX('7. P&L + cash'!$D$37:$AA$37,1,$CB30)} -> 0.82012327 | CD30: ='1. Assumptions'!$G$92 -> 0.74
BF31: =ROWS($BF$29:BF31) -> 3 | BG31: {=(INDEX('7. P&L + cash'!$D$20:$AA$20,1,$BF31)+INDEX('3. Revenue Model'!$D$64:$AA$64,1,$BF31))*12} -> 32096.405 | BH31: {=INDEX('7. P&L + cash'!$D$21:$AA$21,1,$BF31)*12} -> 11129.635 | BI31: {=-INDEX('7. P&L + cash'!$D$23:$AA$23,1,$BF31)*12} -> -17141.797 | BJ31: {=-INDEX('7. P&L + cash'!$D$22:$AA$22,1,$BF31)*12} -> -5535.5245 | BK31: {=INDEX('7. P&L + cash'!$D$24:$AA$24,1,$BF31)*12} -> 20548.718 | BN31: =ROWS($BN$29:BN31) -> 3 | BO31: {=INDEX('7. P&L + cash'!$D$84:$AA$84,1,$BN31)} -> 1490023.8 | BP31: {=MAX(0,INDEX('7. P&L + cash'!$D$81:$AA$81,1,$BN31)*6)} -> 109037.83 | BU31: =ROWS($BU$29:BU31) -> 3 | BV31: {=INDEX('6. Unit Economics'!$B$61:$Y$61,1,$BU31)} -> 8.975294 | BW31: ='1. Assumptions'!$G$109 -> 12 | CB31: =ROWS($CB$29:CB31) -> 3 | CC31: {=INDEX('7. P&L + cash'!$D$37:$AA$37,1,$CB31)} -> 0.82048996 | CD31: ='1. Assumptions'!$G$92 -> 0.74
BF32: =ROWS($BF$29:BF32) -> 4 | BG32: {=(INDEX('7. P&L + cash'!$D$20:$AA$20,1,$BF32)+INDEX('3. Revenue Model'!$D$64:$AA$64,1,$BF32))*12} -> 33525.109 | BH32: {=INDEX('7. P&L + cash'!$D$21:$AA$21,1,$BF32)*12} -> 11680.755 | BI32: {=-INDEX('7. P&L + cash'!$D$23:$AA$23,1,$BF32)*12} -> -17925.748 | BJ32: {=-INDEX('7. P&L + cash'!$D$22:$AA$22,1,$BF32)*12} -> -5741.0117 | BK32: {=INDEX('7. P&L + cash'!$D$24:$AA$24,1,$BF32)*12} -> 21539.105 | BN32: =ROWS($BN$29:BN32) -> 4 | BO32: {=INDEX('7. P&L + cash'!$D$84:$AA$84,1,$BN32)} -> 1457902.1 | BP32: {=MAX(0,INDEX('7. P&L + cash'!$D$81:$AA$81,1,$BN32)*6)} -> 192730.07 | BU32: =ROWS($BU$29:BU32) -> 4 | BV32: {=INDEX('6. Unit Economics'!$B$61:$Y$61,1,$BU32)} -> 9.1004172 | BW32: ='1. Assumptions'!$G$109 -> 12 | CB32: =ROWS($CB$29:CB32) -> 4 | CC32: {=INDEX('7. P&L + cash'!$D$37:$AA$37,1,$CB32)} -> 0.82092287 | CD32: ='1. Assumptions'!$G$92 -> 0.74
BF33: =ROWS($BF$29:BF33) -> 5 | BG33: {=(INDEX('7. P&L + cash'!$D$20:$AA$20,1,$BF33)+INDEX('3. Revenue Model'!$D$64:$AA$64,1,$BF33))*12} -> 35370.396 | BH33: {=INDEX('7. P&L + cash'!$D$21:$AA$21,1,$BF33)*12} -> 12246.06 | BI33: {=-INDEX('7. P&L + cash'!$D$23:$AA$23,1,$BF33)*12} -> -18741.374 | BJ33: {=-INDEX('7. P&L + cash'!$D$22:$AA$22,1,$BF33)*12} -> -5956.4027 | BK33: {=INDEX('7. P&L + cash'!$D$24:$AA$24,1,$BF33)*12} -> 22918.678 | BN33: =ROWS($BN$29:BN33) -> 5 | BO33: {=INDEX('7. P&L + cash'!$D$84:$AA$84,1,$BN33)} -> 1416942.8 | BP33: {=MAX(0,INDEX('7. P&L + cash'!$D$81:$AA$81,1,$BN33)*6)} -> 245755.74 | BU33: =ROWS($BU$29:BU33) -> 5 | BV33: {=INDEX('6. Unit Economics'!$B$61:$Y$61,1,$BU33)} -> 9.2013773 | BW33: ='1. Assumptions'!$G$109 -> 12 | CB33: =ROWS($CB$29:CB33) -> 5 | CC33: {=INDEX('7. P&L + cash'!$D$37:$AA$37,1,$CB33)} -> 0.82139574 | CD33: ='1. Assumptions'!$G$92 -> 0.74
BF34: =ROWS($BF$29:BF34) -> 6 | BG34: {=(INDEX('7. P&L + cash'!$D$20:$AA$20,1,$BF34)+INDEX('3. Revenue Model'!$D$64:$AA$64,1,$BF34))*12} -> 44793.441 | BH34: {=INDEX('7. P&L + cash'!$D$21:$AA$21,1,$BF34)*12} -> 12840.678 | BI34: {=-INDEX('7. P&L + cash'!$D$23:$AA$23,1,$BF34)*12} -> -19604.047 | BJ34: {=-INDEX('7. P&L + cash'!$D$22:$AA$22,1,$BF34)*12} -> -6185.5895 | BK34: {=INDEX('7. P&L + cash'!$D$24:$AA$24,1,$BF34)*12} -> 31844.483 | BN34: =ROWS($BN$29:BN34) -> 6 | BO34: {=INDEX('7. P&L + cash'!$D$84:$AA$84,1,$BN34)} -> 1361562.3 | BP34: {=MAX(0,INDEX('7. P&L + cash'!$D$81:$AA$81,1,$BN34)*6)} -> 332282.81 | BU34: =ROWS($BU$29:BU34) -> 6 | BV34: {=INDEX('6. Unit Economics'!$B$61:$Y$61,1,$BU34)} -> 10.30437 | BW34: ='1. Assumptions'!$G$109 -> 12 | CB34: =ROWS($CB$29:CB34) -> 6 | CC34: {=INDEX('7. P&L + cash'!$D$37:$AA$37,1,$CB34)} -> 0.81963945 | CD34: ='1. Assumptions'!$G$92 -> 0.74
BF35: =ROWS($BF$29:BF35) -> 7 | BG35: {=(INDEX('7. P&L + cash'!$D$20:$AA$20,1,$BF35)+INDEX('3. Revenue Model'!$D$64:$AA$64,1,$BF35))*12} -> 47906.385 | BH35: {=INDEX('7. P&L + cash'!$D$21:$AA$21,1,$BF35)*12} -> 13477.82 | BI35: {=-INDEX('7. P&L + cash'!$D$23:$AA$23,1,$BF35)*12} -> -20624.376 | BJ35: {=-INDEX('7. P&L + cash'!$D$22:$AA$22,1,$BF35)*12} -> -6504.0344 | BK35: {=INDEX('7. P&L + cash'!$D$24:$AA$24,1,$BF35)*12} -> 34255.795 | BN35: =ROWS($BN$29:BN35) -> 7 | BO35: {=INDEX('7. P&L + cash'!$D$84:$AA$84,1,$BN35)} -> 1305944.4 | BP35: {=MAX(0,INDEX('7. P&L + cash'!$D$81:$AA$81,1,$BN35)*6)} -> 333707.25 | BU35: =ROWS($BU$29:BU35) -> 7 | BV35: {=INDEX('6. Unit Economics'!$B$61:$Y$61,1,$BU35)} -> 10.315445 | BW35: ='1. Assumptions'!$G$109 -> 12 | CB35: =ROWS($CB$29:CB35) -> 7 | CC35: {=INDEX('7. P&L + cash'!$D$37:$AA$37,1,$CB35)} -> 0.81797357 | CD35: ='1. Assumptions'!$G$92 -> 0.74
BF36: =ROWS($BF$29:BF36) -> 8 | BG36: {=(INDEX('7. P&L + cash'!$D$20:$AA$20,1,$BF36)+INDEX('3. Revenue Model'!$D$64:$AA$64,1,$BF36))*12} -> 51424.026 | BH36: {=INDEX('7. P&L + cash'!$D$21:$AA$21,1,$BF36)*12} -> 14169.345 | BI36: {=-INDEX('7. P&L + cash'!$D$23:$AA$23,1,$BF36)*12} -> -21724.103 | BJ36: {=-INDEX('7. P&L + cash'!$D$22:$AA$22,1,$BF36)*12} -> -6846.5923 | BK36: {=INDEX('7. P&L + cash'!$D$24:$AA$24,1,$BF36)*12} -> 37022.675 | BN36: =ROWS($BN$29:BN36) -> 8 | BO36: {=INDEX('7. P&L + cash'!$D$84:$AA$84,1,$BN36)} -> 1244676.2 | BP36: {=MAX(0,INDEX('7. P&L + cash'!$D$81:$AA$81,1,$BN36)*6)} -> 367609.71 | BU36: =ROWS($BU$29:BU36) -> 8 | BV36: {=INDEX('6. Unit Economics'!$B$61:$Y$61,1,$BU36)} -> 12.392083 | BW36: ='1. Assumptions'!$G$109 -> 12 | CB36: =ROWS($CB$29:CB36) -> 8 | CC36: {=INDEX('7. P&L + cash'!$D$37:$AA$37,1,$CB36)} -> 0.67959487 | CD36: ='1. Assumptions'!$G$92 -> 0.74
BF37: =ROWS($BF$29:BF37) -> 9 | BG37: {=(INDEX('7. P&L + cash'!$D$20:$AA$20,1,$BF37)+INDEX('3. Revenue Model'!$D$64:$AA$64,1,$BF37))*12} -> 55351.782 | BH37: {=INDEX('7. P&L + cash'!$D$21:$AA$21,1,$BF37)*12} -> 14926.223 | BI37: {=-INDEX('7. P&L + cash'!$D$23:$AA$23,1,$BF37)*12} -> -22916.053 | BJ37: {=-INDEX('7. P&L + cash'!$D$22:$AA$22,1,$BF37)*12} -> -7216.8191 | BK37: {=INDEX('7. P&L + cash'!$D$24:$AA$24,1,$BF37)*12} -> 40145.133 | BN37: =ROWS($BN$29:BN37) -> 9 | BO37: {=INDEX('7. P&L + cash'!$D$84:$AA$84,1,$BN37)} -> 1172539.8 | BP37: {=MAX(0,INDEX('7. P&L + cash'!$D$81:$AA$81,1,$BN37)*6)} -> 432818.34 | BU37: =ROWS($BU$29:BU37) -> 9 | BV37: {=INDEX('6. Unit Economics'!$B$61:$Y$61,1,$BU37)} -> 12.200437 | BW37: ='1. Assumptions'!$G$109 -> 12 | CB37: =ROWS($CB$29:CB37) -> 9 | CC37: {=INDEX('7. P&L + cash'!$D$37:$AA$37,1,$CB37)} -> 0.68859869 | CD37: ='1. Assumptions'!$G$92 -> 0.74
BF38: =ROWS($BF$29:BF38) -> 10 | BG38: {=(INDEX('7. P&L + cash'!$D$20:$AA$20,1,$BF38)+INDEX('3. Revenue Model'!$D$64:$AA$64,1,$BF38))*12} -> 59702.306 | BH38: {=INDEX('7. P&L + cash'!$D$21:$AA$21,1,$BF38)*12} -> 15758.913 | BI38: {=-INDEX('7. P&L + cash'!$D$23:$AA$23,1,$BF38)*12} -> -24212.872 | BJ38: {=-INDEX('7. P&L + cash'!$D$22:$AA$22,1,$BF38)*12} -> -7618.2704 | BK38: {=INDEX('7. P&L + cash'!$D$24:$AA$24,1,$BF38)*12} -> 43630.076 | BN38: =ROWS($BN$29:BN38) -> 10 | BO38: {=INDEX('7. P&L + cash'!$D$84:$AA$84,1,$BN38)} -> 1090493.4 | BP38: {=MAX(0,INDEX('7. P&L + cash'!$D$81:$AA$81,1,$BN38)*6)} -> 492278.33 | BU38: =ROWS($BU$29:BU38) -> 10 | BV38: {=INDEX('6. Unit Economics'!$B$61:$Y$61,1,$BU38)} -> 11.968758 | BW38: ='1. Assumptions'!$G$109 -> 12 | CB38: =ROWS($CB$29:CB38) -> 10 | CC38: {=INDEX('7. P&L + cash'!$D$37:$AA$37,1,$CB38)} -> 0.6972596 | CD38: ='1. Assumptions'!$G$92 -> 0.74
BF39: =ROWS($BF$29:BF39) -> 11 | BG39: {=(INDEX('7. P&L + cash'!$D$20:$AA$20,1,$BF39)+INDEX('3. Revenue Model'!$D$64:$AA$64,1,$BF39))*12} -> 64494.672 | BH39: {=INDEX('7. P&L + cash'!$D$21:$AA$21,1,$BF39)*12} -> 16677.662 | BI39: {=-INDEX('7. P&L + cash'!$D$23:$AA$23,1,$BF39)*12} -> -25627.314 | BJ39: {=-INDEX('7. P&L + cash'!$D$22:$AA$22,1,$BF39)*12} -> -8054.5711 | BK39: {=INDEX('7. P&L + cash'!$D$24:$AA$24,1,$BF39)*12} -> 47490.449 | BN39: =ROWS($BN$29:BN39) -> 11 | BO39: {=INDEX('7. P&L + cash'!$D$84:$AA$84,1,$BN39)} -> 1011976.8 | BP39: {=MAX(0,INDEX('7. P&L + cash'!$D$81:$AA$81,1,$BN39)*6)} -> 471099.56 | BU39: =ROWS($BU$29:BU39) -> 11 | BV39: {=INDEX('6. Unit Economics'!$B$61:$Y$61,1,$BU39)} -> 11.749603 | BW39: ='1. Assumptions'!$G$109 -> 12 | CB39: =ROWS($CB$29:CB39) -> 11 | CC39: {=INDEX('7. P&L + cash'!$D$37:$AA$37,1,$CB39)} -> 0.70557352 | CD39: ='1. Assumptions'!$G$92 -> 0.74
BF40: =ROWS($BF$29:BF40) -> 12 | BG40: {=(INDEX('7. P&L + cash'!$D$20:$AA$20,1,$BF40)+INDEX('3. Revenue Model'!$D$64:$AA$64,1,$BF40))*12} -> 69753.801 | BH40: {=INDEX('7. P&L + cash'!$D$21:$AA$21,1,$BF40)*12} -> 17692.772 | BI40: {=-INDEX('7. P&L + cash'!$D$23:$AA$23,1,$BF40)*12} -> -27172.485 | BJ40: {=-INDEX('7. P&L + cash'!$D$22:$AA$22,1,$BF40)*12} -> -8529.4756 | BK40: {=INDEX('7. P&L + cash'!$D$24:$AA$24,1,$BF40)*12} -> 51744.612 | BN40: =ROWS($BN$29:BN40) -> 12 | BO40: {=INDEX('7. P&L + cash'!$D$84:$AA$84,1,$BN40)} -> 923184.26 | BP40: {=MAX(0,INDEX('7. P&L + cash'!$D$81:$AA$81,1,$BN40)*6)} -> 532755.13 | BU40: =ROWS($BU$29:BU40) -> 12 | BV40: {=INDEX('6. Unit Economics'!$B$61:$Y$61,1,$BU40)} -> 11.543814 | BW40: ='1. Assumptions'!$G$109 -> 12 | CB40: =ROWS($CB$29:CB40) -> 12 | CC40: {=INDEX('7. P&L + cash'!$D$37:$AA$37,1,$CB40)} -> 0.71353776 | CD40: ='1. Assumptions'!$G$92 -> 0.74
... BF43: =ROWS($BF$29:BF43) -> 15 | BG43: {=(INDEX('7. P&L + cash'!$D$20:$AA$20,1,$BF43)+INDEX('3. Revenue Model'!$D$64:$AA$64,1,$BF43))*12} -> 88662.238 | BH43: {=INDEX('7. P&L + cash'!$D$21:$AA$21,1,$BF43)*12} -> 21424.523 | BI43: {=-INDEX('7. P&L + cash'!$D$23:$AA$23,1,$BF43)*12} -> -32733.174 | BJ43: {=-INDEX('7. P&L + cash'!$D$22:$AA$22,1,$BF43)*12} -> -10226.406 | BK43: {=INDEX('7. P&L + cash'!$D$24:$AA$24,1,$BF43)*12} -> 67127.181 | BN43: =ROWS($BN$29:BN43) -> 15 | BO43: {=INDEX('7. P&L + cash'!$D$84:$AA$84,1,$BN43)} -> 652994.09 | BP43: {=MAX(0,INDEX('7. P&L + cash'!$D$81:$AA$81,1,$BN43)*6)} -> 538442.06 | BU43: =ROWS($BU$29:BU43) -> 15 | BV43: {=INDEX('6. Unit Economics'!$B$61:$Y$61,1,$BU43)} -> 11.005965 | BW43: ='1. Assumptions'!$G$109 -> 12 | CB43: =ROWS($CB$29:CB43) -> 15 | CC43: {=INDEX('7. P&L + cash'!$D$37:$AA$37,1,$CB43)} -> 0.73530847 | CD43: ='1. Assumptions'!$G$92 -> 0.74
U44: Gross margin path showing AI cost leverage and optimization | BF44: =ROWS($BF$29:BF44) -> 16 | BG44: {=(INDEX('7. P&L + cash'!$D$20:$AA$20,1,$BF44)+INDEX('3. Revenue Model'!$D$64:$AA$64,1,$BF44))*12} -> 96145.216 | BH44: {=INDEX('7. P&L + cash'!$D$21:$AA$21,1,$BF44)*12} -> 22936.361 | BI44: {=-INDEX('7. P&L + cash'!$D$23:$AA$23,1,$BF44)*12} -> -34946.631 | BJ44: {=-INDEX('7. P&L + cash'!$D$22:$AA$22,1,$BF44)*12} -> -10897.678 | BK44: {=INDEX('7. P&L + cash'!$D$24:$AA$24,1,$BF44)*12} -> 73237.268 | BN44: =ROWS($BN$29:BN44) -> 16 | BO44: {=INDEX('7. P&L + cash'!$D$84:$AA$84,1,$BN44)} -> 560318.8 | BP44: {=MAX(0,INDEX('7. P&L + cash'!$D$81:$AA$81,1,$BN44)*6)} -> 556051.78 | BU44: =ROWS($BU$29:BU44) -> 16 | BV44: {=INDEX('6. Unit Economics'!$B$61:$Y$61,1,$BU44)} -> 12.206202 | BW44: ='1. Assumptions'!$G$109 -> 12 | CB44: =ROWS($CB$29:CB44) -> 16 | CC44: {=INDEX('7. P&L + cash'!$D$37:$AA$37,1,$CB44)} -> 0.65950822 | CD44: ='1. Assumptions'!$G$92 -> 0.74
BF45: =ROWS($BF$29:BF45) -> 17 | BG45: {=(INDEX('7. P&L + cash'!$D$20:$AA$20,1,$BF45)+INDEX('3. Revenue Model'!$D$64:$AA$64,1,$BF45))*12} -> 104299.87 | BH45: {=INDEX('7. P&L + cash'!$D$21:$AA$21,1,$BF45)*12} -> 24603.805 | BI45: {=-INDEX('7. P&L + cash'!$D$23:$AA$23,1,$BF45)*12} -> -37368.695 | BJ45: {=-INDEX('7. P&L + cash'!$D$22:$AA$22,1,$BF45)*12} -> -11630.051 | BK45: {=INDEX('7. P&L + cash'!$D$24:$AA$24,1,$BF45)*12} -> 79904.928 | BN45: =ROWS($BN$29:BN45) -> 17 | BO45: {=INDEX('7. P&L + cash'!$D$84:$AA$84,1,$BN45)} -> 473952.43 | BP45: {=MAX(0,INDEX('7. P&L + cash'!$D$81:$AA$81,1,$BN45)*6)} -> 518198.18 | BU45: =ROWS($BU$29:BU45) -> 17 | BV45: {=INDEX('6. Unit Economics'!$B$61:$Y$61,1,$BU45)} -> 11.93168 | BW45: ='1. Assumptions'!$G$109 -> 12 | CB45: =ROWS($CB$29:CB45) -> 17 | CC45: {=INDEX('7. P&L + cash'!$D$37:$AA$37,1,$CB45)} -> 0.67130608 | CD45: ='1. Assumptions'!$G$92 -> 0.74
BF46: =ROWS($BF$29:BF46) -> 18 | BG46: {=(INDEX('7. P&L + cash'!$D$20:$AA$20,1,$BF46)+INDEX('3. Revenue Model'!$D$64:$AA$64,1,$BF46))*12} -> 113183.55 | BH46: {=INDEX('7. P&L + cash'!$D$21:$AA$21,1,$BF46)*12} -> 26441.429 | BI46: {=-INDEX('7. P&L + cash'!$D$23:$AA$23,1,$BF46)*12} -> -40018.678 | BJ46: {=-INDEX('7. P&L + cash'!$D$22:$AA$22,1,$BF46)*12} -> -12429.1 | BK46: {=INDEX('7. P&L + cash'!$D$24:$AA$24,1,$BF46)*12} -> 87177.204 | BN46: =ROWS($BN$29:BN46) -> 18 | BO46: {=INDEX('7. P&L + cash'!$D$84:$AA$84,1,$BN46)} -> 394527.59 | BP46: {=MAX(0,INDEX('7. P&L + cash'!$D$81:$AA$81,1,$BN46)*6)} -> 476549.02 | BU46: =ROWS($BU$29:BU46) -> 18 | BV46: {=INDEX('6. Unit Economics'!$B$61:$Y$61,1,$BU46)} -> 11.680603 | BW46: ='1. Assumptions'!$G$109 -> 12 | CB46: =ROWS($CB$29:CB46) -> 18 | CC46: {=INDEX('7. P&L + cash'!$D$37:$AA$37,1,$CB46)} -> 0.68247092 | CD46: ='1. Assumptions'!$G$92 -> 0.74
BF47: =ROWS($BF$29:BF47) -> 19 | BG47: {=(INDEX('7. P&L + cash'!$D$20:$AA$20,1,$BF47)+INDEX('3. Revenue Model'!$D$64:$AA$64,1,$BF47))*12} -> 122859.66 | BH47: {=INDEX('7. P&L + cash'!$D$21:$AA$21,1,$BF47)*12} -> 28465.075 | BI47: {=-INDEX('7. P&L + cash'!$D$23:$AA$23,1,$BF47)*12} -> -42917.555 | BJ47: {=-INDEX('7. P&L + cash'!$D$22:$AA$22,1,$BF47)*12} -> -13300.872 | BK47: {=INDEX('7. P&L + cash'!$D$24:$AA$24,1,$BF47)*12} -> 95106.305 | BN47: =ROWS($BN$29:BN47) -> 19 | BO47: {=INDEX('7. P&L + cash'!$D$84:$AA$84,1,$BN47)} -> 322737.38 | BP47: {=MAX(0,INDEX('7. P&L + cash'!$D$81:$AA$81,1,$BN47)*6)} -> 430741.29 | BU47: =ROWS($BU$29:BU47) -> 19 | BV47: {=INDEX('6. Unit Economics'!$B$61:$Y$61,1,$BU47)} -> 11.450576 | BW47: ='1. Assumptions'!$G$109 -> 12 | CB47: =ROWS($CB$29:CB47) -> 19 | CC47: {=INDEX('7. P&L + cash'!$D$37:$AA$37,1,$CB47)} -> 0.69301281 | CD47: ='1. Assumptions'!$G$92 -> 0.74
BF48: =ROWS($BF$29:BF48) -> 20 | BG48: {=(INDEX('7. P&L + cash'!$D$20:$AA$20,1,$BF48)+INDEX('3. Revenue Model'!$D$64:$AA$64,1,$BF48))*12} -> 133398 | BH48: {=INDEX('7. P&L + cash'!$D$21:$AA$21,1,$BF48)*12} -> 30692.018 | BI48: {=-INDEX('7. P&L + cash'!$D$23:$AA$23,1,$BF48)*12} -> -46088.153 | BJ48: {=-INDEX('7. P&L + cash'!$D$22:$AA$22,1,$BF48)*12} -> -14251.935 | BK48: {=INDEX('7. P&L + cash'!$D$24:$AA$24,1,$BF48)*12} -> 103749.93 | BN48: =ROWS($BN$29:BN48) -> 20 | BO48: {=INDEX('7. P&L + cash'!$D$84:$AA$84,1,$BN48)} -> 243174.39 | BP48: {=MAX(0,INDEX('7. P&L + cash'!$D$81:$AA$81,1,$BN48)*6)} -> 477377.93 | BU48: =ROWS($BU$29:BU48) -> 20 | BV48: {=INDEX('6. Unit Economics'!$B$61:$Y$61,1,$BU48)} -> 11.23943 | BW48: ='1. Assumptions'!$G$109 -> 12 | CB48: =ROWS($CB$29:CB48) -> 20 | CC48: {=INDEX('7. P&L + cash'!$D$37:$AA$37,1,$CB48)} -> 0.70294528 | CD48: ='1. Assumptions'!$G$92 -> 0.74
BF49: =ROWS($BF$29:BF49) -> 21 | BG49: {=(INDEX('7. P&L + cash'!$D$20:$AA$20,1,$BF49)+INDEX('3. Revenue Model'!$D$64:$AA$64,1,$BF49))*12} -> 144875.33 | BH49: {=INDEX('7. P&L + cash'!$D$21:$AA$21,1,$BF49)*12} -> 33141.131 | BI49: {=-INDEX('7. P&L + cash'!$D$23:$AA$23,1,$BF49)*12} -> -49555.353 | BJ49: {=-INDEX('7. P&L + cash'!$D$22:$AA$22,1,$BF49)*12} -> -15289.435 | BK49: {=INDEX('7. P&L + cash'!$D$24:$AA$24,1,$BF49)*12} -> 113171.67 | BN49: =ROWS($BN$29:BN49) -> 21 | BO49: {=INDEX('7. P&L + cash'!$D$84:$AA$84,1,$BN49)} -> 172837 | BP49: {=MAX(0,INDEX('7. P&L + cash'!$D$81:$AA$81,1,$BN49)*6)} -> 422024.32 | BU49: =ROWS($BU$29:BU49) -> 21 | BV49: {=INDEX('6. Unit Economics'!$B$61:$Y$61,1,$BU49)} -> 11.045204 | BW49: ='1. Assumptions'!$G$109 -> 12 | CB49: =ROWS($CB$29:CB49) -> 21 | CC49: {=INDEX('7. P&L + cash'!$D$37:$AA$37,1,$CB49)} -> 0.71228494 | CD49: ='1. Assumptions'!$G$92 -> 0.74
BF50: =ROWS($BF$29:BF50) -> 22 | BG50: {=(INDEX('7. P&L + cash'!$D$20:$AA$20,1,$BF50)+INDEX('3. Revenue Model'!$D$64:$AA$64,1,$BF50))*12} -> 157375.84 | BH50: {=INDEX('7. P&L + cash'!$D$21:$AA$21,1,$BF50)*12} -> 35833.06 | BI50: {=-INDEX('7. P&L + cash'!$D$23:$AA$23,1,$BF50)*12} -> -53346.306 | BJ50: {=-INDEX('7. P&L + cash'!$D$22:$AA$22,1,$BF50)*12} -> -16421.151 | BK50: {=INDEX('7. P&L + cash'!$D$24:$AA$24,1,$BF50)*12} -> 123441.45 | BN50: =ROWS($BN$29:BN50) -> 22 | BO50: {=INDEX('7. P&L + cash'!$D$84:$AA$84,1,$BN50)} -> 112636.26 | BP50: {=MAX(0,INDEX('7. P&L + cash'!$D$81:$AA$81,1,$BN50)*6)} -> 361204.45 | BU50: =ROWS($BU$29:BU50) -> 22 | BV50: {=INDEX('6. Unit Economics'!$B$61:$Y$61,1,$BU50)} -> 10.866137 | BW50: ='1. Assumptions'!$G$109 -> 12 | CB50: =ROWS($CB$29:CB50) -> 22 | CC50: {=INDEX('7. P&L + cash'!$D$37:$AA$37,1,$CB50)} -> 0.721051 | CD50: ='1. Assumptions'!$G$92 -> 0.74
BF51: =ROWS($BF$29:BF51) -> 23 | BG51: {=(INDEX('7. P&L + cash'!$D$20:$AA$20,1,$BF51)+INDEX('3. Revenue Model'!$D$64:$AA$64,1,$BF51))*12} -> 170991.87 | BH51: {=INDEX('7. P&L + cash'!$D$21:$AA$21,1,$BF51)*12} -> 38790.415 | BI51: {=-INDEX('7. P&L + cash'!$D$23:$AA$23,1,$BF51)*12} -> -57490.66 | BJ51: {=-INDEX('7. P&L + cash'!$D$22:$AA$22,1,$BF51)*12} -> -17655.566 | BK51: {=INDEX('7. P&L + cash'!$D$24:$AA$24,1,$BF51)*12} -> 134636.06 | BN51: =ROWS($BN$29:BN51) -> 23 | BO51: {=INDEX('7. P&L + cash'!$D$84:$AA$84,1,$BN51)} -> 5063570.2 | BP51: {=MAX(0,INDEX('7. P&L + cash'!$D$81:$AA$81,1,$BN51)*6)} -> 294396.62 | BU51: =ROWS($BU$29:BU51) -> 23 | BV51: {=INDEX('6. Unit Economics'!$B$61:$Y$61,1,$BU51)} -> 10.70065 | BW51: ='1. Assumptions'!$G$109 -> 12 | CB51: =ROWS($CB$29:CB51) -> 23 | CC51: {=INDEX('7. P&L + cash'!$D$37:$AA$37,1,$CB51)} -> 0.72926488 | CD51: ='1. Assumptions'!$G$92 -> 0.74
BF52: =ROWS($BF$29:BF52) -> 24 | BG52: {=(INDEX('7. P&L + cash'!$D$20:$AA$20,1,$BF52)+INDEX('3. Revenue Model'!$D$64:$AA$64,1,$BF52))*12} -> 185824.54 | BH52: {=INDEX('7. P&L + cash'!$D$21:$AA$21,1,$BF52)*12} -> 42037.973 | BI52: {=-INDEX('7. P&L + cash'!$D$23:$AA$23,1,$BF52)*12} -> -62020.818 | BJ52: {=-INDEX('7. P&L + cash'!$D$22:$AA$22,1,$BF52)*12} -> -19001.926 | BK52: {=INDEX('7. P&L + cash'!$D$24:$AA$24,1,$BF52)*12} -> 146839.77 | BN52: =ROWS($BN$29:BN52) -> 24 | BO52: {=INDEX('7. P&L + cash'!$D$84:$AA$84,1,$BN52)} -> 5026732 | BP52: {=MAX(0,INDEX('7. P&L + cash'!$D$81:$AA$81,1,$BN52)*6)} -> 221028.89 | BU52: =ROWS($BU$29:BU52) -> 24 | BV52: {=INDEX('6. Unit Economics'!$B$61:$Y$61,1,$BU52)} -> 10.547331 | BW52: ='1. Assumptions'!$G$109 -> 12 | CB52: =ROWS($CB$29:CB52) -> 24 | CC52: {=INDEX('7. P&L + cash'!$D$37:$AA$37,1,$CB52)} -> 0.73694968 | CD52: ='1. Assumptions'!$G$92 -> 0.74

Sheet 3. Revenue Model
A1: LaunchPlan AI: Revenue Model | F1: YELLOW = Hardcoded Input | G1: BLUE = Formula | H1: GREEN = Dashboard Output | I1: RED = Check / Warning
A2: Section | B2: Line Item | C2: Unit | D2: Month 1 | E2: Month 2 | F2: Month 3 | G2: Month 4 | H2: Month 5 | I2: Month 6 | J2: Month 7 | K2: Month 8 | L2: Month 9 | M2: Month 10 | N2: Month 11 | O2: Month 12 | P2: Month 13 | Q2: Month 14 | R2: Month 15 | S2: Month 16 | T2: Month 17 | U2: Month 18 | V2: Month 19 | W2: Month 20 | X2: Month 21 | Y2: Month 22 | Z2: Month 23 | AA2: Month 24 | AB2: Notes / Formula Logic | AC2: Check / Source
A3: § 1 CONTROL & TIMELINE
A4: Control | B4: Selected Scenario | C4: Text | D4: =INDEX('1. Assumptions'!$G:$G,MATCH("Selected Scenario",'1. Assumptions'!$B:$B,0)) -> Base | E4: =INDEX('1. Assumptions'!$G:$G,MATCH("Selected Scenario",'1. Assumptions'!$B:$B,0)) -> Base | F4: =INDEX('1. Assumptions'!$G:$G,MATCH("Selected Scenario",'1. Assumptions'!$B:$B,0)) -> Base | G4: =INDEX('1. Assumptions'!$G:$G,MATCH("Selected Scenario",'1. Assumptions'!$B:$B,0)) -> Base | H4: =INDEX('1. Assumptions'!$G:$G,MATCH("Selected Scenario",'1. Assumptions'!$B:$B,0)) -> Base | I4: =INDEX('1. Assumptions'!$G:$G,MATCH("Selected Scenario",'1. Assumptions'!$B:$B,0)) -> Base | J4: =INDEX('1. Assumptions'!$G:$G,MATCH("Selected Scenario",'1. Assumptions'!$B:$B,0)) -> Base | K4: =INDEX('1. Assumptions'!$G:$G,MATCH("Selected Scenario",'1. Assumptions'!$B:$B,0)) -> Base | ... AA4: =INDEX('1. Assumptions'!$G:$G,MATCH("Selected Scenario",'1. Assumptions'!$B:$B,0)) -> Base | AC4: Links from Assumptions tab Control Panel
A5: Timeline | B5: Month Number | C5: Month | D5: 1 | E5: =D5+1 -> 2 | F5: =E5+1 -> 3 | G5: =F5+1 -> 4 | H5: =G5+1 -> 5 | I5: =H5+1 -> 6 | J5: =I5+1 -> 7 | K5: =J5+1 -> 8 | L5: =K5+1 -> 9 | ... AA5: =Z5+1 -> 24
A6: Timeline | B6: Calendar Month | C6: Date | D6: =EDATE(INDEX('1. Assumptions'!$G:$G,MATCH("Start Date",'1. Assumptions'!$B:$B,0)),D5-1) -> 46023 | E6: =EDATE(INDEX('1. Assumptions'!$G:$G,MATCH("Start Date",'1. Assumptions'!$B:$B,0)),E5-1) -> 46054 | F6: =EDATE(INDEX('1. Assumptions'!$G:$G,MATCH("Start Date",'1. Assumptions'!$B:$B,0)),F5-1) -> 46082 | G6: =EDATE(INDEX('1. Assumptions'!$G:$G,MATCH("Start Date",'1. Assumptions'!$B:$B,0)),G5-1) -> 46113 | H6: =EDATE(INDEX('1. Assumptions'!$G:$G,MATCH("Start Date",'1. Assumptions'!$B:$B,0)),H5-1) -> 46143 | I6: =EDATE(INDEX('1. Assumptions'!$G:$G,MATCH("Start Date",'1. Assumptions'!$B:$B,0)),I5-1) -> 46174 | J6: =EDATE(INDEX('1. Assumptions'!$G:$G,MATCH("Start Date",'1. Assumptions'!$B:$B,0)),J5-1) -> 46204 | K6: =EDATE(INDEX('1. Assumptions'!$G:$G,MATCH("Start Date",'1. Assumptions'!$B:$B,0)),K5-1) -> 46235 | ... AA6: =EDATE(INDEX('1. Assumptions'!$G:$G,MATCH("Start Date",'1. Assumptions'!$B:$B,0)),AA5-1) -> 46722 | AC6: EDATE(Start_Date, MonthNum-1) — links to Assumptions Start Date
A8: § 2 FREE USER FUNNEL
A9: Free Funnel | B9: Beginning Active Free Users | C9: Users | D9: =INDEX('1. Assumptions'!$G:$G,MATCH("Starting Free Users",'1. Assumptions'!$B:$B,0))*INDEX('1. Assumptions'!$G:$G,MATCH("Free User Activation Rate",'1. Assumptions'!B:B,0)) -> 800 | E9: =D14 -> 784 | F9: =E14 -> 787.52 | G9: =F14 -> 807.8656 | H9: =G14 -> 843.09517 | I9: =H14 -> 891.87023 | J9: =I14 -> 953.34038 | K9: =J14 -> 1027.0553 | L9: =K14 -> 1112.8978 | ... AA9: =Z14 -> 4478.1404 | AC9: M1: Starting Free Users × Activation Rate; M2+: Prior Ending Active Free Users
A10: Free Funnel | B10: New Free Users | C10: Users | D10: =INDEX('1. Assumptions'!$G:$G,MATCH("New Free Users ; M1",'1. Assumptions'!$B:$B,0)) -> 400 | E10: =D10*(1+INDEX('1. Assumptions'!$G:$G,MATCH("Free User Monthly Growth Rate (MoM)",'1. Assumptions'!$B:$B,0))) -> 440 | F10: =E10*(1+INDEX('1. Assumptions'!$G:$G,MATCH("Free User Monthly Growth Rate (MoM)",'1. Assumptions'!$B:$B,0))) -> 484 | G10: =F10*(1+INDEX('1. Assumptions'!$G:$G,MATCH("Free User Monthly Growth Rate (MoM)",'1. Assumptions'!$B:$B,0))) -> 532.4 | H10: =G10*(1+INDEX('1. Assumptions'!$G:$G,MATCH("Free User Monthly Growth Rate (MoM)",'1. Assumptions'!$B:$B,0))) -> 585.64 | I10: =H10*(1+INDEX('1. Assumptions'!$G:$G,MATCH("Free User Monthly Growth Rate (MoM)",'1. Assumptions'!$B:$B,0))) -> 644.204 | J10: =I10*(1+INDEX('1. Assumptions'!$G:$G,MATCH("Free User Monthly Growth Rate (MoM)",'1. Assumptions'!$B:$B,0))) -> 708.6244 | K10: =J10*(1+INDEX('1. Assumptions'!$G:$G,MATCH("Free User Monthly Growth Rate (MoM)",'1. Assumptions'!$B:$B,0))) -> 779.48684 | L10: =K10*(1+INDEX('1. Assumptions'!$G:$G,MATCH("Free User Monthly Growth Rate (MoM)",'1. Assumptions'!$B:$B,0))) -> 857.43552 | ... AA10: =Z10*(1+INDEX('1. Assumptions'!$G:$G,MATCH("Free User Monthly Growth Rate (MoM)",'1. Assumptions'!$B:$B,0))) -> 3581.721 | AC10: XLOOKUP "New Free Users M1" × (1+Growth Rate) each month
A11: Free Funnel | B11: New Activated Free Users | C11: Users | D11: =D10*INDEX('1. Assumptions'!$G:$G,MATCH("Free User Activation Rate",'1. Assumptions'!$B:$B,0)) -> 160 | E11: =E10*INDEX('1. Assumptions'!$G:$G,MATCH("Free User Activation Rate",'1. Assumptions'!$B:$B,0)) -> 176 | F11: =F10*INDEX('1. Assumptions'!$G:$G,MATCH("Free User Activation Rate",'1. Assumptions'!$B:$B,0)) -> 193.6 | G11: =G10*INDEX('1. Assumptions'!$G:$G,MATCH("Free User Activation Rate",'1. Assumptions'!$B:$B,0)) -> 212.96 | H11: =H10*INDEX('1. Assumptions'!$G:$G,MATCH("Free User Activation Rate",'1. Assumptions'!$B:$B,0)) -> 234.256 | I11: =I10*INDEX('1. Assumptions'!$G:$G,MATCH("Free User Activation Rate",'1. Assumptions'!$B:$B,0)) -> 257.6816 | J11: =J10*INDEX('1. Assumptions'!$G:$G,MATCH("Free User Activation Rate",'1. Assumptions'!$B:$B,0)) -> 283.44976 | K11: =K10*INDEX('1. Assumptions'!$G:$G,MATCH("Free User Activation Rate",'1. Assumptions'!$B:$B,0)) -> 311.79474 | ... AA11: =AA10*INDEX('1. Assumptions'!$G:$G,MATCH("Free User Activation Rate",'1. Assumptions'!$B:$B,0)) -> 1432.6884
A12: Free Funnel | B12: Free-to-Starter Conversions | C12: Customers | D12: =D9*INDEX('1. Assumptions'!$G:$G,MATCH("Free-to-Starter Conversion",'1. Assumptions'!$B:$B,0)) -> 32 | E12: =E9*INDEX('1. Assumptions'!$G:$G,MATCH("Free-to-Starter Conversion",'1. Assumptions'!$B:$B,0)) -> 31.36 | F12: =F9*INDEX('1. Assumptions'!$G:$G,MATCH("Free-to-Starter Conversion",'1. Assumptions'!$B:$B,0)) -> 31.5008 | G12: =G9*INDEX('1. Assumptions'!$G:$G,MATCH("Free-to-Starter Conversion",'1. Assumptions'!$B:$B,0)) -> 32.314624 | H12: =H9*INDEX('1. Assumptions'!$G:$G,MATCH("Free-to-Starter Conversion",'1. Assumptions'!$B:$B,0)) -> 33.723807 | I12: =I9*INDEX('1. Assumptions'!$G:$G,MATCH("Free-to-Starter Conversion",'1. Assumptions'!$B:$B,0)) -> 35.674809 | J12: =J9*INDEX('1. Assumptions'!$G:$G,MATCH("Free-to-Starter Conversion",'1. Assumptions'!$B:$B,0)) -> 38.133615 | K12: =K9*INDEX('1. Assumptions'!$G:$G,MATCH("Free-to-Starter Conversion",'1. Assumptions'!$B:$B,0)) -> 41.08221 | ... AA12: =AA9*INDEX('1. Assumptions'!$G:$G,MATCH("Free-to-Starter Conversion",'1. Assumptions'!$B:$B,0)) -> 179.12562 | AC12: Only ACTIVE free users convert to paid — not total free users
A13: Free Funnel | B13: Dormant Free Users | C13: Users | D13: =D9*INDEX('1. Assumptions'!$G:$G,MATCH("Free User Decay Rate (dormancy)",'1. Assumptions'!$B:$B,0)) -> 144 | E13: =E9*INDEX('1. Assumptions'!$G:$G,MATCH("Free User Decay Rate (dormancy)",'1. Assumptions'!$B:$B,0)) -> 141.12 | F13: =F9*INDEX('1. Assumptions'!$G:$G,MATCH("Free User Decay Rate (dormancy)",'1. Assumptions'!$B:$B,0)) -> 141.7536 | G13: =G9*INDEX('1. Assumptions'!$G:$G,MATCH("Free User Decay Rate (dormancy)",'1. Assumptions'!$B:$B,0)) -> 145.41581 | H13: =H9*INDEX('1. Assumptions'!$G:$G,MATCH("Free User Decay Rate (dormancy)",'1. Assumptions'!$B:$B,0)) -> 151.75713 | I13: =I9*INDEX('1. Assumptions'!$G:$G,MATCH("Free User Decay Rate (dormancy)",'1. Assumptions'!$B:$B,0)) -> 160.53664 | J13: =J9*INDEX('1. Assumptions'!$G:$G,MATCH("Free User Decay Rate (dormancy)",'1. Assumptions'!$B:$B,0)) -> 171.60127 | K13: =K9*INDEX('1. Assumptions'!$G:$G,MATCH("Free User Decay Rate (dormancy)",'1. Assumptions'!$B:$B,0)) -> 184.86995 | ... AA13: =AA9*INDEX('1. Assumptions'!$G:$G,MATCH("Free User Decay Rate (dormancy)",'1. Assumptions'!$B:$B,0)) -> 806.06528
A14: Free Funnel | B14: Ending Active Free Users | C14: Users | D14: =D9+D11-D12-D13 -> 784 | E14: =E9+E11-E12-E13 -> 787.52 | F14: =F9+F11-F12-F13 -> 807.8656 | G14: =G9+G11-G12-G13 -> 843.09517 | H14: =H9+H11-H12-H13 -> 891.87023 | I14: =I9+I11-I12-I13 -> 953.34038 | J14: =J9+J11-J12-J13 -> 1027.0553 | K14: =K9+K11-K12-K13 -> 1112.8978 | ... AA14: =AA9+AA11-AA12-AA13 -> 4925.6379 | AC14: Beginning + New Activated - Free-to-Starter Conversions - Dormant
A16: § 3 NEW LOGO ACQUISITION
A17: Acquisition | B17: New Starter Logos – Direct/Self-Serve | C17: Customers | D17: =INDEX('1. Assumptions'!$G:$G,MATCH("New Starter Logos ; M1",'1. Assumptions'!$B:$B,0)) -> 8 | E17: =D17*(1+INDEX('1. Assumptions'!$G:$G,MATCH("Monthly New Logo Growth Rate (MoM)",'1. Assumptions'!$B:$B,0))) -> 8.56 | F17: =E17*(1+INDEX('1. Assumptions'!$G:$G,MATCH("Monthly New Logo Growth Rate (MoM)",'1. Assumptions'!$B:$B,0))) -> 9.1592 | G17: =F17*(1+INDEX('1. Assumptions'!$G:$G,MATCH("Monthly New Logo Growth Rate (MoM)",'1. Assumptions'!$B:$B,0))) -> 9.800344 | H17: =G17*(1+INDEX('1. Assumptions'!$G:$G,MATCH("Monthly New Logo Growth Rate (MoM)",'1. Assumptions'!$B:$B,0))) -> 10.486368 | I17: =H17*(1+INDEX('1. Assumptions'!$G:$G,MATCH("Monthly New Logo Growth Rate (MoM)",'1. Assumptions'!$B:$B,0))) -> 11.220414 | J17: =I17*(1+INDEX('1. Assumptions'!$G:$G,MATCH("Monthly New Logo Growth Rate (MoM)",'1. Assumptions'!$B:$B,0))) -> 12.005843 | K17: =J17*(1+INDEX('1. Assumptions'!$G:$G,MATCH("Monthly New Logo Growth Rate (MoM)",'1. Assumptions'!$B:$B,0))) -> 12.846252 | L17: =K17*(1+INDEX('1. Assumptions'!$G:$G,MATCH("Monthly New Logo Growth Rate (MoM)",'1. Assumptions'!$B:$B,0))) -> 13.745489 | ... AA17: =Z17*(1+INDEX('1. Assumptions'!$G:$G,MATCH("Monthly New Logo Growth Rate (MoM)",'1. Assumptions'!$B:$B,0))) -> 37.924239
A18: Acquisition | B18: New Growth Logos – Direct | C18: Customers | D18: =INDEX('1. Assumptions'!$G:$G,MATCH("New Growth Logos ; M1",'1. Assumptions'!$B:$B,0)) -> 4 | E18: =D18*(1+INDEX('1. Assumptions'!$G:$G,MATCH("Monthly New Logo Growth Rate (MoM)",'1. Assumptions'!$B:$B,0))) -> 4.28 | F18: =E18*(1+INDEX('1. Assumptions'!$G:$G,MATCH("Monthly New Logo Growth Rate (MoM)",'1. Assumptions'!$B:$B,0))) -> 4.5796 | G18: =F18*(1+INDEX('1. Assumptions'!$G:$G,MATCH("Monthly New Logo Growth Rate (MoM)",'1. Assumptions'!$B:$B,0))) -> 4.900172 | H18: =G18*(1+INDEX('1. Assumptions'!$G:$G,MATCH("Monthly New Logo Growth Rate (MoM)",'1. Assumptions'!$B:$B,0))) -> 5.243184 | I18: =H18*(1+INDEX('1. Assumptions'!$G:$G,MATCH("Monthly New Logo Growth Rate (MoM)",'1. Assumptions'!$B:$B,0))) -> 5.6102069 | J18: =I18*(1+INDEX('1. Assumptions'!$G:$G,MATCH("Monthly New Logo Growth Rate (MoM)",'1. Assumptions'!$B:$B,0))) -> 6.0029214 | K18: =J18*(1+INDEX('1. Assumptions'!$G:$G,MATCH("Monthly New Logo Growth Rate (MoM)",'1. Assumptions'!$B:$B,0))) -> 6.4231259 | L18: =K18*(1+INDEX('1. Assumptions'!$G:$G,MATCH("Monthly New Logo Growth Rate (MoM)",'1. Assumptions'!$B:$B,0))) -> 6.8727447 | ... AA18: =Z18*(1+INDEX('1. Assumptions'!$G:$G,MATCH("Monthly New Logo Growth Rate (MoM)",'1. Assumptions'!$B:$B,0))) -> 18.962119
A19: Acquisition | B19: New Enterprise Logos | C19: Customers | D19: =IF(1<INDEX('1. Assumptions'!$G:$G,MATCH("Enterprise Motion Start Month",'1. Assumptions'!$B:$B,0)),0,INDEX('1. Assumptions'!$G:$G,MATCH("New Enterprise Logos ; M6+",'1. Assumptions'!$B:$B,0))) -> 0 | E19: =IF(E5<INDEX('1. Assumptions'!$G:$G,MATCH("Enterprise Motion Start Month",'1. Assumptions'!$B:$B,0)),0,INDEX('1. Assumptions'!$G:$G,MATCH("New Enterprise Logos ; M6+",'1. Assumptions'!$B:$B,0))*(1+INDEX('1. Assumptions'!$G:$G,MATCH("Monthly New Logo Growth Rate (MoM)",'1. Assumptions'!$B:$B,0)))^(E5-INDEX('1. Assumptions'!$G:$G,MATCH("Enterprise Motion Start Month",'1. Assumptions'!$B:$B,0)))) -> 0 | F19: =IF(F5<INDEX('1. Assumptions'!$G:$G,MATCH("Enterprise Motion Start Month",'1. Assumptions'!$B:$B,0)),0,INDEX('1. Assumptions'!$G:$G,MATCH("New Enterprise Logos ; M6+",'1. Assumptions'!$B:$B,0))*(1+INDEX('1. Assumptions'!$G:$G,MATCH("Monthly New Logo Growth Rate (MoM)",'1. Assumptions'!$B:$B,0)))^(F5-INDEX('1. Assumptions'!$G:$G,MATCH("Enterprise Motion Start Month",'1. Assumptions'!$B:$B,0)))) -> 0 | G19: =IF(G5<INDEX('1. Assumptions'!$G:$G,MATCH("Enterprise Motion Start Month",'1. Assumptions'!$B:$B,0)),0,INDEX('1. Assumptions'!$G:$G,MATCH("New Enterprise Logos ; M6+",'1. Assumptions'!$B:$B,0))*(1+INDEX('1. Assumptions'!$G:$G,MATCH("Monthly New Logo Growth Rate (MoM)",'1. Assumptions'!$B:$B,0)))^(G5-INDEX('1. Assumptions'!$G:$G,MATCH("Enterprise Motion Start Month",'1. Assumptions'!$B:$B,0)))) -> 0 | H19: =IF(H5<INDEX('1. Assumptions'!$G:$G,MATCH("Enterprise Motion Start Month",'1. Assumptions'!$B:$B,0)),0,INDEX('1. Assumptions'!$G:$G,MATCH("New Enterprise Logos ; M6+",'1. Assumptions'!$B:$B,0))*(1+INDEX('1. Assumptions'!$G:$G,MATCH("Monthly New Logo Growth Rate (MoM)",'1. Assumptions'!$B:$B,0)))^(H5-INDEX('1. Assumptions'!$G:$G,MATCH("Enterprise Motion Start Month",'1. Assumptions'!$B:$B,0)))) -> 0 | I19: =IF(I5<INDEX('1. Assumptions'!$G:$G,MATCH("Enterprise Motion Start Month",'1. Assumptions'!$B:$B,0)),0,INDEX('1. Assumptions'!$G:$G,MATCH("New Enterprise Logos ; M6+",'1. Assumptions'!$B:$B,0))*(1+INDEX('1. Assumptions'!$G:$G,MATCH("Monthly New Logo Growth Rate (MoM)",'1. Assumptions'!$B:$B,0)))^(I5-INDEX('1. Assumptions'!$G:$G,MATCH("Enterprise Motion Start Month",'1. Assumptions'!$B:$B,0)))) -> 1 | J19: =IF(J5<INDEX('1. Assumptions'!$G:$G,MATCH("Enterprise Motion Start Month",'1. Assumptions'!$B:$B,0)),0,INDEX('1. Assumptions'!$G:$G,MATCH("New Enterprise Logos ; M6+",'1. Assumptions'!$B:$B,0))*(1+INDEX('1. Assumptions'!$G:$G,MATCH("Monthly New Logo Growth Rate (MoM)",'1. Assumptions'!$B:$B,0)))^(J5-INDEX('1. Assumptions'!$G:$G,MATCH("Enterprise Motion Start Month",'1. Assumptions'!$B:$B,0)))) -> 1.07 | K19: =IF(K5<INDEX('1. Assumptions'!$G:$G,MATCH("Enterprise Motion Start Month",'1. Assumptions'!$B:$B,0)),0,INDEX('1. Assumptions'!$G:$G,MATCH("New Enterprise Logos ; M6+",'1. Assumptions'!$B:$B,0))*(1+INDEX('1. Assumptions'!$G:$G,MATCH("Monthly New Logo Growth Rate (MoM)",'1. Assumptions'!$B:$B,0)))^(K5-INDEX('1. Assumptions'!$G:$G,MATCH("Enterprise Motion Start Month",'1. Assumptions'!$B:$B,0)))) -> 1.1449 | L19: =IF(L5<INDEX('1. Assumptions'!$G:$G,MATCH("Enterprise Motion Start Month",'1. Assumptions'!$B:$B,0)),0,INDEX('1. Assumptions'!$G:$G,MATCH("New Enterprise Logos ; M6+",'1. Assumptions'!$B:$B,0))*(1+INDEX('1. Assumptions'!$G:$G,MATCH("Monthly New Logo Growth Rate (MoM)",'1. Assumptions'!$B:$B,0)))^(L5-INDEX('1. Assumptions'!$G:$G,MATCH("Enterprise Motion Start Month",'1. Assumptions'!$B:$B,0)))) -> 1.225043 | ... AA19: =IF(AA5<INDEX('1. Assumptions'!$G:$G,MATCH("Enterprise Motion Start Month",'1. Assumptions'!$B:$B,0)),0,INDEX('1. Assumptions'!$G:$G,MATCH("New Enterprise Logos ; M6+",'1. Assumptions'!$B:$B,0))*(1+INDEX('1. Assumptions'!$G:$G,MATCH("Monthly New Logo Growth Rate (MoM)",'1. Assumptions'!$B:$B,0)))^(AA5-INDEX('1. Assumptions'!$G:$G,MATCH("Enterprise Motion Start Month",'1. Assumptions'!$B:$B,0)))) -> 3.3799323 | AC19: 0 before Enterprise Motion Start Month; grows monthly after
A20: Acquisition | B20: Free-to-Starter Conversions (from Free Funnel) | C20: Customers | D20: =D12 -> 32 | E20: =E12 -> 31.36 | F20: =F12 -> 31.5008 | G20: =G12 -> 32.314624 | H20: =H12 -> 33.723807 | I20: =I12 -> 35.674809 | J20: =J12 -> 38.133615 | K20: =K12 -> 41.08221 | ... AA20: =AA12 -> 179.12562
A21: Acquisition | B21: Total New Paid Logos | C21: Customers | D21: =D17+D18+D19+D20 -> 44 | E21: =E17+E18+E19+E20 -> 44.2 | F21: =F17+F18+F19+F20 -> 45.2396 | G21: =G17+G18+G19+G20 -> 47.01514 | H21: =H17+H18+H19+H20 -> 49.453359 | I21: =I17+I18+I19+I20 -> 53.50543 | J21: =J17+J18+J19+J20 -> 57.212379 | K21: =K17+K18+K19+K20 -> 61.496488 | ... AA21: =AA17+AA18+AA19+AA20 -> 239.39191 | AC21: Starter + Growth + Enterprise + Free-to-Starter
A23: § 4 STARTER CUSTOMER ROLL-FORWARD
A24: Starter Customers | B24: Beginning Starter Customers | C24: Customers | D24: =INDEX('1. Assumptions'!$G:$G,MATCH("Starting Starter Customers",'1. Assumptions'!$B:$B,0)) -> 300 | E24: =D29 -> 334 | F24: =E29 -> 353.88 | G24: =F29 -> 373.3072 | H24: =G29 -> 393.02374 | I24: =H29 -> 413.65249 | J24: =I29 -> 435.72856 | K24: =J29 -> 459.7243 | L24: =K29 -> 486.06931 | ... AA24: =Z29 -> 1459.2527
A25: Starter Customers | B25: New Starter Logos | C25: Customers | D25: =D17 -> 8 | E25: =E17 -> 8.56 | F25: =F17 -> 9.1592 | G25: =G17 -> 9.800344 | H25: =H17 -> 10.486368 | I25: =I17 -> 11.220414 | J25: =J17 -> 12.005843 | K25: =K17 -> 12.846252 | ... AA25: =AA17 -> 37.924239
A26: Starter Customers | B26: Free-to-Starter Conversions | C26: Customers | D26: =D12 -> 32 | E26: =E12 -> 31.36 | F26: =F12 -> 31.5008 | G26: =G12 -> 32.314624 | H26: =H12 -> 33.723807 | I26: =I12 -> 35.674809 | J26: =J12 -> 38.133615 | K26: =K12 -> 41.08221 | ... AA26: =AA12 -> 179.12562
A27: Starter Customers | B27: Starter-to-Growth Upgrades | C27: Customers | D27: =D24*INDEX('1. Assumptions'!$G:$G,MATCH("Starter-to-Growth Monthly Upgrade Rate",'1. Assumptions'!$B:$B,0)) -> 6 | E27: =E24*INDEX('1. Assumptions'!$G:$G,MATCH("Starter-to-Growth Monthly Upgrade Rate",'1. Assumptions'!$B:$B,0)) -> 6.68 | F27: =F24*INDEX('1. Assumptions'!$G:$G,MATCH("Starter-to-Growth Monthly Upgrade Rate",'1. Assumptions'!$B:$B,0)) -> 7.0776 | G27: =G24*INDEX('1. Assumptions'!$G:$G,MATCH("Starter-to-Growth Monthly Upgrade Rate",'1. Assumptions'!$B:$B,0)) -> 7.466144 | H27: =H24*INDEX('1. Assumptions'!$G:$G,MATCH("Starter-to-Growth Monthly Upgrade Rate",'1. Assumptions'!$B:$B,0)) -> 7.8604747 | I27: =I24*INDEX('1. Assumptions'!$G:$G,MATCH("Starter-to-Growth Monthly Upgrade Rate",'1. Assumptions'!$B:$B,0)) -> 8.2730497 | J27: =J24*INDEX('1. Assumptions'!$G:$G,MATCH("Starter-to-Growth Monthly Upgrade Rate",'1. Assumptions'!$B:$B,0)) -> 8.7145712 | K27: =K24*INDEX('1. Assumptions'!$G:$G,MATCH("Starter-to-Growth Monthly Upgrade Rate",'1. Assumptions'!$B:$B,0)) -> 9.1944861 | ... AA27: =AA24*INDEX('1. Assumptions'!$G:$G,MATCH("Starter-to-Growth Monthly Upgrade Rate",'1. Assumptions'!$B:$B,0)) -> 29.185054
A28: Starter Customers | B28: Starter Churned Customers | C28: Customers | D28: =IF(D5<INDEX('1. Assumptions'!$G:$G,MATCH("Churn Start Month",'1. Assumptions'!$B:$B,0)),0,D24*INDEX('1. Assumptions'!$G:$G,MATCH("Starter Monthly Churn",'1. Assumptions'!$B:$B,0))) -> 0 | E28: =IF(E5<INDEX('1. Assumptions'!$G:$G,MATCH("Churn Start Month",'1. Assumptions'!$B:$B,0)),0,E24*INDEX('1. Assumptions'!$G:$G,MATCH("Starter Monthly Churn",'1. Assumptions'!$B:$B,0))) -> 13.36 | F28: =IF(F5<INDEX('1. Assumptions'!$G:$G,MATCH("Churn Start Month",'1. Assumptions'!$B:$B,0)),0,F24*INDEX('1. Assumptions'!$G:$G,MATCH("Starter Monthly Churn",'1. Assumptions'!$B:$B,0))) -> 14.1552 | G28: =IF(G5<INDEX('1. Assumptions'!$G:$G,MATCH("Churn Start Month",'1. Assumptions'!$B:$B,0)),0,G24*INDEX('1. Assumptions'!$G:$G,MATCH("Starter Monthly Churn",'1. Assumptions'!$B:$B,0))) -> 14.932288 | H28: =IF(H5<INDEX('1. Assumptions'!$G:$G,MATCH("Churn Start Month",'1. Assumptions'!$B:$B,0)),0,H24*INDEX('1. Assumptions'!$G:$G,MATCH("Starter Monthly Churn",'1. Assumptions'!$B:$B,0))) -> 15.720949 | I28: =IF(I5<INDEX('1. Assumptions'!$G:$G,MATCH("Churn Start Month",'1. Assumptions'!$B:$B,0)),0,I24*INDEX('1. Assumptions'!$G:$G,MATCH("Starter Monthly Churn",'1. Assumptions'!$B:$B,0))) -> 16.546099 | J28: =IF(J5<INDEX('1. Assumptions'!$G:$G,MATCH("Churn Start Month",'1. Assumptions'!$B:$B,0)),0,J24*INDEX('1. Assumptions'!$G:$G,MATCH("Starter Monthly Churn",'1. Assumptions'!$B:$B,0))) -> 17.429142 | K28: =IF(K5<INDEX('1. Assumptions'!$G:$G,MATCH("Churn Start Month",'1. Assumptions'!$B:$B,0)),0,K24*INDEX('1. Assumptions'!$G:$G,MATCH("Starter Monthly Churn",'1. Assumptions'!$B:$B,0))) -> 18.388972 | ... AA28: =IF(AA5<INDEX('1. Assumptions'!$G:$G,MATCH("Churn Start Month",'1. Assumptions'!$B:$B,0)),0,AA24*INDEX('1. Assumptions'!$G:$G,MATCH("Starter Monthly Churn",'1. Assumptions'!$B:$B,0))) -> 58.370108
A29: Starter Customers | B29: Ending Starter Customers | C29: Customers | D29: =D24+D25+D26-D27-D28 -> 334 | E29: =E24+E25+E26-E27-E28 -> 353.88 | F29: =F24+F25+F26-F27-F28 -> 373.3072 | G29: =G24+G25+G26-G27-G28 -> 393.02374 | H29: =H24+H25+H26-H27-H28 -> 413.65249 | I29: =I24+I25+I26-I27-I28 -> 435.72856 | J29: =J24+J25+J26-J27-J28 -> 459.7243 | K29: =K24+K25+K26-K27-K28 -> 486.06931 | ... AA29: =AA24+AA25+AA26-AA27-AA28 -> 1588.7474 | AC29: Beginning + New + Free Conversions - Upgrades - Churn
A31: § 5 GROWTH CUSTOMER ROLL-FORWARD
A32: Growth Customers | B32: Beginning Growth Customers | C32: Customers | D32: =INDEX('1. Assumptions'!$G:$G,MATCH("Starting Growth Customers",'1. Assumptions'!$B:$B,0)) -> 180 | E32: =D37 -> 189.55 | F32: =E37 -> 195.29738 | G32: =F37 -> 201.5839 | H32: =G37 -> 208.40666 | I32: =H37 -> 215.77913 | J32: =I37 -> 223.72846 | K32: =J37 -> 232.29342 | L32: =K37 -> 241.52297 | ... AA32: =Z37 -> 519.6969
A33: Growth Customers | B33: New Growth Logos | C33: Customers | D33: =D18 -> 4 | E33: =E18 -> 4.28 | F33: =F18 -> 4.5796 | G33: =G18 -> 4.900172 | H33: =H18 -> 5.243184 | I33: =I18 -> 5.6102069 | J33: =J18 -> 6.0029214 | K33: =K18 -> 6.4231259 | ... AA33: =AA18 -> 18.962119
A34: Growth Customers | B34: Upgrades from Starter | C34: Customers | D34: =D27 -> 6 | E34: =E27 -> 6.68 | F34: =F27 -> 7.0776 | G34: =G27 -> 7.466144 | H34: =H27 -> 7.8604747 | I34: =I27 -> 8.2730497 | J34: =J27 -> 8.7145712 | K34: =K27 -> 9.1944861 | ... AA34: =AA27 -> 29.185054
A35: Growth Customers | B35: Growth-to-Enterprise Upgrades | C35: Customers | D35: =D32*INDEX('1. Assumptions'!$G:$G,MATCH("Growth-to-Enterprise Monthly Upgrade Rate",'1. Assumptions'!$B:$B,0)) -> 0.45 | E35: =E32*INDEX('1. Assumptions'!$G:$G,MATCH("Growth-to-Enterprise Monthly Upgrade Rate",'1. Assumptions'!$B:$B,0)) -> 0.473875 | F35: =F32*INDEX('1. Assumptions'!$G:$G,MATCH("Growth-to-Enterprise Monthly Upgrade Rate",'1. Assumptions'!$B:$B,0)) -> 0.48824344 | G35: =G32*INDEX('1. Assumptions'!$G:$G,MATCH("Growth-to-Enterprise Monthly Upgrade Rate",'1. Assumptions'!$B:$B,0)) -> 0.50395974 | H35: =H32*INDEX('1. Assumptions'!$G:$G,MATCH("Growth-to-Enterprise Monthly Upgrade Rate",'1. Assumptions'!$B:$B,0)) -> 0.52101664 | I35: =I32*INDEX('1. Assumptions'!$G:$G,MATCH("Growth-to-Enterprise Monthly Upgrade Rate",'1. Assumptions'!$B:$B,0)) -> 0.53944783 | J35: =J32*INDEX('1. Assumptions'!$G:$G,MATCH("Growth-to-Enterprise Monthly Upgrade Rate",'1. Assumptions'!$B:$B,0)) -> 0.55932116 | K35: =K32*INDEX('1. Assumptions'!$G:$G,MATCH("Growth-to-Enterprise Monthly Upgrade Rate",'1. Assumptions'!$B:$B,0)) -> 0.58073356 | ... AA35: =AA32*INDEX('1. Assumptions'!$G:$G,MATCH("Growth-to-Enterprise Monthly Upgrade Rate",'1. Assumptions'!$B:$B,0)) -> 1.2992423
A36: Growth Customers | B36: Growth Churned Customers | C36: Customers | D36: =IF(D5<INDEX('1. Assumptions'!$G:$G,MATCH("Churn Start Month",'1. Assumptions'!$B:$B,0)),0,D32*INDEX('1. Assumptions'!$G:$G,MATCH("Growth Monthly Churn",'1. Assumptions'!$B:$B,0))) -> 0 | E36: =IF(E5<INDEX('1. Assumptions'!$G:$G,MATCH("Churn Start Month",'1. Assumptions'!$B:$B,0)),0,E32*INDEX('1. Assumptions'!$G:$G,MATCH("Growth Monthly Churn",'1. Assumptions'!$B:$B,0))) -> 4.73875 | F36: =IF(F5<INDEX('1. Assumptions'!$G:$G,MATCH("Churn Start Month",'1. Assumptions'!$B:$B,0)),0,F32*INDEX('1. Assumptions'!$G:$G,MATCH("Growth Monthly Churn",'1. Assumptions'!$B:$B,0))) -> 4.8824344 | G36: =IF(G5<INDEX('1. Assumptions'!$G:$G,MATCH("Churn Start Month",'1. Assumptions'!$B:$B,0)),0,G32*INDEX('1. Assumptions'!$G:$G,MATCH("Growth Monthly Churn",'1. Assumptions'!$B:$B,0))) -> 5.0395974 | H36: =IF(H5<INDEX('1. Assumptions'!$G:$G,MATCH("Churn Start Month",'1. Assumptions'!$B:$B,0)),0,H32*INDEX('1. Assumptions'!$G:$G,MATCH("Growth Monthly Churn",'1. Assumptions'!$B:$B,0))) -> 5.2101664 | I36: =IF(I5<INDEX('1. Assumptions'!$G:$G,MATCH("Churn Start Month",'1. Assumptions'!$B:$B,0)),0,I32*INDEX('1. Assumptions'!$G:$G,MATCH("Growth Monthly Churn",'1. Assumptions'!$B:$B,0))) -> 5.3944783 | J36: =IF(J5<INDEX('1. Assumptions'!$G:$G,MATCH("Churn Start Month",'1. Assumptions'!$B:$B,0)),0,J32*INDEX('1. Assumptions'!$G:$G,MATCH("Growth Monthly Churn",'1. Assumptions'!$B:$B,0))) -> 5.5932116 | K36: =IF(K5<INDEX('1. Assumptions'!$G:$G,MATCH("Churn Start Month",'1. Assumptions'!$B:$B,0)),0,K32*INDEX('1. Assumptions'!$G:$G,MATCH("Growth Monthly Churn",'1. Assumptions'!$B:$B,0))) -> 5.8073356 | ... AA36: =IF(AA5<INDEX('1. Assumptions'!$G:$G,MATCH("Churn Start Month",'1. Assumptions'!$B:$B,0)),0,AA32*INDEX('1. Assumptions'!$G:$G,MATCH("Growth Monthly Churn",'1. Assumptions'!$B:$B,0))) -> 12.992423
A37: Growth Customers | B37: Ending Growth Customers | C37: Customers | D37: =D32+D33+D34-D35-D36 -> 189.55 | E37: =E32+E33+E34-E35-E36 -> 195.29738 | F37: =F32+F33+F34-F35-F36 -> 201.5839 | G37: =G32+G33+G34-G35-G36 -> 208.40666 | H37: =H32+H33+H34-H35-H36 -> 215.77913 | I37: =I32+I33+I34-I35-I36 -> 223.72846 | J37: =J32+J33+J34-J35-J36 -> 232.29342 | K37: =K32+K33+K34-K35-K36 -> 241.52297 | ... AA37: =AA32+AA33+AA34-AA35-AA36 -> 553.55241 | AC37: Beginning + New + Starter Upgrades - Enterprise Upgrades - Churn
A39: § 6 ENTERPRISE CUSTOMER ROLL-FORWARD
A40: Enterprise Customers | B40: Beginning Enterprise Customers | C40: Customers | D40: =INDEX('1. Assumptions'!$G:$G,MATCH("Starting Enterprise Customers",'1. Assumptions'!$B:$B,0)) -> 0 | E40: =D44 -> 0.45 | F40: =E44 -> 0.91782162 | G40: =F44 -> 1.3937186 | H40: =G44 -> 1.8789301 | I40: =H44 -> 2.3746715 | J40: =I44 -> 3.8821753 | K40: =J44 -> 5.4592737 | L40: =K44 -> 7.1114694 | ... AA40: =Z44 -> 46.21598
A41: Enterprise Customers | B41: New Enterprise Logos | C41: Customers | D41: =D19 -> 0 | E41: =E19 -> 0 | F41: =F19 -> 0 | G41: =G19 -> 0 | H41: =H19 -> 0 | I41: =I19 -> 1 | J41: =J19 -> 1.07 | K41: =K19 -> 1.1449 | ... AA41: =AA19 -> 3.3799323
A42: Enterprise Customers | B42: Upgrades from Growth | C42: Customers | D42: =D35 -> 0.45 | E42: =E35 -> 0.473875 | F42: =F35 -> 0.48824344 | G42: =G35 -> 0.50395974 | H42: =H35 -> 0.52101664 | I42: =I35 -> 0.53944783 | J42: =J35 -> 0.55932116 | K42: =K35 -> 0.58073356 | ... AA42: =AA35 -> 1.2992423
A43: Enterprise Customers | B43: Enterprise Churned Customers | C43: Customers | D43: =IF(D5<INDEX('1. Assumptions'!$G:$G,MATCH("Churn Start Month",'1. Assumptions'!$B:$B,0)),0,D40*INDEX('1. Assumptions'!$G:$G,MATCH("Enterprise Monthly Churn (converted)",'1. Assumptions'!$B:$B,0))) -> 0 | E43: =IF(E5<INDEX('1. Assumptions'!$G:$G,MATCH("Churn Start Month",'1. Assumptions'!$B:$B,0)),0,E40*INDEX('1. Assumptions'!$G:$G,MATCH("Enterprise Monthly Churn (converted)",'1. Assumptions'!$B:$B,0))) -> 0.0060533762 | F43: =IF(F5<INDEX('1. Assumptions'!$G:$G,MATCH("Churn Start Month",'1. Assumptions'!$B:$B,0)),0,F40*INDEX('1. Assumptions'!$G:$G,MATCH("Enterprise Monthly Churn (converted)",'1. Assumptions'!$B:$B,0))) -> 0.012346488 | G43: =IF(G5<INDEX('1. Assumptions'!$G:$G,MATCH("Churn Start Month",'1. Assumptions'!$B:$B,0)),0,G40*INDEX('1. Assumptions'!$G:$G,MATCH("Enterprise Monthly Churn (converted)",'1. Assumptions'!$B:$B,0))) -> 0.018748228 | H43: =IF(H5<INDEX('1. Assumptions'!$G:$G,MATCH("Churn Start Month",'1. Assumptions'!$B:$B,0)),0,H40*INDEX('1. Assumptions'!$G:$G,MATCH("Enterprise Monthly Churn (converted)",'1. Assumptions'!$B:$B,0))) -> 0.025275268 | I43: =IF(I5<INDEX('1. Assumptions'!$G:$G,MATCH("Churn Start Month",'1. Assumptions'!$B:$B,0)),0,I40*INDEX('1. Assumptions'!$G:$G,MATCH("Enterprise Monthly Churn (converted)",'1. Assumptions'!$B:$B,0))) -> 0.031943955 | J43: =IF(J5<INDEX('1. Assumptions'!$G:$G,MATCH("Churn Start Month",'1. Assumptions'!$B:$B,0)),0,J40*INDEX('1. Assumptions'!$G:$G,MATCH("Enterprise Monthly Churn (converted)",'1. Assumptions'!$B:$B,0))) -> 0.052222817 | K43: =IF(K5<INDEX('1. Assumptions'!$G:$G,MATCH("Churn Start Month",'1. Assumptions'!$B:$B,0)),0,K40*INDEX('1. Assumptions'!$G:$G,MATCH("Enterprise Monthly Churn (converted)",'1. Assumptions'!$B:$B,0))) -> 0.07343786 | ... AA43: =IF(AA5<INDEX('1. Assumptions'!$G:$G,MATCH("Churn Start Month",'1. Assumptions'!$B:$B,0)),0,AA40*INDEX('1. Assumptions'!$G:$G,MATCH("Enterprise Monthly Churn (converted)",'1. Assumptions'!$B:$B,0))) -> 0.62169492
A44: Enterprise Customers | B44: Ending Enterprise Customers | C44: Customers | D44: =D40+D41+D42-D43 -> 0.45 | E44: =E40+E41+E42-E43 -> 0.91782162 | F44: =F40+F41+F42-F43 -> 1.3937186 | G44: =G40+G41+G42-G43 -> 1.8789301 | H44: =H40+H41+H42-H43 -> 2.3746715 | I44: =I40+I41+I42-I43 -> 3.8821753 | J44: =J40+J41+J42-J43 -> 5.4592737 | K44: =K40+K41+K42-K43 -> 7.1114694 | ... AA44: =AA40+AA41+AA42-AA43 -> 50.27346
A46: § 7 TOTAL CUSTOMER SUMMARY
A47: Customer Summary | B47: Total Beginning Paid Customers | C47: Customers | D47: =D24+D32+D40 -> 480 | E47: =E24+E32+E40 -> 524 | F47: =F24+F32+F40 -> 550.0952 | G47: =G24+G32+G40 -> 576.28482 | H47: =H24+H32+H40 -> 603.30932 | I47: =I24+I32+I40 -> 631.80629 | J47: =J24+J32+J40 -> 663.3392 | K47: =K24+K32+K40 -> 697.477 | ... AA47: =AA24+AA32+AA40 -> 2025.1656
A48: Customer Summary | B48: Total New Paid Customers | C48: Customers | D48: =D21 -> 44 | E48: =E21 -> 44.2 | F48: =F21 -> 45.2396 | G48: =G21 -> 47.01514 | H48: =H21 -> 49.453359 | I48: =I21 -> 53.50543 | J48: =J21 -> 57.212379 | K48: =K21 -> 61.496488 | ... AA48: =AA21 -> 239.39191
A49: Customer Summary | B49: Total Churned Customers | C49: Customers | D49: =D28+D36+D43 -> 0 | E49: =E28+E36+E43 -> 18.104803 | F49: =F28+F36+F43 -> 19.049981 | G49: =G28+G36+G43 -> 19.990634 | H49: =H28+H36+H43 -> 20.956391 | I49: =I28+I36+I43 -> 21.972522 | J49: =J28+J36+J43 -> 23.074577 | K49: =K28+K36+K43 -> 24.269746 | ... AA49: =AA28+AA36+AA43 -> 71.984226
A50: Customer Summary | B50: Total Ending Paid Customers | C50: Customers | D50: =D29+D37+D44 -> 524 | E50: =E29+E37+E44 -> 550.0952 | F50: =F29+F37+F44 -> 576.28482 | G50: =G29+G37+G44 -> 603.30932 | H50: =H29+H37+H44 -> 631.80629 | I50: =I29+I37+I44 -> 663.3392 | J50: =J29+J37+J44 -> 697.477 | K50: =K29+K37+K44 -> 734.70374 | ... AA50: =AA29+AA37+AA44 -> 2192.5733 | AC50: Feeds Dashboard tab — key SaaS growth metric
A51: Customer Summary | B51: Logo Churn Rate | C51: % | D51: =IFERROR(D49/D47,0) -> 0 | E51: =IFERROR(E49/E47,0) -> 0.034551151 | F51: =IFERROR(F49/F47,0) -> 0.034630335 | G51: =IFERROR(G49/G47,0) -> 0.034688809 | H51: =IFERROR(H49/H47,0) -> 0.034735732 | I51: =IFERROR(I49/I47,0) -> 0.034777308 | J51: =IFERROR(J49/J47,0) -> 0.034785487 | K51: =IFERROR(K49/K47,0) -> 0.034796482 | ... AA51: =IFERROR(AA49/AA47,0) -> 0.035544859 | AC51: Logo Churn = Churned / Beginning Paid. Target: Starter<6%, Growth<4%, Enterprise<2% monthly
A53: § 8 SUBSCRIPTION MRR BY PLAN
A54: Subscription MRR | B54: Starter MRR | C54: $ | D54: =D29*INDEX('1. Assumptions'!$G:$G,MATCH("Starter Plan Price ($/mo)",'1. Assumptions'!$B:$B,0)) -> 16366 | E54: =E29*INDEX('1. Assumptions'!$G:$G,MATCH("Starter Plan Price ($/mo)",'1. Assumptions'!$B:$B,0)) -> 17340.12 | F54: =F29*INDEX('1. Assumptions'!$G:$G,MATCH("Starter Plan Price ($/mo)",'1. Assumptions'!$B:$B,0)) -> 18292.053 | G54: =G29*INDEX('1. Assumptions'!$G:$G,MATCH("Starter Plan Price ($/mo)",'1. Assumptions'!$B:$B,0)) -> 19258.163 | H54: =H29*INDEX('1. Assumptions'!$G:$G,MATCH("Starter Plan Price ($/mo)",'1. Assumptions'!$B:$B,0)) -> 20268.972 | I54: =I29*INDEX('1. Assumptions'!$G:$G,MATCH("Starter Plan Price ($/mo)",'1. Assumptions'!$B:$B,0)) -> 21350.699 | J54: =J29*INDEX('1. Assumptions'!$G:$G,MATCH("Starter Plan Price ($/mo)",'1. Assumptions'!$B:$B,0)) -> 22526.491 | K54: =K29*INDEX('1. Assumptions'!$G:$G,MATCH("Starter Plan Price ($/mo)",'1. Assumptions'!$B:$B,0)) -> 23817.396 | ... AA54: =AA29*INDEX('1. Assumptions'!$G:$G,MATCH("Starter Plan Price ($/mo)",'1. Assumptions'!$B:$B,0)) -> 77848.623
A55: Subscription MRR | B55: Growth MRR | C55: $ | D55: =D37*INDEX('1. Assumptions'!$G:$G,MATCH("Growth Plan Price ($/mo)",'1. Assumptions'!$B:$B,0)) -> 28242.95 | E55: =E37*INDEX('1. Assumptions'!$G:$G,MATCH("Growth Plan Price ($/mo)",'1. Assumptions'!$B:$B,0)) -> 29099.309 | F55: =F37*INDEX('1. Assumptions'!$G:$G,MATCH("Growth Plan Price ($/mo)",'1. Assumptions'!$B:$B,0)) -> 30036.001 | G55: =G37*INDEX('1. Assumptions'!$G:$G,MATCH("Growth Plan Price ($/mo)",'1. Assumptions'!$B:$B,0)) -> 31052.592 | H55: =H37*INDEX('1. Assumptions'!$G:$G,MATCH("Growth Plan Price ($/mo)",'1. Assumptions'!$B:$B,0)) -> 32151.091 | I55: =I37*INDEX('1. Assumptions'!$G:$G,MATCH("Growth Plan Price ($/mo)",'1. Assumptions'!$B:$B,0)) -> 33335.541 | J55: =J37*INDEX('1. Assumptions'!$G:$G,MATCH("Growth Plan Price ($/mo)",'1. Assumptions'!$B:$B,0)) -> 34611.72 | K55: =K37*INDEX('1. Assumptions'!$G:$G,MATCH("Growth Plan Price ($/mo)",'1. Assumptions'!$B:$B,0)) -> 35986.922 | ... AA55: =AA37*INDEX('1. Assumptions'!$G:$G,MATCH("Growth Plan Price ($/mo)",'1. Assumptions'!$B:$B,0)) -> 82479.309
A56: Subscription MRR | B56: Enterprise MRR | C56: $ | D56: =D44*INDEX('1. Assumptions'!$G:$G,MATCH("Enterprise Plan Price ($/mo)",'1. Assumptions'!$B:$B,0)) -> 269.55 | E56: =E44*INDEX('1. Assumptions'!$G:$G,MATCH("Enterprise Plan Price ($/mo)",'1. Assumptions'!$B:$B,0)) -> 549.77515 | F56: =F44*INDEX('1. Assumptions'!$G:$G,MATCH("Enterprise Plan Price ($/mo)",'1. Assumptions'!$B:$B,0)) -> 834.83743 | G56: =G44*INDEX('1. Assumptions'!$G:$G,MATCH("Enterprise Plan Price ($/mo)",'1. Assumptions'!$B:$B,0)) -> 1125.4791 | H56: =H44*INDEX('1. Assumptions'!$G:$G,MATCH("Enterprise Plan Price ($/mo)",'1. Assumptions'!$B:$B,0)) -> 1422.4282 | I56: =I44*INDEX('1. Assumptions'!$G:$G,MATCH("Enterprise Plan Price ($/mo)",'1. Assumptions'!$B:$B,0)) -> 2325.423 | J56: =J44*INDEX('1. Assumptions'!$G:$G,MATCH("Enterprise Plan Price ($/mo)",'1. Assumptions'!$B:$B,0)) -> 3270.1049 | K56: =K44*INDEX('1. Assumptions'!$G:$G,MATCH("Enterprise Plan Price ($/mo)",'1. Assumptions'!$B:$B,0)) -> 4259.7702 | ... AA56: =AA44*INDEX('1. Assumptions'!$G:$G,MATCH("Enterprise Plan Price ($/mo)",'1. Assumptions'!$B:$B,0)) -> 30113.803
A57: Subscription MRR | B57: Gross Subscription MRR Before Contraction | C57: $ | D57: =D54+D55+D56 -> 44878.5 | E57: =E54+E55+E56 -> 46989.204 | F57: =F54+F55+F56 -> 49162.891 | G57: =G54+G55+G56 -> 51436.234 | H57: =H54+H55+H56 -> 53842.491 | I57: =I54+I55+I56 -> 57011.663 | J57: =J54+J55+J56 -> 60408.316 | K57: =K54+K55+K56 -> 64064.088 | ... AA57: =AA54+AA55+AA56 -> 190441.73
A58: Subscription MRR | B58: Cumulative Contraction MRR | C58: $ | D58: =D67 -> 415.2 | E58: =D58+E67 -> 859.833 | F58: =E58+F67 -> 1321.1267 | G58: =F58+G67 -> 1799.5444 | H58: =G58+H67 -> 2295.9112 | I58: =H58+I67 -> 2811.377 | J58: =I58+J67 -> 3353.3799 | K58: =J58+K67 -> 3923.9293 | L58: =K58+L67 -> 4525.3309 | ... AA58: =Z58+AA67 -> 19855.701
A59: Subscription MRR | B59: Ending Subscription MRR | C59: $ | D59: =D57-D58 -> 44463.3 | E59: =E57-E58 -> 46129.371 | F59: =F57-F58 -> 47841.764 | G59: =G57-G58 -> 49636.69 | H59: =H57-H58 -> 51546.579 | I59: =I57-I58 -> 54200.286 | J59: =J57-J58 -> 57054.936 | K59: =K57-K58 -> 60140.159 | ... AA59: =AA57-AA58 -> 170586.03 | AC59: Gross Subscription MRR - Contraction MRR. Recurring subscription only.
A61: § 9 MRR BRIDGE (WHY DID MRR CHANGE?)
A62: MRR Bridge | B62: Beginning Subscription MRR | C62: $ | D62: =INDEX('1. Assumptions'!$G:$G,MATCH("Starting MRR ($)",'1. Assumptions'!$B:$B,0)) -> 41520 | E62: =D68 -> 44463.3 | F62: =E68 -> 46129.371 | G62: =F68 -> 47841.764 | H62: =G68 -> 49636.69 | I62: =H68 -> 51546.579 | J62: =I68 -> 54200.286 | K62: =J68 -> 57054.936 | L62: =K68 -> 60140.159 | ... AA62: =Z68 -> 158349.39
A63: MRR Bridge | B63: New Logo MRR | C63: $ | D63: =D17*INDEX('1. Assumptions'!$G:$G,MATCH("Starter Plan Price ($/mo)",'1. Assumptions'!$B:$B,0))+D18*INDEX('1. Assumptions'!$G:$G,MATCH("Growth Plan Price ($/mo)",'1. Assumptions'!$B:$B,0))+D19*INDEX('1. Assumptions'!$G:$G,MATCH("Enterprise Plan Price ($/mo)",'1. Assumptions'!$B:$B,0)) -> 988 | E63: =E17*INDEX('1. Assumptions'!$G:$G,MATCH("Starter Plan Price ($/mo)",'1. Assumptions'!$B:$B,0))+E18*INDEX('1. Assumptions'!$G:$G,MATCH("Growth Plan Price ($/mo)",'1. Assumptions'!$B:$B,0))+E19*INDEX('1. Assumptions'!$G:$G,MATCH("Enterprise Plan Price ($/mo)",'1. Assumptions'!$B:$B,0)) -> 1057.16 | F63: =F17*INDEX('1. Assumptions'!$G:$G,MATCH("Starter Plan Price ($/mo)",'1. Assumptions'!$B:$B,0))+F18*INDEX('1. Assumptions'!$G:$G,MATCH("Growth Plan Price ($/mo)",'1. Assumptions'!$B:$B,0))+F19*INDEX('1. Assumptions'!$G:$G,MATCH("Enterprise Plan Price ($/mo)",'1. Assumptions'!$B:$B,0)) -> 1131.1612 | G63: =G17*INDEX('1. Assumptions'!$G:$G,MATCH("Starter Plan Price ($/mo)",'1. Assumptions'!$B:$B,0))+G18*INDEX('1. Assumptions'!$G:$G,MATCH("Growth Plan Price ($/mo)",'1. Assumptions'!$B:$B,0))+G19*INDEX('1. Assumptions'!$G:$G,MATCH("Enterprise Plan Price ($/mo)",'1. Assumptions'!$B:$B,0)) -> 1210.3425 | H63: =H17*INDEX('1. Assumptions'!$G:$G,MATCH("Starter Plan Price ($/mo)",'1. Assumptions'!$B:$B,0))+H18*INDEX('1. Assumptions'!$G:$G,MATCH("Growth Plan Price ($/mo)",'1. Assumptions'!$B:$B,0))+H19*INDEX('1. Assumptions'!$G:$G,MATCH("Enterprise Plan Price ($/mo)",'1. Assumptions'!$B:$B,0)) -> 1295.0665 | I63: =I17*INDEX('1. Assumptions'!$G:$G,MATCH("Starter Plan Price ($/mo)",'1. Assumptions'!$B:$B,0))+I18*INDEX('1. Assumptions'!$G:$G,MATCH("Growth Plan Price ($/mo)",'1. Assumptions'!$B:$B,0))+I19*INDEX('1. Assumptions'!$G:$G,MATCH("Enterprise Plan Price ($/mo)",'1. Assumptions'!$B:$B,0)) -> 1984.7211 | J63: =J17*INDEX('1. Assumptions'!$G:$G,MATCH("Starter Plan Price ($/mo)",'1. Assumptions'!$B:$B,0))+J18*INDEX('1. Assumptions'!$G:$G,MATCH("Growth Plan Price ($/mo)",'1. Assumptions'!$B:$B,0))+J19*INDEX('1. Assumptions'!$G:$G,MATCH("Enterprise Plan Price ($/mo)",'1. Assumptions'!$B:$B,0)) -> 2123.6516 | K63: =K17*INDEX('1. Assumptions'!$G:$G,MATCH("Starter Plan Price ($/mo)",'1. Assumptions'!$B:$B,0))+K18*INDEX('1. Assumptions'!$G:$G,MATCH("Growth Plan Price ($/mo)",'1. Assumptions'!$B:$B,0))+K19*INDEX('1. Assumptions'!$G:$G,MATCH("Enterprise Plan Price ($/mo)",'1. Assumptions'!$B:$B,0)) -> 2272.3072 | ... AA63: =AA17*INDEX('1. Assumptions'!$G:$G,MATCH("Starter Plan Price ($/mo)",'1. Assumptions'!$B:$B,0))+AA18*INDEX('1. Assumptions'!$G:$G,MATCH("Growth Plan Price ($/mo)",'1. Assumptions'!$B:$B,0))+AA19*INDEX('1. Assumptions'!$G:$G,MATCH("Enterprise Plan Price ($/mo)",'1. Assumptions'!$B:$B,0)) -> 6708.2229
A64: MRR Bridge | B64: Free Conversion MRR | C64: $ | D64: =D12*INDEX('1. Assumptions'!$G:$G,MATCH("Starter Plan Price ($/mo)",'1. Assumptions'!$B:$B,0)) -> 1568 | E64: =E12*INDEX('1. Assumptions'!$G:$G,MATCH("Starter Plan Price ($/mo)",'1. Assumptions'!$B:$B,0)) -> 1536.64 | F64: =F12*INDEX('1. Assumptions'!$G:$G,MATCH("Starter Plan Price ($/mo)",'1. Assumptions'!$B:$B,0)) -> 1543.5392 | G64: =G12*INDEX('1. Assumptions'!$G:$G,MATCH("Starter Plan Price ($/mo)",'1. Assumptions'!$B:$B,0)) -> 1583.4166 | H64: =H12*INDEX('1. Assumptions'!$G:$G,MATCH("Starter Plan Price ($/mo)",'1. Assumptions'!$B:$B,0)) -> 1652.4665 | I64: =I12*INDEX('1. Assumptions'!$G:$G,MATCH("Starter Plan Price ($/mo)",'1. Assumptions'!$B:$B,0)) -> 1748.0657 | J64: =J12*INDEX('1. Assumptions'!$G:$G,MATCH("Starter Plan Price ($/mo)",'1. Assumptions'!$B:$B,0)) -> 1868.5471 | K64: =K12*INDEX('1. Assumptions'!$G:$G,MATCH("Starter Plan Price ($/mo)",'1. Assumptions'!$B:$B,0)) -> 2013.0283 | ... AA64: =AA12*INDEX('1. Assumptions'!$G:$G,MATCH("Starter Plan Price ($/mo)",'1. Assumptions'!$B:$B,0)) -> 8777.1553
A65: MRR Bridge | B65: Upgrade / Expansion MRR | C65: $ | D65: =D27*(INDEX('1. Assumptions'!$G:$G,MATCH("Growth Plan Price ($/mo)",'1. Assumptions'!$B:$B,0))-INDEX('1. Assumptions'!$G:$G,MATCH("Starter Plan Price ($/mo)",'1. Assumptions'!$B:$B,0)))+D35*(INDEX('1. Assumptions'!$G:$G,MATCH("Enterprise Plan Price ($/mo)",'1. Assumptions'!$B:$B,0))-INDEX('1. Assumptions'!$G:$G,MATCH("Growth Plan Price ($/mo)",'1. Assumptions'!$B:$B,0))) -> 802.5 | E65: =E27*(INDEX('1. Assumptions'!$G:$G,MATCH("Growth Plan Price ($/mo)",'1. Assumptions'!$B:$B,0))-INDEX('1. Assumptions'!$G:$G,MATCH("Starter Plan Price ($/mo)",'1. Assumptions'!$B:$B,0)))+E35*(INDEX('1. Assumptions'!$G:$G,MATCH("Enterprise Plan Price ($/mo)",'1. Assumptions'!$B:$B,0))-INDEX('1. Assumptions'!$G:$G,MATCH("Growth Plan Price ($/mo)",'1. Assumptions'!$B:$B,0))) -> 881.24375 | F65: =F27*(INDEX('1. Assumptions'!$G:$G,MATCH("Growth Plan Price ($/mo)",'1. Assumptions'!$B:$B,0))-INDEX('1. Assumptions'!$G:$G,MATCH("Starter Plan Price ($/mo)",'1. Assumptions'!$B:$B,0)))+F35*(INDEX('1. Assumptions'!$G:$G,MATCH("Enterprise Plan Price ($/mo)",'1. Assumptions'!$B:$B,0))-INDEX('1. Assumptions'!$G:$G,MATCH("Growth Plan Price ($/mo)",'1. Assumptions'!$B:$B,0))) -> 927.46955 | G65: =G27*(INDEX('1. Assumptions'!$G:$G,MATCH("Growth Plan Price ($/mo)",'1. Assumptions'!$B:$B,0))-INDEX('1. Assumptions'!$G:$G,MATCH("Starter Plan Price ($/mo)",'1. Assumptions'!$B:$B,0)))+G35*(INDEX('1. Assumptions'!$G:$G,MATCH("Enterprise Plan Price ($/mo)",'1. Assumptions'!$B:$B,0))-INDEX('1. Assumptions'!$G:$G,MATCH("Growth Plan Price ($/mo)",'1. Assumptions'!$B:$B,0))) -> 973.39628 | H65: =H27*(INDEX('1. Assumptions'!$G:$G,MATCH("Growth Plan Price ($/mo)",'1. Assumptions'!$B:$B,0))-INDEX('1. Assumptions'!$G:$G,MATCH("Starter Plan Price ($/mo)",'1. Assumptions'!$B:$B,0)))+H35*(INDEX('1. Assumptions'!$G:$G,MATCH("Enterprise Plan Price ($/mo)",'1. Assumptions'!$B:$B,0))-INDEX('1. Assumptions'!$G:$G,MATCH("Growth Plan Price ($/mo)",'1. Assumptions'!$B:$B,0))) -> 1020.505 | I65: =I27*(INDEX('1. Assumptions'!$G:$G,MATCH("Growth Plan Price ($/mo)",'1. Assumptions'!$B:$B,0))-INDEX('1. Assumptions'!$G:$G,MATCH("Starter Plan Price ($/mo)",'1. Assumptions'!$B:$B,0)))+I35*(INDEX('1. Assumptions'!$G:$G,MATCH("Enterprise Plan Price ($/mo)",'1. Assumptions'!$B:$B,0))-INDEX('1. Assumptions'!$G:$G,MATCH("Growth Plan Price ($/mo)",'1. Assumptions'!$B:$B,0))) -> 1070.0565 | J65: =J27*(INDEX('1. Assumptions'!$G:$G,MATCH("Growth Plan Price ($/mo)",'1. Assumptions'!$B:$B,0))-INDEX('1. Assumptions'!$G:$G,MATCH("Starter Plan Price ($/mo)",'1. Assumptions'!$B:$B,0)))+J35*(INDEX('1. Assumptions'!$G:$G,MATCH("Enterprise Plan Price ($/mo)",'1. Assumptions'!$B:$B,0))-INDEX('1. Assumptions'!$G:$G,MATCH("Growth Plan Price ($/mo)",'1. Assumptions'!$B:$B,0))) -> 1123.1516 | K65: =K27*(INDEX('1. Assumptions'!$G:$G,MATCH("Growth Plan Price ($/mo)",'1. Assumptions'!$B:$B,0))-INDEX('1. Assumptions'!$G:$G,MATCH("Starter Plan Price ($/mo)",'1. Assumptions'!$B:$B,0)))+K35*(INDEX('1. Assumptions'!$G:$G,MATCH("Enterprise Plan Price ($/mo)",'1. Assumptions'!$B:$B,0))-INDEX('1. Assumptions'!$G:$G,MATCH("Growth Plan Price ($/mo)",'1. Assumptions'!$B:$B,0))) -> 1180.7787 | ... AA65: =AA27*(INDEX('1. Assumptions'!$G:$G,MATCH("Growth Plan Price ($/mo)",'1. Assumptions'!$B:$B,0))-INDEX('1. Assumptions'!$G:$G,MATCH("Starter Plan Price ($/mo)",'1. Assumptions'!$B:$B,0)))+AA35*(INDEX('1. Assumptions'!$G:$G,MATCH("Enterprise Plan Price ($/mo)",'1. Assumptions'!$B:$B,0))-INDEX('1. Assumptions'!$G:$G,MATCH("Growth Plan Price ($/mo)",'1. Assumptions'!$B:$B,0))) -> 3503.1644
A66: MRR Bridge | B66: Churned MRR | C66: $ | D66: =D28*INDEX('1. Assumptions'!$G:$G,MATCH("Starter Plan Price ($/mo)",'1. Assumptions'!$B:$B,0))+D36*INDEX('1. Assumptions'!$G:$G,MATCH("Growth Plan Price ($/mo)",'1. Assumptions'!$B:$B,0))+D43*INDEX('1. Assumptions'!$G:$G,MATCH("Enterprise Plan Price ($/mo)",'1. Assumptions'!$B:$B,0)) -> 0 | E66: =E28*INDEX('1. Assumptions'!$G:$G,MATCH("Starter Plan Price ($/mo)",'1. Assumptions'!$B:$B,0))+E36*INDEX('1. Assumptions'!$G:$G,MATCH("Growth Plan Price ($/mo)",'1. Assumptions'!$B:$B,0))+E43*INDEX('1. Assumptions'!$G:$G,MATCH("Enterprise Plan Price ($/mo)",'1. Assumptions'!$B:$B,0)) -> 1364.3397 | F66: =F28*INDEX('1. Assumptions'!$G:$G,MATCH("Starter Plan Price ($/mo)",'1. Assumptions'!$B:$B,0))+F36*INDEX('1. Assumptions'!$G:$G,MATCH("Growth Plan Price ($/mo)",'1. Assumptions'!$B:$B,0))+F43*INDEX('1. Assumptions'!$G:$G,MATCH("Enterprise Plan Price ($/mo)",'1. Assumptions'!$B:$B,0)) -> 1428.4831 | G66: =G28*INDEX('1. Assumptions'!$G:$G,MATCH("Starter Plan Price ($/mo)",'1. Assumptions'!$B:$B,0))+G36*INDEX('1. Assumptions'!$G:$G,MATCH("Growth Plan Price ($/mo)",'1. Assumptions'!$B:$B,0))+G43*INDEX('1. Assumptions'!$G:$G,MATCH("Enterprise Plan Price ($/mo)",'1. Assumptions'!$B:$B,0)) -> 1493.8123 | H66: =H28*INDEX('1. Assumptions'!$G:$G,MATCH("Starter Plan Price ($/mo)",'1. Assumptions'!$B:$B,0))+H36*INDEX('1. Assumptions'!$G:$G,MATCH("Growth Plan Price ($/mo)",'1. Assumptions'!$B:$B,0))+H43*INDEX('1. Assumptions'!$G:$G,MATCH("Enterprise Plan Price ($/mo)",'1. Assumptions'!$B:$B,0)) -> 1561.7812 | I66: =I28*INDEX('1. Assumptions'!$G:$G,MATCH("Starter Plan Price ($/mo)",'1. Assumptions'!$B:$B,0))+I36*INDEX('1. Assumptions'!$G:$G,MATCH("Growth Plan Price ($/mo)",'1. Assumptions'!$B:$B,0))+I43*INDEX('1. Assumptions'!$G:$G,MATCH("Enterprise Plan Price ($/mo)",'1. Assumptions'!$B:$B,0)) -> 1633.6706 | J66: =J28*INDEX('1. Assumptions'!$G:$G,MATCH("Starter Plan Price ($/mo)",'1. Assumptions'!$B:$B,0))+J36*INDEX('1. Assumptions'!$G:$G,MATCH("Growth Plan Price ($/mo)",'1. Assumptions'!$B:$B,0))+J43*INDEX('1. Assumptions'!$G:$G,MATCH("Enterprise Plan Price ($/mo)",'1. Assumptions'!$B:$B,0)) -> 1718.698 | K66: =K28*INDEX('1. Assumptions'!$G:$G,MATCH("Starter Plan Price ($/mo)",'1. Assumptions'!$B:$B,0))+K36*INDEX('1. Assumptions'!$G:$G,MATCH("Growth Plan Price ($/mo)",'1. Assumptions'!$B:$B,0))+K43*INDEX('1. Assumptions'!$G:$G,MATCH("Enterprise Plan Price ($/mo)",'1. Assumptions'!$B:$B,0)) -> 1810.3419 | ... AA66: =AA28*INDEX('1. Assumptions'!$G:$G,MATCH("Starter Plan Price ($/mo)",'1. Assumptions'!$B:$B,0))+AA36*INDEX('1. Assumptions'!$G:$G,MATCH("Growth Plan Price ($/mo)",'1. Assumptions'!$B:$B,0))+AA43*INDEX('1. Assumptions'!$G:$G,MATCH("Enterprise Plan Price ($/mo)",'1. Assumptions'!$B:$B,0)) -> 5168.4015
A67: MRR Bridge | B67: Contraction MRR | C67: $ | D67: =D62*INDEX('1. Assumptions'!$G:$G,MATCH("Contraction MRR Rate (monthly)",'1. Assumptions'!$B:$B,0)) -> 415.2 | E67: =E62*INDEX('1. Assumptions'!$G:$G,MATCH("Contraction MRR Rate (monthly)",'1. Assumptions'!$B:$B,0)) -> 444.633 | F67: =F62*INDEX('1. Assumptions'!$G:$G,MATCH("Contraction MRR Rate (monthly)",'1. Assumptions'!$B:$B,0)) -> 461.29371 | G67: =G62*INDEX('1. Assumptions'!$G:$G,MATCH("Contraction MRR Rate (monthly)",'1. Assumptions'!$B:$B,0)) -> 478.41764 | H67: =H62*INDEX('1. Assumptions'!$G:$G,MATCH("Contraction MRR Rate (monthly)",'1. Assumptions'!$B:$B,0)) -> 496.3669 | I67: =I62*INDEX('1. Assumptions'!$G:$G,MATCH("Contraction MRR Rate (monthly)",'1. Assumptions'!$B:$B,0)) -> 515.46579 | J67: =J62*INDEX('1. Assumptions'!$G:$G,MATCH("Contraction MRR Rate (monthly)",'1. Assumptions'!$B:$B,0)) -> 542.00286 | K67: =K62*INDEX('1. Assumptions'!$G:$G,MATCH("Contraction MRR Rate (monthly)",'1. Assumptions'!$B:$B,0)) -> 570.54936 | ... AA67: =AA62*INDEX('1. Assumptions'!$G:$G,MATCH("Contraction MRR Rate (monthly)",'1. Assumptions'!$B:$B,0)) -> 1583.4939
A68: MRR Bridge | B68: Ending Subscription MRR (Bridge) | C68: $ | D68: =D62+D63+D64+D65-D66-D67 -> 44463.3 | E68: =E62+E63+E64+E65-E66-E67 -> 46129.371 | F68: =F62+F63+F64+F65-F66-F67 -> 47841.764 | G68: =G62+G63+G64+G65-G66-G67 -> 49636.69 | H68: =H62+H63+H64+H65-H66-H67 -> 51546.579 | I68: =I62+I63+I64+I65-I66-I67 -> 54200.286 | J68: =J62+J63+J64+J65-J66-J67 -> 57054.936 | K68: =K62+K63+K64+K65-K66-K67 -> 60140.159 | ... AA68: =AA62+AA63+AA64+AA65-AA66-AA67 -> 170586.03
A69: MRR Bridge | B69: MRR Bridge Check (should = 0) | C69: $ | D69: =D68-D59 -> 0 | E69: =E68-E59 -> 0 | F69: =F68-F59 -> 0 | G69: =G68-G59 -> 0 | H69: =H68-H59 -> 0 | I69: =I68-I59 -> 0 | J69: =J68-J59 -> 0 | K69: =K68-K59 -> 0 | ... AA69: =AA68-AA59 -> 0 | AC69: MUST = 0. If not zero, check roll-forward logic. | AD69: =IF(ABS(D69)>1,"ERROR","OK") -> OK
A71: § 10 AI USAGE REVENUE
A72: AI Usage Revenue | B72: AI Usage Revenue Active? | C72: Yes/No | D72: =IF(D5>=INDEX('1. Assumptions'!$G:$G,MATCH("AI Usage Revenue Start Month",'1. Assumptions'!$B:$B,0)),"Yes","No") -> No | E72: =IF(E5>=INDEX('1. Assumptions'!$G:$G,MATCH("AI Usage Revenue Start Month",'1. Assumptions'!$B:$B,0)),"Yes","No") -> No | F72: =IF(F5>=INDEX('1. Assumptions'!$G:$G,MATCH("AI Usage Revenue Start Month",'1. Assumptions'!$B:$B,0)),"Yes","No") -> No | G72: =IF(G5>=INDEX('1. Assumptions'!$G:$G,MATCH("AI Usage Revenue Start Month",'1. Assumptions'!$B:$B,0)),"Yes","No") -> No | H72: =IF(H5>=INDEX('1. Assumptions'!$G:$G,MATCH("AI Usage Revenue Start Month",'1. Assumptions'!$B:$B,0)),"Yes","No") -> No | I72: =IF(I5>=INDEX('1. Assumptions'!$G:$G,MATCH("AI Usage Revenue Start Month",'1. Assumptions'!$B:$B,0)),"Yes","No") -> No | J72: =IF(J5>=INDEX('1. Assumptions'!$G:$G,MATCH("AI Usage Revenue Start Month",'1. Assumptions'!$B:$B,0)),"Yes","No") -> No | K72: =IF(K5>=INDEX('1. Assumptions'!$G:$G,MATCH("AI Usage Revenue Start Month",'1. Assumptions'!$B:$B,0)),"Yes","No") -> No | ... AA72: =IF(AA5>=INDEX('1. Assumptions'!$G:$G,MATCH("AI Usage Revenue Start Month",'1. Assumptions'!$B:$B,0)),"Yes","No") -> Yes
A73: AI Usage Revenue | B73: Total Eligible Paid Customers | C73: Customers | D73: =D50 -> 524 | E73: =E50 -> 550.0952 | F73: =F50 -> 576.28482 | G73: =G50 -> 603.30932 | H73: =H50 -> 631.80629 | I73: =I50 -> 663.3392 | J73: =J50 -> 697.477 | K73: =K50 -> 734.70374 | ... AA73: =AA50 -> 2192.5733
A74: AI Usage Revenue | B74: % Customers Exceeding Query Limit | C74: % | D74: =IF(D5<INDEX('1. Assumptions'!$G:$G,MATCH("AI Usage Revenue Start Month",'1. Assumptions'!$B:$B,0)),0,INDEX('1. Assumptions'!$G:$G,MATCH("% Customers Exceeding Query Limit ; M24",'1. Assumptions'!$B:$B,0))*(D5-INDEX('1. Assumptions'!$G:$G,MATCH("AI Usage Revenue Start Month",'1. Assumptions'!$B:$B,0))+1)/('3. Revenue Model'!$AA$5-INDEX('1. Assumptions'!$G:$G,MATCH("AI Usage Revenue Start Month",'1. Assumptions'!$B:$B,0))+1)) -> 0 | E74: =IF(E5<INDEX('1. Assumptions'!$G:$G,MATCH("AI Usage Revenue Start Month",'1. Assumptions'!$B:$B,0)),0,INDEX('1. Assumptions'!$G:$G,MATCH("% Customers Exceeding Query Limit ; M24",'1. Assumptions'!$B:$B,0))*(E5-INDEX('1. Assumptions'!$G:$G,MATCH("AI Usage Revenue Start Month",'1. Assumptions'!$B:$B,0))+1)/('3. Revenue Model'!$AA$5-INDEX('1. Assumptions'!$G:$G,MATCH("AI Usage Revenue Start Month",'1. Assumptions'!$B:$B,0))+1)) -> 0 | F74: =IF(F5<INDEX('1. Assumptions'!$G:$G,MATCH("AI Usage Revenue Start Month",'1. Assumptions'!$B:$B,0)),0,INDEX('1. Assumptions'!$G:$G,MATCH("% Customers Exceeding Query Limit ; M24",'1. Assumptions'!$B:$B,0))*(F5-INDEX('1. Assumptions'!$G:$G,MATCH("AI Usage Revenue Start Month",'1. Assumptions'!$B:$B,0))+1)/('3. Revenue Model'!$AA$5-INDEX('1. Assumptions'!$G:$G,MATCH("AI Usage Revenue Start Month",'1. Assumptions'!$B:$B,0))+1)) -> 0 | G74: =IF(G5<INDEX('1. Assumptions'!$G:$G,MATCH("AI Usage Revenue Start Month",'1. Assumptions'!$B:$B,0)),0,INDEX('1. Assumptions'!$G:$G,MATCH("% Customers Exceeding Query Limit ; M24",'1. Assumptions'!$B:$B,0))*(G5-INDEX('1. Assumptions'!$G:$G,MATCH("AI Usage Revenue Start Month",'1. Assumptions'!$B:$B,0))+1)/('3. Revenue Model'!$AA$5-INDEX('1. Assumptions'!$G:$G,MATCH("AI Usage Revenue Start Month",'1. Assumptions'!$B:$B,0))+1)) -> 0 | H74: =IF(H5<INDEX('1. Assumptions'!$G:$G,MATCH("AI Usage Revenue Start Month",'1. Assumptions'!$B:$B,0)),0,INDEX('1. Assumptions'!$G:$G,MATCH("% Customers Exceeding Query Limit ; M24",'1. Assumptions'!$B:$B,0))*(H5-INDEX('1. Assumptions'!$G:$G,MATCH("AI Usage Revenue Start Month",'1. Assumptions'!$B:$B,0))+1)/('3. Revenue Model'!$AA$5-INDEX('1. Assumptions'!$G:$G,MATCH("AI Usage Revenue Start Month",'1. Assumptions'!$B:$B,0))+1)) -> 0 | I74: =IF(I5<INDEX('1. Assumptions'!$G:$G,MATCH("AI Usage Revenue Start Month",'1. Assumptions'!$B:$B,0)),0,INDEX('1. Assumptions'!$G:$G,MATCH("% Customers Exceeding Query Limit ; M24",'1. Assumptions'!$B:$B,0))*(I5-INDEX('1. Assumptions'!$G:$G,MATCH("AI Usage Revenue Start Month",'1. Assumptions'!$B:$B,0))+1)/('3. Revenue Model'!$AA$5-INDEX('1. Assumptions'!$G:$G,MATCH("AI Usage Revenue Start Month",'1. Assumptions'!$B:$B,0))+1)) -> 0 | J74: =IF(J5<INDEX('1. Assumptions'!$G:$G,MATCH("AI Usage Revenue Start Month",'1. Assumptions'!$B:$B,0)),0,INDEX('1. Assumptions'!$G:$G,MATCH("% Customers Exceeding Query Limit ; M24",'1. Assumptions'!$B:$B,0))*(J5-INDEX('1. Assumptions'!$G:$G,MATCH("AI Usage Revenue Start Month",'1. Assumptions'!$B:$B,0))+1)/('3. Revenue Model'!$AA$5-INDEX('1. Assumptions'!$G:$G,MATCH("AI Usage Revenue Start Month",'1. Assumptions'!$B:$B,0))+1)) -> 0 | K74: =IF(K5<INDEX('1. Assumptions'!$G:$G,MATCH("AI Usage Revenue Start Month",'1. Assumptions'!$B:$B,0)),0,INDEX('1. Assumptions'!$G:$G,MATCH("% Customers Exceeding Query Limit ; M24",'1. Assumptions'!$B:$B,0))*(K5-INDEX('1. Assumptions'!$G:$G,MATCH("AI Usage Revenue Start Month",'1. Assumptions'!$B:$B,0))+1)/('3. Revenue Model'!$AA$5-INDEX('1. Assumptions'!$G:$G,MATCH("AI Usage Revenue Start Month",'1. Assumptions'!$B:$B,0))+1)) -> 0 | ... AA74: =IF(AA5<INDEX('1. Assumptions'!$G:$G,MATCH("AI Usage Revenue Start Month",'1. Assumptions'!$B:$B,0)),0,INDEX('1. Assumptions'!$G:$G,MATCH("% Customers Exceeding Query Limit ; M24",'1. Assumptions'!$B:$B,0))*(AA5-INDEX('1. Assumptions'!$G:$G,MATCH("AI Usage Revenue Start Month",'1. Assumptions'!$B:$B,0))+1)/('3. Revenue Model'!$AA$5-INDEX('1. Assumptions'!$G:$G,MATCH("AI Usage Revenue Start Month",'1. Assumptions'!$B:$B,0))+1)) -> 0.2 | AC74: Ramp: 0 until AI Usage Start Month, then linear ramp to M24 target %
A75: AI Usage Revenue | B75: Customers Exceeding Query Limit | C75: Customers | D75: =D73*D74 -> 0 | E75: =E73*E74 -> 0 | F75: =F73*F74 -> 0 | G75: =G73*G74 -> 0 | H75: =H73*H74 -> 0 | I75: =I73*I74 -> 0 | J75: =J73*J74 -> 0 | K75: =K73*K74 -> 0 | ... AA75: =AA73*AA74 -> 438.51465
A76: AI Usage Revenue | B76: Avg Overage Queries per Exceeding Customer | C76: Queries | D76: =INDEX('1. Assumptions'!$G:$G,MATCH("Avg Overage Queries Per Exceeding Customer/mo",'1. Assumptions'!$B:$B,0)) -> 250 | E76: =INDEX('1. Assumptions'!$G:$G,MATCH("Avg Overage Queries Per Exceeding Customer/mo",'1. Assumptions'!$B:$B,0)) -> 250 | F76: =INDEX('1. Assumptions'!$G:$G,MATCH("Avg Overage Queries Per Exceeding Customer/mo",'1. Assumptions'!$B:$B,0)) -> 250 | G76: =INDEX('1. Assumptions'!$G:$G,MATCH("Avg Overage Queries Per Exceeding Customer/mo",'1. Assumptions'!$B:$B,0)) -> 250 | H76: =INDEX('1. Assumptions'!$G:$G,MATCH("Avg Overage Queries Per Exceeding Customer/mo",'1. Assumptions'!$B:$B,0)) -> 250 | I76: =INDEX('1. Assumptions'!$G:$G,MATCH("Avg Overage Queries Per Exceeding Customer/mo",'1. Assumptions'!$B:$B,0)) -> 250 | J76: =INDEX('1. Assumptions'!$G:$G,MATCH("Avg Overage Queries Per Exceeding Customer/mo",'1. Assumptions'!$B:$B,0)) -> 250 | K76: =INDEX('1. Assumptions'!$G:$G,MATCH("Avg Overage Queries Per Exceeding Customer/mo",'1. Assumptions'!$B:$B,0)) -> 250 | ... AA76: =INDEX('1. Assumptions'!$G:$G,MATCH("Avg Overage Queries Per Exceeding Customer/mo",'1. Assumptions'!$B:$B,0)) -> 250
A77: AI Usage Revenue | B77: AI Overage Price per Query | C77: $/query | D77: =INDEX('1. Assumptions'!$G:$G,MATCH("AI Overage Price Per Query ($/query)",'1. Assumptions'!$B:$B,0)) -> 0.1 | E77: =INDEX('1. Assumptions'!$G:$G,MATCH("AI Overage Price Per Query ($/query)",'1. Assumptions'!$B:$B,0)) -> 0.1 | F77: =INDEX('1. Assumptions'!$G:$G,MATCH("AI Overage Price Per Query ($/query)",'1. Assumptions'!$B:$B,0)) -> 0.1 | G77: =INDEX('1. Assumptions'!$G:$G,MATCH("AI Overage Price Per Query ($/query)",'1. Assumptions'!$B:$B,0)) -> 0.1 | H77: =INDEX('1. Assumptions'!$G:$G,MATCH("AI Overage Price Per Query ($/query)",'1. Assumptions'!$B:$B,0)) -> 0.1 | I77: =INDEX('1. Assumptions'!$G:$G,MATCH("AI Overage Price Per Query ($/query)",'1. Assumptions'!$B:$B,0)) -> 0.1 | J77: =INDEX('1. Assumptions'!$G:$G,MATCH("AI Overage Price Per Query ($/query)",'1. Assumptions'!$B:$B,0)) -> 0.1 | K77: =INDEX('1. Assumptions'!$G:$G,MATCH("AI Overage Price Per Query ($/query)",'1. Assumptions'!$B:$B,0)) -> 0.1 | ... AA77: =INDEX('1. Assumptions'!$G:$G,MATCH("AI Overage Price Per Query ($/query)",'1. Assumptions'!$B:$B,0)) -> 0.1
A78: AI Usage Revenue | B78: AI Usage Revenue | C78: $ | D78: =D75*D76*D77 -> 0 | E78: =E75*E76*E77 -> 0 | F78: =F75*F76*F77 -> 0 | G78: =G75*G76*G77 -> 0 | H78: =H75*H76*H77 -> 0 | I78: =I75*I76*I77 -> 0 | J78: =J75*J76*J77 -> 0 | K78: =K75*K76*K77 -> 0 | ... AA78: =AA75*AA76*AA77 -> 10962.866 | AC78: Exceeding Customers x Avg Overage Queries x Overage Price per Query
A79: AI Usage Revenue | B79: AI Usage Revenue as % of Subscription MRR | C79: % | D79: =IFERROR(D78/D59,0) -> 0 | E79: =IFERROR(E78/E59,0) -> 0 | F79: =IFERROR(F78/F59,0) -> 0 | G79: =IFERROR(G78/G59,0) -> 0 | H79: =IFERROR(H78/H59,0) -> 0 | I79: =IFERROR(I78/I59,0) -> 0 | J79: =IFERROR(J78/J59,0) -> 0 | K79: =IFERROR(K78/K59,0) -> 0 | ... AA79: =IFERROR(AA78/AA59,0) -> 0.064265908
A81: § 11 IMPLEMENTATION REVENUE (Non-Recurring)
A82: Implementation Revenue | B82: New Enterprise Logos | C82: Customers | D82: =D19 -> 0 | E82: =E19 -> 0 | F82: =F19 -> 0 | G82: =G19 -> 0 | H82: =H19 -> 0 | I82: =I19 -> 1 | J82: =J19 -> 1.07 | K82: =K19 -> 1.1449 | ... AA82: =AA19 -> 3.3799323
A83: Implementation Revenue | B83: Implementation Fee per Logo | C83: $ | D83: =INDEX('1. Assumptions'!$G:$G,MATCH("Enterprise Implementation Fee ($/logo)",'1. Assumptions'!$B:$B,0)) -> 3000 | E83: =INDEX('1. Assumptions'!$G:$G,MATCH("Enterprise Implementation Fee ($/logo)",'1. Assumptions'!$B:$B,0)) -> 3000 | F83: =INDEX('1. Assumptions'!$G:$G,MATCH("Enterprise Implementation Fee ($/logo)",'1. Assumptions'!$B:$B,0)) -> 3000 | G83: =INDEX('1. Assumptions'!$G:$G,MATCH("Enterprise Implementation Fee ($/logo)",'1. Assumptions'!$B:$B,0)) -> 3000 | H83: =INDEX('1. Assumptions'!$G:$G,MATCH("Enterprise Implementation Fee ($/logo)",'1. Assumptions'!$B:$B,0)) -> 3000 | I83: =INDEX('1. Assumptions'!$G:$G,MATCH("Enterprise Implementation Fee ($/logo)",'1. Assumptions'!$B:$B,0)) -> 3000 | J83: =INDEX('1. Assumptions'!$G:$G,MATCH("Enterprise Implementation Fee ($/logo)",'1. Assumptions'!$B:$B,0)) -> 3000 | K83: =INDEX('1. Assumptions'!$G:$G,MATCH("Enterprise Implementation Fee ($/logo)",'1. Assumptions'!$B:$B,0)) -> 3000 | ... AA83: =INDEX('1. Assumptions'!$G:$G,MATCH("Enterprise Implementation Fee ($/logo)",'1. Assumptions'!$B:$B,0)) -> 3000
A84: Implementation Revenue | B84: New Implementation Bookings | C84: $ | D84: =D82*D83 -> 0 | E84: =E82*E83 -> 0 | F84: =F82*F83 -> 0 | G84: =G82*G83 -> 0 | H84: =H82*H83 -> 0 | I84: =I82*I83 -> 3000 | J84: =J82*J83 -> 3210 | K84: =K82*K83 -> 3434.7 | ... AA84: =AA82*AA83 -> 10139.797
A85: Implementation Revenue | B85: Recognized Implementation Revenue | C85: $ | D85: =D84/3 -> 0 | E85: =(E84+D84)/3 -> 0 | F85: =(F84+E84+D84)/3 -> 0 | G85: =(G84+F84+E84)/3 -> 0 | H85: =(H84+G84+F84)/3 -> 0 | I85: =(I84+H84+G84)/3 -> 1000 | J85: =(J84+I84+H84)/3 -> 2070 | K85: =(K84+J84+I84)/3 -> 3214.9 | L85: =(L84+K84+J84)/3 -> 3439.943 | M85: =(M84+L84+K84)/3 -> 3680.739 | ... AA85: =(AA84+Z84+Y84)/3 -> 9490.9112 | AC85: Recognized over 3 months: (Current + Prior + 2-Months-Ago Bookings) / 3
A86: Implementation Revenue | B86: ARR Inclusion Check | C86: Check | D86: =IF(_xlfn.XLOOKUP("Implementation Fee Included in ARR?",'1. Assumptions'!$B:$B,'1. Assumptions'!$G:$G)="No","OK - Excluded from ARR","ERROR - Included in ARR") -> OK - Excluded from ARR | E86: =IF(_xlfn.XLOOKUP("Implementation Fee Included in ARR?",'1. Assumptions'!$B:$B,'1. Assumptions'!$G:$G)="No","OK - Excluded from ARR","ERROR - Included in ARR") -> OK - Excluded from ARR | F86: =IF(_xlfn.XLOOKUP("Implementation Fee Included in ARR?",'1. Assumptions'!$B:$B,'1. Assumptions'!$G:$G)="No","OK - Excluded from ARR","ERROR - Included in ARR") -> OK - Excluded from ARR | G86: =IF(_xlfn.XLOOKUP("Implementation Fee Included in ARR?",'1. Assumptions'!$B:$B,'1. Assumptions'!$G:$G)="No","OK - Excluded from ARR","ERROR - Included in ARR") -> OK - Excluded from ARR | H86: =IF(_xlfn.XLOOKUP("Implementation Fee Included in ARR?",'1. Assumptions'!$B:$B,'1. Assumptions'!$G:$G)="No","OK - Excluded from ARR","ERROR - Included in ARR") -> OK - Excluded from ARR | I86: =IF(_xlfn.XLOOKUP("Implementation Fee Included in ARR?",'1. Assumptions'!$B:$B,'1. Assumptions'!$G:$G)="No","OK - Excluded from ARR","ERROR - Included in ARR") -> OK - Excluded from ARR | J86: =IF(_xlfn.XLOOKUP("Implementation Fee Included in ARR?",'1. Assumptions'!$B:$B,'1. Assumptions'!$G:$G)="No","OK - Excluded from ARR","ERROR - Included in ARR") -> OK - Excluded from ARR | K86: =IF(_xlfn.XLOOKUP("Implementation Fee Included in ARR?",'1. Assumptions'!$B:$B,'1. Assumptions'!$G:$G)="No","OK - Excluded from ARR","ERROR - Included in ARR") -> OK - Excluded from ARR | ... AA86: =IF(_xlfn.XLOOKUP("Implementation Fee Included in ARR?",'1. Assumptions'!$B:$B,'1. Assumptions'!$G:$G)="No","OK - Excluded from ARR","ERROR - Included in ARR") -> OK - Excluded from ARR
A88: § 12 TOTAL REVENUE SUMMARY ★
A89: Revenue Summary | B89: Ending Subscription MRR | C89: $ | D89: =D59 -> 44463.3 | E89: =E59 -> 46129.371 | F89: =F59 -> 47841.764 | G89: =G59 -> 49636.69 | H89: =H59 -> 51546.579 | I89: =I59 -> 54200.286 | J89: =J59 -> 57054.936 | K89: =K59 -> 60140.159 | ... AA89: =AA59 -> 170586.03
A90: Revenue Summary | B90: AI Usage Revenue | C90: $ | D90: =D78 -> 0 | E90: =E78 -> 0 | F90: =F78 -> 0 | G90: =G78 -> 0 | H90: =H78 -> 0 | I90: =I78 -> 0 | J90: =J78 -> 0 | K90: =K78 -> 0 | ... AA90: =AA78 -> 10962.866
A91: Revenue Summary | B91: Total Recurring MRR | C91: $ | D91: =D89+D90 -> 44463.3 | E91: =E89+E90 -> 46129.371 | F91: =F89+F90 -> 47841.764 | G91: =G89+G90 -> 49636.69 | H91: =H89+H90 -> 51546.579 | I91: =I89+I90 -> 54200.286 | J91: =J89+J90 -> 57054.936 | K91: =K89+K90 -> 60140.159 | ... AA91: =AA89+AA90 -> 181548.9
A92: Revenue Summary | B92: Implementation Revenue (Non-Recurring) | C92: $ | D92: =D85 -> 0 | E92: =E85 -> 0 | F92: =F85 -> 0 | G92: =G85 -> 0 | H92: =H85 -> 0 | I92: =I85 -> 1000 | J92: =J85 -> 2070 | K92: =K85 -> 3214.9 | ... AA92: =AA85 -> 9490.9112
A93: Revenue Summary | B93: Total Monthly Revenue | C93: $ | D93: =D91+D92 -> 44463.3 | E93: =E91+E92 -> 46129.371 | F93: =F91+F92 -> 47841.764 | G93: =G91+G92 -> 49636.69 | H93: =H91+H92 -> 51546.579 | I93: =I91+I92 -> 55200.286 | J93: =J91+J92 -> 59124.936 | K93: =K91+K92 -> 63355.059 | ... AA93: =AA91+AA92 -> 191039.81
A94: Revenue Summary | B94: ARR (Recurring Only) | C94: $ | D94: =D91*12 -> 533559.6 | E94: =E91*12 -> 553552.45 | F94: =F91*12 -> 574101.17 | G94: =G91*12 -> 595640.27 | H94: =H91*12 -> 618558.95 | I94: =I91*12 -> 650403.44 | J94: =J91*12 -> 684659.23 | K94: =K91*12 -> 721681.91 | ... AA94: =AA91*12 -> 2178586.8 | AC94: ARR = Total Recurring MRR × 12. Excludes implementation fees. | AD94: KEY ARR METRIC
A95: Revenue Summary | B95: Subscription ARR | C95: $ | D95: =D89*12 -> 533559.6 | E95: =E89*12 -> 553552.45 | F95: =F89*12 -> 574101.17 | G95: =G89*12 -> 595640.27 | H95: =H89*12 -> 618558.95 | I95: =I89*12 -> 650403.44 | J95: =J89*12 -> 684659.23 | K95: =K89*12 -> 721681.91 | ... AA95: =AA89*12 -> 2047032.4
A96: Revenue Summary | B96: AI Usage ARR Run-Rate | C96: $ | D96: =D90*12 -> 0 | E96: =E90*12 -> 0 | F96: =F90*12 -> 0 | G96: =G90*12 -> 0 | H96: =H90*12 -> 0 | I96: =I90*12 -> 0 | J96: =J90*12 -> 0 | K96: =K90*12 -> 0 | ... AA96: =AA90*12 -> 131554.4
A97: Revenue Summary | B97: MRR Growth % (MoM) | C97: % | D97: 0 | E97: =IFERROR(E91/D91-1,0) -> 0.037470701 | F97: =IFERROR(F91/E91-1,0) -> 0.037121537 | G97: =IFERROR(G91/F91-1,0) -> 0.03751796 | H97: =IFERROR(H91/G91-1,0) -> 0.038477382 | I97: =IFERROR(I91/H91-1,0) -> 0.051481726 | J97: =IFERROR(J91/I91-1,0) -> 0.052668533 | K97: =IFERROR(K91/J91-1,0) -> 0.054074602 | L97: =IFERROR(L91/K91-1,0) -> 0.055627185 | ... AA97: =IFERROR(AA91/Z91-1,0) -> 0.081935207
A99: § 13 REVENUE KPIs (DASHBOARD FEED)
A100: Revenue KPIs | B100: Total Paid Customers | C100: Customers | D100: =D50 -> 524 | E100: =E50 -> 550.0952 | F100: =F50 -> 576.28482 | G100: =G50 -> 603.30932 | H100: =H50 -> 631.80629 | I100: =I50 -> 663.3392 | J100: =J50 -> 697.477 | K100: =K50 -> 734.70374 | ... AA100: =AA50 -> 2192.5733
A101: Revenue KPIs | B101: ARPU (Total Recurring) | C101: $/customer | D101: =IFERROR(D91/D100,0) -> 84.853626 | E101: =IFERROR(E91/E100,0) -> 83.857069 | F101: =IFERROR(F91/F100,0) -> 83.017569 | G101: =IFERROR(G91/G100,0) -> 82.274031 | H101: =IFERROR(H91/H100,0) -> 81.58605 | I101: =IFERROR(I91/I100,0) -> 81.708252 | J101: =IFERROR(J91/J100,0) -> 81.801889 | K101: =IFERROR(K91/K100,0) -> 81.856339 | ... AA101: =IFERROR(AA91/AA100,0) -> 82.801748
A102: Revenue KPIs | B102: Subscription ARPU | C102: $/customer | D102: =IFERROR(D89/D100,0) -> 84.853626 | E102: =IFERROR(E89/E100,0) -> 83.857069 | F102: =IFERROR(F89/F100,0) -> 83.017569 | G102: =IFERROR(G89/G100,0) -> 82.274031 | H102: =IFERROR(H89/H100,0) -> 81.58605 | I102: =IFERROR(I89/I100,0) -> 81.708252 | J102: =IFERROR(J89/J100,0) -> 81.801889 | K102: =IFERROR(K89/K100,0) -> 81.856339 | ... AA102: =IFERROR(AA89/AA100,0) -> 77.801748
A103: Revenue KPIs | B103: AI Usage % of Recurring MRR | C103: % | D103: =IFERROR(D90/D91,0) -> 0 | E103: =IFERROR(E90/E91,0) -> 0 | F103: =IFERROR(F90/F91,0) -> 0 | G103: =IFERROR(G90/G91,0) -> 0 | H103: =IFERROR(H90/H91,0) -> 0 | I103: =IFERROR(I90/I91,0) -> 0 | J103: =IFERROR(J90/J91,0) -> 0 | K103: =IFERROR(K90/K91,0) -> 0 | ... AA103: =IFERROR(AA90/AA91,0) -> 0.060385198
A104: Revenue KPIs | B104: Enterprise Mix % of Subscription MRR | C104: % | D104: =IFERROR(D56/D89,0) -> 0.0060623031 | E104: =IFERROR(E56/E89,0) -> 0.011918115 | F104: =IFERROR(F56/F89,0) -> 0.017449972 | G104: =IFERROR(G56/G89,0) -> 0.022674339 | H104: =IFERROR(H56/H89,0) -> 0.027595007 | I104: =IFERROR(I56/I89,0) -> 0.042904257 | J104: =IFERROR(J56/J89,0) -> 0.057315022 | K104: =IFERROR(K56/K89,0) -> 0.07083071 | ... AA104: =IFERROR(AA56/AA89,0) -> 0.17653147
A105: Revenue KPIs | B105: Free-to-Paid Conversion Rate | C105: % | D105: =IFERROR(D12/D9,0) -> 0.04 | E105: =IFERROR(E12/E9,0) -> 0.04 | F105: =IFERROR(F12/F9,0) -> 0.04 | G105: =IFERROR(G12/G9,0) -> 0.04 | H105: =IFERROR(H12/H9,0) -> 0.04 | I105: =IFERROR(I12/I9,0) -> 0.04 | J105: =IFERROR(J12/J9,0) -> 0.04 | K105: =IFERROR(K12/K9,0) -> 0.04 | ... AA105: =IFERROR(AA12/AA9,0) -> 0.04
A106: Revenue KPIs | B106: Logo Churn Rate | C106: % | D106: =D51 -> 0 | E106: =E51 -> 0.034551151 | F106: =F51 -> 0.034630335 | G106: =G51 -> 0.034688809 | H106: =H51 -> 0.034735732 | I106: =I51 -> 0.034777308 | J106: =J51 -> 0.034785487 | K106: =K51 -> 0.034796482 | ... AA106: =AA51 -> 0.035544859
A107: Revenue KPIs | B107: Net New MRR | C107: $ | D107: =D91 -> 44463.3 | E107: =E91-D91 -> 1666.071 | F107: =F91-E91 -> 1712.3932 | G107: =G91-F91 -> 1794.9254 | H107: =H91-G91 -> 1909.8898 | I107: =I91-H91 -> 2653.7069 | J107: =J91-I91 -> 2854.6495 | K107: =K91-J91 -> 3085.2229 | L107: =L91-K91 -> 3345.4277 | ... AA107: =AA91-Z91 -> 13748.741
A109: § 14 ERROR CHECKS & MODEL VALIDATION
A110: Checks | B110: Starter Roll-Forward Check (should = 0) | C110: Customers | D110: =D24+D25+D26-D27-D28-D29 -> 0 | E110: =E24+E25+E26-E27-E28-E29 -> 0 | F110: =F24+F25+F26-F27-F28-F29 -> 0 | G110: =G24+G25+G26-G27-G28-G29 -> 0 | H110: =H24+H25+H26-H27-H28-H29 -> 0 | I110: =I24+I25+I26-I27-I28-I29 -> 0 | J110: =J24+J25+J26-J27-J28-J29 -> 0 | K110: =K24+K25+K26-K27-K28-K29 -> 0 | ... AA110: =AA24+AA25+AA26-AA27-AA28-AA29 -> 0
A111: Checks | B111: Growth Roll-Forward Check (should = 0) | C111: Customers | D111: =D32+D33+D34-D35-D36-D37 -> 0 | E111: =E32+E33+E34-E35-E36-E37 -> 0 | F111: =F32+F33+F34-F35-F36-F37 -> 0 | G111: =G32+G33+G34-G35-G36-G37 -> 0 | H111: =H32+H33+H34-H35-H36-H37 -> 0 | I111: =I32+I33+I34-I35-I36-I37 -> 0 | J111: =J32+J33+J34-J35-J36-J37 -> 0 | K111: =K32+K33+K34-K35-K36-K37 -> 0 | ... AA111: =AA32+AA33+AA34-AA35-AA36-AA37 -> 0
A112: Checks | B112: Enterprise Roll-Forward Check (should = 0) | C112: Customers | D112: =D40+D41+D42-D43-D44 -> 0 | E112: =E40+E41+E42-E43-E44 -> 0 | F112: =F40+F41+F42-F43-F44 -> 0 | G112: =G40+G41+G42-G43-G44 -> 0 | H112: =H40+H41+H42-H43-H44 -> 0 | I112: =I40+I41+I42-I43-I44 -> 0 | J112: =J40+J41+J42-J43-J44 -> 0 | K112: =K40+K41+K42-K43-K44 -> 0 | ... AA112: =AA40+AA41+AA42-AA43-AA44 -> 0
A113: Checks | B113: MRR Bridge Check (should = 0) | C113: $ | D113: =D69 -> 0 | E113: =E69 -> 0 | F113: =F69 -> 0 | G113: =G69 -> 0 | H113: =H69 -> 0 | I113: =I69 -> 0 | J113: =J69 -> 0 | K113: =K69 -> 0 | ... AA113: =AA69 -> 0
...

Sheet 4. Headcount
A1: LaunchPlan AI: Headcount Plan
A3: Section | B3: Line Item | C3: Unit | D3: =+'3. Revenue Model'!D2 -> Month 1 | E3: =+'3. Revenue Model'!E2 -> Month 2 | F3: =+'3. Revenue Model'!F2 -> Month 3 | G3: =+'3. Revenue Model'!G2 -> Month 4 | H3: =+'3. Revenue Model'!H2 -> Month 5 | I3: =+'3. Revenue Model'!I2 -> Month 6 | J3: =+'3. Revenue Model'!J2 -> Month 7 | K3: =+'3. Revenue Model'!K2 -> Month 8 | ... AC3: =+'3. Revenue Model'!AC2 -> Check / Source
A4: § 1 CONTROL & TIMELINE
A5: Control | B5: Selected Scenario | C5: Text | D5: =INDEX('1. Assumptions'!$G:$G,MATCH("Selected Scenario",'1. Assumptions'!$B:$B,0)) -> Base | E5: =INDEX('1. Assumptions'!$G:$G,MATCH("Selected Scenario",'1. Assumptions'!$B:$B,0)) -> Base | F5: =INDEX('1. Assumptions'!$G:$G,MATCH("Selected Scenario",'1. Assumptions'!$B:$B,0)) -> Base | G5: =INDEX('1. Assumptions'!$G:$G,MATCH("Selected Scenario",'1. Assumptions'!$B:$B,0)) -> Base | H5: =INDEX('1. Assumptions'!$G:$G,MATCH("Selected Scenario",'1. Assumptions'!$B:$B,0)) -> Base | I5: =INDEX('1. Assumptions'!$G:$G,MATCH("Selected Scenario",'1. Assumptions'!$B:$B,0)) -> Base | J5: =INDEX('1. Assumptions'!$G:$G,MATCH("Selected Scenario",'1. Assumptions'!$B:$B,0)) -> Base | K5: =INDEX('1. Assumptions'!$G:$G,MATCH("Selected Scenario",'1. Assumptions'!$B:$B,0)) -> Base | ... AA5: =INDEX('1. Assumptions'!$G:$G,MATCH("Selected Scenario",'1. Assumptions'!$B:$B,0)) -> Base
A6: Timeline | B6: Month Number | C6: Month | D6: =+'3. Revenue Model'!D5 -> 1 | E6: =+'3. Revenue Model'!E5 -> 2 | F6: =+'3. Revenue Model'!F5 -> 3 | G6: =+'3. Revenue Model'!G5 -> 4 | H6: =+'3. Revenue Model'!H5 -> 5 | I6: =+'3. Revenue Model'!I5 -> 6 | J6: =+'3. Revenue Model'!J5 -> 7 | K6: =+'3. Revenue Model'!K5 -> 8 | ... AA6: =+'3. Revenue Model'!AA5 -> 24
A7: Timeline | B7: Calendar Month | C7: Date | D7: =+'3. Revenue Model'!D6 -> 46023 | E7: =+'3. Revenue Model'!E6 -> 46054 | F7: =+'3. Revenue Model'!F6 -> 46082 | G7: =+'3. Revenue Model'!G6 -> 46113 | H7: =+'3. Revenue Model'!H6 -> 46143 | I7: =+'3. Revenue Model'!I6 -> 46174 | J7: =+'3. Revenue Model'!J6 -> 46204 | K7: =+'3. Revenue Model'!K6 -> 46235 | ... AA7: =+'3. Revenue Model'!AA6 -> 46722
A9: § 2 LINKED OPERATING DRIVERS
A10: Operating Drivers | B10: Total Paid Customers | C10: Customers | D10: =INDEX('3. Revenue Model'!$D:$AA,MATCH($B10,'3. Revenue Model'!$B:$B,0),MATCH(D$3,'3. Revenue Model'!$D$2:$AA$2,0)) -> 524 | E10: =INDEX('3. Revenue Model'!$D:$AA,MATCH($B10,'3. Revenue Model'!$B:$B,0),MATCH(E$3,'3. Revenue Model'!$D$2:$AA$2,0)) -> 550.0952 | F10: =INDEX('3. Revenue Model'!$D:$AA,MATCH($B10,'3. Revenue Model'!$B:$B,0),MATCH(F$3,'3. Revenue Model'!$D$2:$AA$2,0)) -> 576.28482 | G10: =INDEX('3. Revenue Model'!$D:$AA,MATCH($B10,'3. Revenue Model'!$B:$B,0),MATCH(G$3,'3. Revenue Model'!$D$2:$AA$2,0)) -> 603.30932 | H10: =INDEX('3. Revenue Model'!$D:$AA,MATCH($B10,'3. Revenue Model'!$B:$B,0),MATCH(H$3,'3. Revenue Model'!$D$2:$AA$2,0)) -> 631.80629 | I10: =INDEX('3. Revenue Model'!$D:$AA,MATCH($B10,'3. Revenue Model'!$B:$B,0),MATCH(I$3,'3. Revenue Model'!$D$2:$AA$2,0)) -> 663.3392 | J10: =INDEX('3. Revenue Model'!$D:$AA,MATCH($B10,'3. Revenue Model'!$B:$B,0),MATCH(J$3,'3. Revenue Model'!$D$2:$AA$2,0)) -> 697.477 | K10: =INDEX('3. Revenue Model'!$D:$AA,MATCH($B10,'3. Revenue Model'!$B:$B,0),MATCH(K$3,'3. Revenue Model'!$D$2:$AA$2,0)) -> 734.70374 | ... AA10: =INDEX('3. Revenue Model'!$D:$AA,MATCH($B10,'3. Revenue Model'!$B:$B,0),MATCH(AA$3,'3. Revenue Model'!$D$2:$AA$2,0)) -> 2192.5733
A11: Operating Drivers | B11: Ending Starter Customers | C11: Customers | D11: =INDEX('3. Revenue Model'!$D:$AA,MATCH($B11,'3. Revenue Model'!$B:$B,0),MATCH(D$3,'3. Revenue Model'!$D$2:$AA$2,0)) -> 334 | E11: =INDEX('3. Revenue Model'!$D:$AA,MATCH($B11,'3. Revenue Model'!$B:$B,0),MATCH(E$3,'3. Revenue Model'!$D$2:$AA$2,0)) -> 353.88 | F11: =INDEX('3. Revenue Model'!$D:$AA,MATCH($B11,'3. Revenue Model'!$B:$B,0),MATCH(F$3,'3. Revenue Model'!$D$2:$AA$2,0)) -> 373.3072 | G11: =INDEX('3. Revenue Model'!$D:$AA,MATCH($B11,'3. Revenue Model'!$B:$B,0),MATCH(G$3,'3. Revenue Model'!$D$2:$AA$2,0)) -> 393.02374 | H11: =INDEX('3. Revenue Model'!$D:$AA,MATCH($B11,'3. Revenue Model'!$B:$B,0),MATCH(H$3,'3. Revenue Model'!$D$2:$AA$2,0)) -> 413.65249 | I11: =INDEX('3. Revenue Model'!$D:$AA,MATCH($B11,'3. Revenue Model'!$B:$B,0),MATCH(I$3,'3. Revenue Model'!$D$2:$AA$2,0)) -> 435.72856 | J11: =INDEX('3. Revenue Model'!$D:$AA,MATCH($B11,'3. Revenue Model'!$B:$B,0),MATCH(J$3,'3. Revenue Model'!$D$2:$AA$2,0)) -> 459.7243 | K11: =INDEX('3. Revenue Model'!$D:$AA,MATCH($B11,'3. Revenue Model'!$B:$B,0),MATCH(K$3,'3. Revenue Model'!$D$2:$AA$2,0)) -> 486.06931 | ... AA11: =INDEX('3. Revenue Model'!$D:$AA,MATCH($B11,'3. Revenue Model'!$B:$B,0),MATCH(AA$3,'3. Revenue Model'!$D$2:$AA$2,0)) -> 1588.7474
A12: Operating Drivers | B12: Ending Growth Customers | C12: Customers | D12: =INDEX('3. Revenue Model'!$D:$AA,MATCH($B12,'3. Revenue Model'!$B:$B,0),MATCH(D$3,'3. Revenue Model'!$D$2:$AA$2,0)) -> 189.55 | E12: =INDEX('3. Revenue Model'!$D:$AA,MATCH($B12,'3. Revenue Model'!$B:$B,0),MATCH(E$3,'3. Revenue Model'!$D$2:$AA$2,0)) -> 195.29738 | F12: =INDEX('3. Revenue Model'!$D:$AA,MATCH($B12,'3. Revenue Model'!$B:$B,0),MATCH(F$3,'3. Revenue Model'!$D$2:$AA$2,0)) -> 201.5839 | G12: =INDEX('3. Revenue Model'!$D:$AA,MATCH($B12,'3. Revenue Model'!$B:$B,0),MATCH(G$3,'3. Revenue Model'!$D$2:$AA$2,0)) -> 208.40666 | H12: =INDEX('3. Revenue Model'!$D:$AA,MATCH($B12,'3. Revenue Model'!$B:$B,0),MATCH(H$3,'3. Revenue Model'!$D$2:$AA$2,0)) -> 215.77913 | I12: =INDEX('3. Revenue Model'!$D:$AA,MATCH($B12,'3. Revenue Model'!$B:$B,0),MATCH(I$3,'3. Revenue Model'!$D$2:$AA$2,0)) -> 223.72846 | J12: =INDEX('3. Revenue Model'!$D:$AA,MATCH($B12,'3. Revenue Model'!$B:$B,0),MATCH(J$3,'3. Revenue Model'!$D$2:$AA$2,0)) -> 232.29342 | K12: =INDEX('3. Revenue Model'!$D:$AA,MATCH($B12,'3. Revenue Model'!$B:$B,0),MATCH(K$3,'3. Revenue Model'!$D$2:$AA$2,0)) -> 241.52297 | ... AA12: =INDEX('3. Revenue Model'!$D:$AA,MATCH($B12,'3. Revenue Model'!$B:$B,0),MATCH(AA$3,'3. Revenue Model'!$D$2:$AA$2,0)) -> 553.55241
A13: Operating Drivers | B13: Ending Enterprise Customers | C13: Customers | D13: =INDEX('3. Revenue Model'!$D:$AA,MATCH($B13,'3. Revenue Model'!$B:$B,0),MATCH(D$3,'3. Revenue Model'!$D$2:$AA$2,0)) -> 0.45 | E13: =INDEX('3. Revenue Model'!$D:$AA,MATCH($B13,'3. Revenue Model'!$B:$B,0),MATCH(E$3,'3. Revenue Model'!$D$2:$AA$2,0)) -> 0.91782162 | F13: =INDEX('3. Revenue Model'!$D:$AA,MATCH($B13,'3. Revenue Model'!$B:$B,0),MATCH(F$3,'3. Revenue Model'!$D$2:$AA$2,0)) -> 1.3937186 | G13: =INDEX('3. Revenue Model'!$D:$AA,MATCH($B13,'3. Revenue Model'!$B:$B,0),MATCH(G$3,'3. Revenue Model'!$D$2:$AA$2,0)) -> 1.8789301 | H13: =INDEX('3. Revenue Model'!$D:$AA,MATCH($B13,'3. Revenue Model'!$B:$B,0),MATCH(H$3,'3. Revenue Model'!$D$2:$AA$2,0)) -> 2.3746715 | I13: =INDEX('3. Revenue Model'!$D:$AA,MATCH($B13,'3. Revenue Model'!$B:$B,0),MATCH(I$3,'3. Revenue Model'!$D$2:$AA$2,0)) -> 3.8821753 | J13: =INDEX('3. Revenue Model'!$D:$AA,MATCH($B13,'3. Revenue Model'!$B:$B,0),MATCH(J$3,'3. Revenue Model'!$D$2:$AA$2,0)) -> 5.4592737 | K13: =INDEX('3. Revenue Model'!$D:$AA,MATCH($B13,'3. Revenue Model'!$B:$B,0),MATCH(K$3,'3. Revenue Model'!$D$2:$AA$2,0)) -> 7.1114694 | ... AA13: =INDEX('3. Revenue Model'!$D:$AA,MATCH($B13,'3. Revenue Model'!$B:$B,0),MATCH(AA$3,'3. Revenue Model'!$D$2:$AA$2,0)) -> 50.27346
A14: Operating Drivers | B14: New Enterprise Logos | C14: Customers | D14: =INDEX('3. Revenue Model'!$D:$AA,MATCH($B14,'3. Revenue Model'!$B:$B,0),MATCH(D$3,'3. Revenue Model'!$D$2:$AA$2,0)) -> 0 | E14: =INDEX('3. Revenue Model'!$D:$AA,MATCH($B14,'3. Revenue Model'!$B:$B,0),MATCH(E$3,'3. Revenue Model'!$D$2:$AA$2,0)) -> 0 | F14: =INDEX('3. Revenue Model'!$D:$AA,MATCH($B14,'3. Revenue Model'!$B:$B,0),MATCH(F$3,'3. Revenue Model'!$D$2:$AA$2,0)) -> 0 | G14: =INDEX('3. Revenue Model'!$D:$AA,MATCH($B14,'3. Revenue Model'!$B:$B,0),MATCH(G$3,'3. Revenue Model'!$D$2:$AA$2,0)) -> 0 | H14: =INDEX('3. Revenue Model'!$D:$AA,MATCH($B14,'3. Revenue Model'!$B:$B,0),MATCH(H$3,'3. Revenue Model'!$D$2:$AA$2,0)) -> 0 | I14: =INDEX('3. Revenue Model'!$D:$AA,MATCH($B14,'3. Revenue Model'!$B:$B,0),MATCH(I$3,'3. Revenue Model'!$D$2:$AA$2,0)) -> 1 | J14: =INDEX('3. Revenue Model'!$D:$AA,MATCH($B14,'3. Revenue Model'!$B:$B,0),MATCH(J$3,'3. Revenue Model'!$D$2:$AA$2,0)) -> 1.07 | K14: =INDEX('3. Revenue Model'!$D:$AA,MATCH($B14,'3. Revenue Model'!$B:$B,0),MATCH(K$3,'3. Revenue Model'!$D$2:$AA$2,0)) -> 1.1449 | ... AA14: =INDEX('3. Revenue Model'!$D:$AA,MATCH($B14,'3. Revenue Model'!$B:$B,0),MATCH(AA$3,'3. Revenue Model'!$D$2:$AA$2,0)) -> 3.3799323
A15: Operating Drivers | B15: Ending Subscription MRR | C15: $ | D15: =INDEX('3. Revenue Model'!$D:$AA,MATCH($B15,'3. Revenue Model'!$B:$B,0),MATCH(D$3,'3. Revenue Model'!$D$2:$AA$2,0)) -> 44463.3 | E15: =INDEX('3. Revenue Model'!$D:$AA,MATCH($B15,'3. Revenue Model'!$B:$B,0),MATCH(E$3,'3. Revenue Model'!$D$2:$AA$2,0)) -> 46129.371 | F15: =INDEX('3. Revenue Model'!$D:$AA,MATCH($B15,'3. Revenue Model'!$B:$B,0),MATCH(F$3,'3. Revenue Model'!$D$2:$AA$2,0)) -> 47841.764 | G15: =INDEX('3. Revenue Model'!$D:$AA,MATCH($B15,'3. Revenue Model'!$B:$B,0),MATCH(G$3,'3. Revenue Model'!$D$2:$AA$2,0)) -> 49636.69 | H15: =INDEX('3. Revenue Model'!$D:$AA,MATCH($B15,'3. Revenue Model'!$B:$B,0),MATCH(H$3,'3. Revenue Model'!$D$2:$AA$2,0)) -> 51546.579 | I15: =INDEX('3. Revenue Model'!$D:$AA,MATCH($B15,'3. Revenue Model'!$B:$B,0),MATCH(I$3,'3. Revenue Model'!$D$2:$AA$2,0)) -> 54200.286 | J15: =INDEX('3. Revenue Model'!$D:$AA,MATCH($B15,'3. Revenue Model'!$B:$B,0),MATCH(J$3,'3. Revenue Model'!$D$2:$AA$2,0)) -> 57054.936 | K15: =INDEX('3. Revenue Model'!$D:$AA,MATCH($B15,'3. Revenue Model'!$B:$B,0),MATCH(K$3,'3. Revenue Model'!$D$2:$AA$2,0)) -> 60140.159 | ... AA15: =INDEX('3. Revenue Model'!$D:$AA,MATCH($B15,'3. Revenue Model'!$B:$B,0),MATCH(AA$3,'3. Revenue Model'!$D$2:$AA$2,0)) -> 170586.03
A16: Operating Drivers | B16: Total Recurring MRR | C16: $ | D16: =INDEX('3. Revenue Model'!$D:$AA,MATCH($B16,'3. Revenue Model'!$B:$B,0),MATCH(D$3,'3. Revenue Model'!$D$2:$AA$2,0)) -> 44463.3 | E16: =INDEX('3. Revenue Model'!$D:$AA,MATCH($B16,'3. Revenue Model'!$B:$B,0),MATCH(E$3,'3. Revenue Model'!$D$2:$AA$2,0)) -> 46129.371 | F16: =INDEX('3. Revenue Model'!$D:$AA,MATCH($B16,'3. Revenue Model'!$B:$B,0),MATCH(F$3,'3. Revenue Model'!$D$2:$AA$2,0)) -> 47841.764 | G16: =INDEX('3. Revenue Model'!$D:$AA,MATCH($B16,'3. Revenue Model'!$B:$B,0),MATCH(G$3,'3. Revenue Model'!$D$2:$AA$2,0)) -> 49636.69 | H16: =INDEX('3. Revenue Model'!$D:$AA,MATCH($B16,'3. Revenue Model'!$B:$B,0),MATCH(H$3,'3. Revenue Model'!$D$2:$AA$2,0)) -> 51546.579 | I16: =INDEX('3. Revenue Model'!$D:$AA,MATCH($B16,'3. Revenue Model'!$B:$B,0),MATCH(I$3,'3. Revenue Model'!$D$2:$AA$2,0)) -> 54200.286 | J16: =INDEX('3. Revenue Model'!$D:$AA,MATCH($B16,'3. Revenue Model'!$B:$B,0),MATCH(J$3,'3. Revenue Model'!$D$2:$AA$2,0)) -> 57054.936 | K16: =INDEX('3. Revenue Model'!$D:$AA,MATCH($B16,'3. Revenue Model'!$B:$B,0),MATCH(K$3,'3. Revenue Model'!$D$2:$AA$2,0)) -> 60140.159 | ... AA16: =INDEX('3. Revenue Model'!$D:$AA,MATCH($B16,'3. Revenue Model'!$B:$B,0),MATCH(AA$3,'3. Revenue Model'!$D$2:$AA$2,0)) -> 181548.9
A17: Operating Drivers | B17: ARR (Recurring Only) | C17: $ | D17: =INDEX('3. Revenue Model'!$D:$AA,MATCH($B17,'3. Revenue Model'!$B:$B,0),MATCH(D$3,'3. Revenue Model'!$D$2:$AA$2,0)) -> 533559.6 | E17: =INDEX('3. Revenue Model'!$D:$AA,MATCH($B17,'3. Revenue Model'!$B:$B,0),MATCH(E$3,'3. Revenue Model'!$D$2:$AA$2,0)) -> 553552.45 | F17: =INDEX('3. Revenue Model'!$D:$AA,MATCH($B17,'3. Revenue Model'!$B:$B,0),MATCH(F$3,'3. Revenue Model'!$D$2:$AA$2,0)) -> 574101.17 | G17: =INDEX('3. Revenue Model'!$D:$AA,MATCH($B17,'3. Revenue Model'!$B:$B,0),MATCH(G$3,'3. Revenue Model'!$D$2:$AA$2,0)) -> 595640.27 | H17: =INDEX('3. Revenue Model'!$D:$AA,MATCH($B17,'3. Revenue Model'!$B:$B,0),MATCH(H$3,'3. Revenue Model'!$D$2:$AA$2,0)) -> 618558.95 | I17: =INDEX('3. Revenue Model'!$D:$AA,MATCH($B17,'3. Revenue Model'!$B:$B,0),MATCH(I$3,'3. Revenue Model'!$D$2:$AA$2,0)) -> 650403.44 | J17: =INDEX('3. Revenue Model'!$D:$AA,MATCH($B17,'3. Revenue Model'!$B:$B,0),MATCH(J$3,'3. Revenue Model'!$D$2:$AA$2,0)) -> 684659.23 | K17: =INDEX('3. Revenue Model'!$D:$AA,MATCH($B17,'3. Revenue Model'!$B:$B,0),MATCH(K$3,'3. Revenue Model'!$D$2:$AA$2,0)) -> 721681.91 | ... AA17: =INDEX('3. Revenue Model'!$D:$AA,MATCH($B17,'3. Revenue Model'!$B:$B,0),MATCH(AA$3,'3. Revenue Model'!$D$2:$AA$2,0)) -> 2178586.8
A18: Operating Drivers | B18: Net New MRR | C18: $ | D18: =INDEX('3. Revenue Model'!$D:$AA,MATCH($B18,'3. Revenue Model'!$B:$B,0),MATCH(D$3,'3. Revenue Model'!$D$2:$AA$2,0)) -> 44463.3 | E18: =INDEX('3. Revenue Model'!$D:$AA,MATCH($B18,'3. Revenue Model'!$B:$B,0),MATCH(E$3,'3. Revenue Model'!$D$2:$AA$2,0)) -> 1666.071 | F18: =INDEX('3. Revenue Model'!$D:$AA,MATCH($B18,'3. Revenue Model'!$B:$B,0),MATCH(F$3,'3. Revenue Model'!$D$2:$AA$2,0)) -> 1712.3932 | G18: =INDEX('3. Revenue Model'!$D:$AA,MATCH($B18,'3. Revenue Model'!$B:$B,0),MATCH(G$3,'3. Revenue Model'!$D$2:$AA$2,0)) -> 1794.9254 | H18: =INDEX('3. Revenue Model'!$D:$AA,MATCH($B18,'3. Revenue Model'!$B:$B,0),MATCH(H$3,'3. Revenue Model'!$D$2:$AA$2,0)) -> 1909.8898 | I18: =INDEX('3. Revenue Model'!$D:$AA,MATCH($B18,'3. Revenue Model'!$B:$B,0),MATCH(I$3,'3. Revenue Model'!$D$2:$AA$2,0)) -> 2653.7069 | J18: =INDEX('3. Revenue Model'!$D:$AA,MATCH($B18,'3. Revenue Model'!$B:$B,0),MATCH(J$3,'3. Revenue Model'!$D$2:$AA$2,0)) -> 2854.6495 | K18: =INDEX('3. Revenue Model'!$D:$AA,MATCH($B18,'3. Revenue Model'!$B:$B,0),MATCH(K$3,'3. Revenue Model'!$D$2:$AA$2,0)) -> 3085.2229 | ... AA18: =INDEX('3. Revenue Model'!$D:$AA,MATCH($B18,'3. Revenue Model'!$B:$B,0),MATCH(AA$3,'3. Revenue Model'!$D$2:$AA$2,0)) -> 13748.741
A20: § 3 HIRING GATE INPUTS
A21: Hiring Gate | B21: CAC Payback Months (link from Unit Economics when ready) | C21: Months | D21: {=INDEX('6. Unit Economics'!$B$47:$Y$64,MATCH("Blended CAC Payback",'6. Unit Economics'!$A$47:$A$64,0),0)} -> 8.624653 | E21: 8.8190809 | F21: 8.975294 | G21: 9.1004172 | H21: 9.2013773 | I21: 10.30437 | J21: 10.315445 | K21: 12.392083 | L21: 12.200437 | M21: 11.968758 | N21: 11.749603 | O21: 11.543814 | P21: 11.351538 | Q21: 11.172458 | R21: 11.005965 | S21: 12.206202 | T21: 11.93168 | U21: 11.680603 | V21: 11.450576 | W21: 11.23943 | X21: 11.045204 | Y21: 10.866137 | Z21: 10.70065 | AA21: 10.547331
A23: § 4 ROLE-LEVEL Start Months
A24: Role Level | B24: Founder / CEO ; Start Month | C24: Month | D24: =INDEX('1. Assumptions'!$G:$G,MATCH($B24,'1. Assumptions'!$B:$B,0)) -> 1 | E24: =INDEX('1. Assumptions'!$G:$G,MATCH($B24,'1. Assumptions'!$B:$B,0)) -> 1 | F24: =INDEX('1. Assumptions'!$G:$G,MATCH($B24,'1. Assumptions'!$B:$B,0)) -> 1 | G24: =INDEX('1. Assumptions'!$G:$G,MATCH($B24,'1. Assumptions'!$B:$B,0)) -> 1 | H24: =INDEX('1. Assumptions'!$G:$G,MATCH($B24,'1. Assumptions'!$B:$B,0)) -> 1 | I24: =INDEX('1. Assumptions'!$G:$G,MATCH($B24,'1. Assumptions'!$B:$B,0)) -> 1 | J24: =INDEX('1. Assumptions'!$G:$G,MATCH($B24,'1. Assumptions'!$B:$B,0)) -> 1 | K24: =INDEX('1. Assumptions'!$G:$G,MATCH($B24,'1. Assumptions'!$B:$B,0)) -> 1 | ... AA24: =INDEX('1. Assumptions'!$G:$G,MATCH($B24,'1. Assumptions'!$B:$B,0)) -> 1
A25: Role Level | B25: Founder / CTO ; Start Month | C25: Month | D25: =INDEX('1. Assumptions'!$G:$G,MATCH($B25,'1. Assumptions'!$B:$B,0)) -> 1 | E25: =INDEX('1. Assumptions'!$G:$G,MATCH($B25,'1. Assumptions'!$B:$B,0)) -> 1 | F25: =INDEX('1. Assumptions'!$G:$G,MATCH($B25,'1. Assumptions'!$B:$B,0)) -> 1 | G25: =INDEX('1. Assumptions'!$G:$G,MATCH($B25,'1. Assumptions'!$B:$B,0)) -> 1 | H25: =INDEX('1. Assumptions'!$G:$G,MATCH($B25,'1. Assumptions'!$B:$B,0)) -> 1 | I25: =INDEX('1. Assumptions'!$G:$G,MATCH($B25,'1. Assumptions'!$B:$B,0)) -> 1 | J25: =INDEX('1. Assumptions'!$G:$G,MATCH($B25,'1. Assumptions'!$B:$B,0)) -> 1 | K25: =INDEX('1. Assumptions'!$G:$G,MATCH($B25,'1. Assumptions'!$B:$B,0)) -> 1 | ... AA25: =INDEX('1. Assumptions'!$G:$G,MATCH($B25,'1. Assumptions'!$B:$B,0)) -> 1
A26: Role Level | B26: Full-Stack Engineer #1 ; Start Month | C26: Month | D26: =INDEX('1. Assumptions'!$G:$G,MATCH($B26,'1. Assumptions'!$B:$B,0)) -> 3 | E26: =INDEX('1. Assumptions'!$G:$G,MATCH($B26,'1. Assumptions'!$B:$B,0)) -> 3 | F26: =INDEX('1. Assumptions'!$G:$G,MATCH($B26,'1. Assumptions'!$B:$B,0)) -> 3 | G26: =INDEX('1. Assumptions'!$G:$G,MATCH($B26,'1. Assumptions'!$B:$B,0)) -> 3 | H26: =INDEX('1. Assumptions'!$G:$G,MATCH($B26,'1. Assumptions'!$B:$B,0)) -> 3 | I26: =INDEX('1. Assumptions'!$G:$G,MATCH($B26,'1. Assumptions'!$B:$B,0)) -> 3 | J26: =INDEX('1. Assumptions'!$G:$G,MATCH($B26,'1. Assumptions'!$B:$B,0)) -> 3 | K26: =INDEX('1. Assumptions'!$G:$G,MATCH($B26,'1. Assumptions'!$B:$B,0)) -> 3 | ... AA26: =INDEX('1. Assumptions'!$G:$G,MATCH($B26,'1. Assumptions'!$B:$B,0)) -> 3
A27: Role Level | B27: Head of Growth / AE #1 ; Start Month | C27: Month | D27: =INDEX('1. Assumptions'!$G:$G,MATCH($B27,'1. Assumptions'!$B:$B,0)) -> 4 | E27: =INDEX('1. Assumptions'!$G:$G,MATCH($B27,'1. Assumptions'!$B:$B,0)) -> 4 | F27: =INDEX('1. Assumptions'!$G:$G,MATCH($B27,'1. Assumptions'!$B:$B,0)) -> 4 | G27: =INDEX('1. Assumptions'!$G:$G,MATCH($B27,'1. Assumptions'!$B:$B,0)) -> 4 | H27: =INDEX('1. Assumptions'!$G:$G,MATCH($B27,'1. Assumptions'!$B:$B,0)) -> 4 | I27: =INDEX('1. Assumptions'!$G:$G,MATCH($B27,'1. Assumptions'!$B:$B,0)) -> 4 | J27: =INDEX('1. Assumptions'!$G:$G,MATCH($B27,'1. Assumptions'!$B:$B,0)) -> 4 | K27: =INDEX('1. Assumptions'!$G:$G,MATCH($B27,'1. Assumptions'!$B:$B,0)) -> 4 | ... AA27: =INDEX('1. Assumptions'!$G:$G,MATCH($B27,'1. Assumptions'!$B:$B,0)) -> 4
A28: Role Level | B28: Marketing Manager ; Start Month | C28: Month | D28: =INDEX('1. Assumptions'!$G:$G,MATCH($B28,'1. Assumptions'!$B:$B,0)) -> 5 | E28: =INDEX('1. Assumptions'!$G:$G,MATCH($B28,'1. Assumptions'!$B:$B,0)) -> 5 | F28: =INDEX('1. Assumptions'!$G:$G,MATCH($B28,'1. Assumptions'!$B:$B,0)) -> 5 | G28: =INDEX('1. Assumptions'!$G:$G,MATCH($B28,'1. Assumptions'!$B:$B,0)) -> 5 | H28: =INDEX('1. Assumptions'!$G:$G,MATCH($B28,'1. Assumptions'!$B:$B,0)) -> 5 | I28: =INDEX('1. Assumptions'!$G:$G,MATCH($B28,'1. Assumptions'!$B:$B,0)) -> 5 | J28: =INDEX('1. Assumptions'!$G:$G,MATCH($B28,'1. Assumptions'!$B:$B,0)) -> 5 | K28: =INDEX('1. Assumptions'!$G:$G,MATCH($B28,'1. Assumptions'!$B:$B,0)) -> 5 | ... AA28: =INDEX('1. Assumptions'!$G:$G,MATCH($B28,'1. Assumptions'!$B:$B,0)) -> 5
A29: Role Level | B29: Full-Stack Engineer #2 ; Start Month | C29: Month | D29: =INDEX('1. Assumptions'!$G:$G,MATCH($B29,'1. Assumptions'!$B:$B,0)) -> 6 | E29: =INDEX('1. Assumptions'!$G:$G,MATCH($B29,'1. Assumptions'!$B:$B,0)) -> 6 | F29: =INDEX('1. Assumptions'!$G:$G,MATCH($B29,'1. Assumptions'!$B:$B,0)) -> 6 | G29: =INDEX('1. Assumptions'!$G:$G,MATCH($B29,'1. Assumptions'!$B:$B,0)) -> 6 | H29: =INDEX('1. Assumptions'!$G:$G,MATCH($B29,'1. Assumptions'!$B:$B,0)) -> 6 | I29: =INDEX('1. Assumptions'!$G:$G,MATCH($B29,'1. Assumptions'!$B:$B,0)) -> 6 | J29: =INDEX('1. Assumptions'!$G:$G,MATCH($B29,'1. Assumptions'!$B:$B,0)) -> 6 | K29: =INDEX('1. Assumptions'!$G:$G,MATCH($B29,'1. Assumptions'!$B:$B,0)) -> 6 | ... AA29: =INDEX('1. Assumptions'!$G:$G,MATCH($B29,'1. Assumptions'!$B:$B,0)) -> 6
A30: Role Level | B30: Customer Success #1 ; Planned Start Month | C30: Month | D30: =IFERROR(INDEX('1. Assumptions'!$G:$G,MATCH($B30,'1. Assumptions'!$B:$B,0)),"CHECK") -> 8 | E30: =IFERROR(INDEX('1. Assumptions'!$G:$G,MATCH($B30,'1. Assumptions'!$B:$B,0)),"CHECK") -> 8 | F30: =IFERROR(INDEX('1. Assumptions'!$G:$G,MATCH($B30,'1. Assumptions'!$B:$B,0)),"CHECK") -> 8 | G30: =IFERROR(INDEX('1. Assumptions'!$G:$G,MATCH($B30,'1. Assumptions'!$B:$B,0)),"CHECK") -> 8 | H30: =IFERROR(INDEX('1. Assumptions'!$G:$G,MATCH($B30,'1. Assumptions'!$B:$B,0)),"CHECK") -> 8 | I30: =IFERROR(INDEX('1. Assumptions'!$G:$G,MATCH($B30,'1. Assumptions'!$B:$B,0)),"CHECK") -> 8 | J30: =IFERROR(INDEX('1. Assumptions'!$G:$G,MATCH($B30,'1. Assumptions'!$B:$B,0)),"CHECK") -> 8 | K30: =IFERROR(INDEX('1. Assumptions'!$G:$G,MATCH($B30,'1. Assumptions'!$B:$B,0)),"CHECK") -> 8 | ... AA30: =IFERROR(INDEX('1. Assumptions'!$G:$G,MATCH($B30,'1. Assumptions'!$B:$B,0)),"CHECK") -> 8
A31: Role Level | B31: Customer Success #1 ; Trigger Month | C31: Month | D31: {=IFERROR(INDEX($D$6:$AA$6,1,MATCH(TRUE,($D$10:$AA$10-$D$10)>=INDEX('1. Assumptions'!$G:$G,MATCH("*CS Hire Trigger*",'1. Assumptions'!$B:$B,0)),0)),"Not Triggered")} -> 5 | E31: {=IFERROR(INDEX($D$6:$AA$6,1,MATCH(TRUE,($D$10:$AA$10-$D$10)>=INDEX('1. Assumptions'!$G:$G,MATCH("*CS Hire Trigger*",'1. Assumptions'!$B:$B,0)),0)),"Not Triggered")} -> 5 | F31: {=IFERROR(INDEX($D$6:$AA$6,1,MATCH(TRUE,($D$10:$AA$10-$D$10)>=INDEX('1. Assumptions'!$G:$G,MATCH("*CS Hire Trigger*",'1. Assumptions'!$B:$B,0)),0)),"Not Triggered")} -> 5 | G31: {=IFERROR(INDEX($D$6:$AA$6,1,MATCH(TRUE,($D$10:$AA$10-$D$10)>=INDEX('1. Assumptions'!$G:$G,MATCH("*CS Hire Trigger*",'1. Assumptions'!$B:$B,0)),0)),"Not Triggered")} -> 5 | H31: {=IFERROR(INDEX($D$6:$AA$6,1,MATCH(TRUE,($D$10:$AA$10-$D$10)>=INDEX('1. Assumptions'!$G:$G,MATCH("*CS Hire Trigger*",'1. Assumptions'!$B:$B,0)),0)),"Not Triggered")} -> 5 | I31: {=IFERROR(INDEX($D$6:$AA$6,1,MATCH(TRUE,($D$10:$AA$10-$D$10)>=INDEX('1. Assumptions'!$G:$G,MATCH("*CS Hire Trigger*",'1. Assumptions'!$B:$B,0)),0)),"Not Triggered")} -> 5 | J31: {=IFERROR(INDEX($D$6:$AA$6,1,MATCH(TRUE,($D$10:$AA$10-$D$10)>=INDEX('1. Assumptions'!$G:$G,MATCH("*CS Hire Trigger*",'1. Assumptions'!$B:$B,0)),0)),"Not Triggered")} -> 5 | K31: {=IFERROR(INDEX($D$6:$AA$6,1,MATCH(TRUE,($D$10:$AA$10-$D$10)>=INDEX('1. Assumptions'!$G:$G,MATCH("*CS Hire Trigger*",'1. Assumptions'!$B:$B,0)),0)),"Not Triggered")} -> 5 | ... AA31: {=IFERROR(INDEX($D$6:$AA$6,1,MATCH(TRUE,($D$10:$AA$10-$D$10)>=INDEX('1. Assumptions'!$G:$G,MATCH("*CS Hire Trigger*",'1. Assumptions'!$B:$B,0)),0)),"Not Triggered")} -> 5
A32: Role Level | B32: Customer Success #1 ; Actual Start Month | C32: Month | D32: =IF(D31="Not Triggered","Deferred",MAX(D30,D31)) -> 8 | E32: =IF(E31="Not Triggered","Deferred",MAX(E30,E31)) -> 8 | F32: =IF(F31="Not Triggered","Deferred",MAX(F30,F31)) -> 8 | G32: =IF(G31="Not Triggered","Deferred",MAX(G30,G31)) -> 8 | H32: =IF(H31="Not Triggered","Deferred",MAX(H30,H31)) -> 8 | I32: =IF(I31="Not Triggered","Deferred",MAX(I30,I31)) -> 8 | J32: =IF(J31="Not Triggered","Deferred",MAX(J30,J31)) -> 8 | K32: =IF(K31="Not Triggered","Deferred",MAX(K30,K31)) -> 8 | ... AA32: =IF(AA31="Not Triggered","Deferred",MAX(AA30,AA31)) -> 8
A33: Role Level | B33: Product Manager ; Start Month | C33: Month | D33: =INDEX('1. Assumptions'!$G:$G,MATCH($B33,'1. Assumptions'!$B:$B,0)) -> 10 | E33: =INDEX('1. Assumptions'!$G:$G,MATCH($B33,'1. Assumptions'!$B:$B,0)) -> 10 | F33: =INDEX('1. Assumptions'!$G:$G,MATCH($B33,'1. Assumptions'!$B:$B,0)) -> 10 | G33: =INDEX('1. Assumptions'!$G:$G,MATCH($B33,'1. Assumptions'!$B:$B,0)) -> 10 | H33: =INDEX('1. Assumptions'!$G:$G,MATCH($B33,'1. Assumptions'!$B:$B,0)) -> 10 | I33: =INDEX('1. Assumptions'!$G:$G,MATCH($B33,'1. Assumptions'!$B:$B,0)) -> 10 | J33: =INDEX('1. Assumptions'!$G:$G,MATCH($B33,'1. Assumptions'!$B:$B,0)) -> 10 | K33: =INDEX('1. Assumptions'!$G:$G,MATCH($B33,'1. Assumptions'!$B:$B,0)) -> 10 | ... AA33: =INDEX('1. Assumptions'!$G:$G,MATCH($B33,'1. Assumptions'!$B:$B,0)) -> 10
A34: Role Level | B34: Data Engineer ; Start Month | C34: Month | D34: =INDEX('1. Assumptions'!$G:$G,MATCH($B34,'1. Assumptions'!$B:$B,0)) -> 12 | E34: =INDEX('1. Assumptions'!$G:$G,MATCH($B34,'1. Assumptions'!$B:$B,0)) -> 12 | F34: =INDEX('1. Assumptions'!$G:$G,MATCH($B34,'1. Assumptions'!$B:$B,0)) -> 12 | G34: =INDEX('1. Assumptions'!$G:$G,MATCH($B34,'1. Assumptions'!$B:$B,0)) -> 12 | H34: =INDEX('1. Assumptions'!$G:$G,MATCH($B34,'1. Assumptions'!$B:$B,0)) -> 12 | I34: =INDEX('1. Assumptions'!$G:$G,MATCH($B34,'1. Assumptions'!$B:$B,0)) -> 12 | J34: =INDEX('1. Assumptions'!$G:$G,MATCH($B34,'1. Assumptions'!$B:$B,0)) -> 12 | K34: =INDEX('1. Assumptions'!$G:$G,MATCH($B34,'1. Assumptions'!$B:$B,0)) -> 12 | ... AA34: =INDEX('1. Assumptions'!$G:$G,MATCH($B34,'1. Assumptions'!$B:$B,0)) -> 12
A35: Role Level | B35: AE #2 ; Start Month | C35: Month | D35: =INDEX('1. Assumptions'!$G:$G,MATCH($B35,'1. Assumptions'!$B:$B,0)) -> 9 | E35: =INDEX('1. Assumptions'!$G:$G,MATCH($B35,'1. Assumptions'!$B:$B,0)) -> 9 | F35: =INDEX('1. Assumptions'!$G:$G,MATCH($B35,'1. Assumptions'!$B:$B,0)) -> 9 | G35: =INDEX('1. Assumptions'!$G:$G,MATCH($B35,'1. Assumptions'!$B:$B,0)) -> 9 | H35: =INDEX('1. Assumptions'!$G:$G,MATCH($B35,'1. Assumptions'!$B:$B,0)) -> 9 | I35: =INDEX('1. Assumptions'!$G:$G,MATCH($B35,'1. Assumptions'!$B:$B,0)) -> 9 | J35: =INDEX('1. Assumptions'!$G:$G,MATCH($B35,'1. Assumptions'!$B:$B,0)) -> 9 | K35: =INDEX('1. Assumptions'!$G:$G,MATCH($B35,'1. Assumptions'!$B:$B,0)) -> 9 | ... AA35: =INDEX('1. Assumptions'!$G:$G,MATCH($B35,'1. Assumptions'!$B:$B,0)) -> 9
A36: Role Level | B36: Customer Success #2 ; Planned Start Month | C36: Month | D36: =IFERROR(INDEX('1. Assumptions'!$G:$G,MATCH($B36,'1. Assumptions'!$B:$B,0)),"CHECK") -> 16 | E36: =IFERROR(INDEX('1. Assumptions'!$G:$G,MATCH($B36,'1. Assumptions'!$B:$B,0)),"CHECK") -> 16 | F36: =IFERROR(INDEX('1. Assumptions'!$G:$G,MATCH($B36,'1. Assumptions'!$B:$B,0)),"CHECK") -> 16 | G36: =IFERROR(INDEX('1. Assumptions'!$G:$G,MATCH($B36,'1. Assumptions'!$B:$B,0)),"CHECK") -> 16 | H36: =IFERROR(INDEX('1. Assumptions'!$G:$G,MATCH($B36,'1. Assumptions'!$B:$B,0)),"CHECK") -> 16 | I36: =IFERROR(INDEX('1. Assumptions'!$G:$G,MATCH($B36,'1. Assumptions'!$B:$B,0)),"CHECK") -> 16 | J36: =IFERROR(INDEX('1. Assumptions'!$G:$G,MATCH($B36,'1. Assumptions'!$B:$B,0)),"CHECK") -> 16 | K36: =IFERROR(INDEX('1. Assumptions'!$G:$G,MATCH($B36,'1. Assumptions'!$B:$B,0)),"CHECK") -> 16 | ... AA36: =IFERROR(INDEX('1. Assumptions'!$G:$G,MATCH($B36,'1. Assumptions'!$B:$B,0)),"CHECK") -> 16
A37: Role Level | B37: Customer Success #2 ; Trigger Start Month | C37: Month | D37: {=IFERROR(INDEX($D$6:$AA$6,1,MATCH(1,--(($D$10:$AA$10-$D$10)>=2*INDEX('1. Assumptions'!$G:$G,MATCH("*CS Hire Trigger*",'1. Assumptions'!$B:$B,0))),0)),"Not Triggered")} -> 7 | E37: {=IFERROR(INDEX($D$6:$AA$6,1,MATCH(1,--(($D$10:$AA$10-$D$10)>=2*INDEX('1. Assumptions'!$G:$G,MATCH("*CS Hire Trigger*",'1. Assumptions'!$B:$B,0))),0)),"Not Triggered")} -> 7 | F37: {=IFERROR(INDEX($D$6:$AA$6,1,MATCH(1,--(($D$10:$AA$10-$D$10)>=2*INDEX('1. Assumptions'!$G:$G,MATCH("*CS Hire Trigger*",'1. Assumptions'!$B:$B,0))),0)),"Not Triggered")} -> 7 | G37: {=IFERROR(INDEX($D$6:$AA$6,1,MATCH(1,--(($D$10:$AA$10-$D$10)>=2*INDEX('1. Assumptions'!$G:$G,MATCH("*CS Hire Trigger*",'1. Assumptions'!$B:$B,0))),0)),"Not Triggered")} -> 7 | H37: {=IFERROR(INDEX($D$6:$AA$6,1,MATCH(1,--(($D$10:$AA$10-$D$10)>=2*INDEX('1. Assumptions'!$G:$G,MATCH("*CS Hire Trigger*",'1. Assumptions'!$B:$B,0))),0)),"Not Triggered")} -> 7 | I37: {=IFERROR(INDEX($D$6:$AA$6,1,MATCH(1,--(($D$10:$AA$10-$D$10)>=2*INDEX('1. Assumptions'!$G:$G,MATCH("*CS Hire Trigger*",'1. Assumptions'!$B:$B,0))),0)),"Not Triggered")} -> 7 | J37: {=IFERROR(INDEX($D$6:$AA$6,1,MATCH(1,--(($D$10:$AA$10-$D$10)>=2*INDEX('1. Assumptions'!$G:$G,MATCH("*CS Hire Trigger*",'1. Assumptions'!$B:$B,0))),0)),"Not Triggered")} -> 7 | K37: {=IFERROR(INDEX($D$6:$AA$6,1,MATCH(1,--(($D$10:$AA$10-$D$10)>=2*INDEX('1. Assumptions'!$G:$G,MATCH("*CS Hire Trigger*",'1. Assumptions'!$B:$B,0))),0)),"Not Triggered")} -> 7 | ... AA37: {=IFERROR(INDEX($D$6:$AA$6,1,MATCH(1,--(($D$10:$AA$10-$D$10)>=2*INDEX('1. Assumptions'!$G:$G,MATCH("*CS Hire Trigger*",'1. Assumptions'!$B:$B,0))),0)),"Not Triggered")} -> 7
A38: Role Level | B38: Customer Success #2 ; Actual Start Month | C38: Month | D38: =IF(D37="Not Triggered","Deferred",MAX(D36,D37)) -> 16 | E38: =IF(E37="Not Triggered","Deferred",MAX(E36,E37)) -> 16 | F38: =IF(F37="Not Triggered","Deferred",MAX(F36,F37)) -> 16 | G38: =IF(G37="Not Triggered","Deferred",MAX(G36,G37)) -> 16 | H38: =IF(H37="Not Triggered","Deferred",MAX(H36,H37)) -> 16 | I38: =IF(I37="Not Triggered","Deferred",MAX(I36,I37)) -> 16 | J38: =IF(J37="Not Triggered","Deferred",MAX(J36,J37)) -> 16 | K38: =IF(K37="Not Triggered","Deferred",MAX(K36,K37)) -> 16 | ... AA38: =IF(AA37="Not Triggered","Deferred",MAX(AA36,AA37)) -> 16
A39: Role Level | B39: AE #3 ; Earliest Possible Start Month | C39: Month | D39: =INDEX('1. Assumptions'!$G:$G,MATCH($B39,'1. Assumptions'!$B:$B,0)) -> 14 | E39: =INDEX('1. Assumptions'!$G:$G,MATCH($B39,'1. Assumptions'!$B:$B,0)) -> 14 | F39: =INDEX('1. Assumptions'!$G:$G,MATCH($B39,'1. Assumptions'!$B:$B,0)) -> 14 | G39: =INDEX('1. Assumptions'!$G:$G,MATCH($B39,'1. Assumptions'!$B:$B,0)) -> 14 | H39: =INDEX('1. Assumptions'!$G:$G,MATCH($B39,'1. Assumptions'!$B:$B,0)) -> 14 | I39: =INDEX('1. Assumptions'!$G:$G,MATCH($B39,'1. Assumptions'!$B:$B,0)) -> 14 | J39: =INDEX('1. Assumptions'!$G:$G,MATCH($B39,'1. Assumptions'!$B:$B,0)) -> 14 | K39: =INDEX('1. Assumptions'!$G:$G,MATCH($B39,'1. Assumptions'!$B:$B,0)) -> 14 | ... AA39: =INDEX('1. Assumptions'!$G:$G,MATCH($B39,'1. Assumptions'!$B:$B,0)) -> 14
A40: Role Level | B40: AE #3 ; Latest Delay Month (runway protection) | C40: Month | D40: =INDEX('1. Assumptions'!$G:$G,MATCH($B40,'1. Assumptions'!$B:$B,0)) -> 18 | E40: =INDEX('1. Assumptions'!$G:$G,MATCH($B40,'1. Assumptions'!$B:$B,0)) -> 18 | F40: =INDEX('1. Assumptions'!$G:$G,MATCH($B40,'1. Assumptions'!$B:$B,0)) -> 18 | G40: =INDEX('1. Assumptions'!$G:$G,MATCH($B40,'1. Assumptions'!$B:$B,0)) -> 18 | H40: =INDEX('1. Assumptions'!$G:$G,MATCH($B40,'1. Assumptions'!$B:$B,0)) -> 18 | I40: =INDEX('1. Assumptions'!$G:$G,MATCH($B40,'1. Assumptions'!$B:$B,0)) -> 18 | J40: =INDEX('1. Assumptions'!$G:$G,MATCH($B40,'1. Assumptions'!$B:$B,0)) -> 18 | K40: =INDEX('1. Assumptions'!$G:$G,MATCH($B40,'1. Assumptions'!$B:$B,0)) -> 18 | ... AA40: =INDEX('1. Assumptions'!$G:$G,MATCH($B40,'1. Assumptions'!$B:$B,0)) -> 18
A41: Role Level | B41: CFO / Finance Hire ; Start Month | C41: Month | D41: =INDEX('1. Assumptions'!$G:$G,MATCH($B41,'1. Assumptions'!$B:$B,0)) -> 20 | E41: =INDEX('1. Assumptions'!$G:$G,MATCH($B41,'1. Assumptions'!$B:$B,0)) -> 20 | F41: =INDEX('1. Assumptions'!$G:$G,MATCH($B41,'1. Assumptions'!$B:$B,0)) -> 20 | G41: =INDEX('1. Assumptions'!$G:$G,MATCH($B41,'1. Assumptions'!$B:$B,0)) -> 20 | H41: =INDEX('1. Assumptions'!$G:$G,MATCH($B41,'1. Assumptions'!$B:$B,0)) -> 20 | I41: =INDEX('1. Assumptions'!$G:$G,MATCH($B41,'1. Assumptions'!$B:$B,0)) -> 20 | J41: =INDEX('1. Assumptions'!$G:$G,MATCH($B41,'1. Assumptions'!$B:$B,0)) -> 20 | K41: =INDEX('1. Assumptions'!$G:$G,MATCH($B41,'1. Assumptions'!$B:$B,0)) -> 20 | ... AA41: =INDEX('1. Assumptions'!$G:$G,MATCH($B41,'1. Assumptions'!$B:$B,0)) -> 20
A43: § 4 ROLE-LEVEL FTE
A44: Role FTE | B44: Founder / CEO FTE | C44: FTE | D44: =IF(D$6>=$D$24,1,0) -> 1 | E44: =IF(E$6>=$D$24,1,0) -> 1 | F44: =IF(F$6>=$D$24,1,0) -> 1 | G44: =IF(G$6>=$D$24,1,0) -> 1 | H44: =IF(H$6>=$D$24,1,0) -> 1 | I44: =IF(I$6>=$D$24,1,0) -> 1 | J44: =IF(J$6>=$D$24,1,0) -> 1 | K44: =IF(K$6>=$D$24,1,0) -> 1 | ... AA44: =IF(AA$6>=$D$24,1,0) -> 1
A45: Role FTE | B45: Founder / CTO FTE | C45: FTE | D45: =IF(D$6>=$D$25,1,0) -> 1 | E45: =IF(E$6>=$D$25,1,0) -> 1 | F45: =IF(F$6>=$D$25,1,0) -> 1 | G45: =IF(G$6>=$D$25,1,0) -> 1 | H45: =IF(H$6>=$D$25,1,0) -> 1 | I45: =IF(I$6>=$D$25,1,0) -> 1 | J45: =IF(J$6>=$D$25,1,0) -> 1 | K45: =IF(K$6>=$D$25,1,0) -> 1 | ... AA45: =IF(AA$6>=$D$25,1,0) -> 1
A46: Role FTE | B46: Full-Stack Engineer #1 FTE | C46: FTE | D46: =IF(D$6>=$D$26,1,0) -> 0 | E46: =IF(E$6>=$D$26,1,0) -> 0 | F46: =IF(F$6>=$D$26,1,0) -> 1 | G46: =IF(G$6>=$D$26,1,0) -> 1 | H46: =IF(H$6>=$D$26,1,0) -> 1 | I46: =IF(I$6>=$D$26,1,0) -> 1 | J46: =IF(J$6>=$D$26,1,0) -> 1 | K46: =IF(K$6>=$D$26,1,0) -> 1 | ... AA46: =IF(AA$6>=$D$26,1,0) -> 1
A47: Role FTE | B47: Head of Growth / AE #1 FTE | C47: FTE | D47: =IF(D$6>=$D$27,1,0) -> 0 | E47: =IF(E$6>=$D$27,1,0) -> 0 | F47: =IF(F$6>=$D$27,1,0) -> 0 | G47: =IF(G$6>=$D$27,1,0) -> 1 | H47: =IF(H$6>=$D$27,1,0) -> 1 | I47: =IF(I$6>=$D$27,1,0) -> 1 | J47: =IF(J$6>=$D$27,1,0) -> 1 | K47: =IF(K$6>=$D$27,1,0) -> 1 | ... AA47: =IF(AA$6>=$D$27,1,0) -> 1
A48: Role FTE | B48: Marketing Manager FTE | C48: FTE | D48: =IF(D$6>=$D$28,1,0) -> 0 | E48: =IF(E$6>=$D$28,1,0) -> 0 | F48: =IF(F$6>=$D$28,1,0) -> 0 | G48: =IF(G$6>=$D$28,1,0) -> 0 | H48: =IF(H$6>=$D$28,1,0) -> 1 | I48: =IF(I$6>=$D$28,1,0) -> 1 | J48: =IF(J$6>=$D$28,1,0) -> 1 | K48: =IF(K$6>=$D$28,1,0) -> 1 | ... AA48: =IF(AA$6>=$D$28,1,0) -> 1
A49: Role FTE | B49: Full-Stack Engineer #2 FTE | C49: FTE | D49: =IF(D$6>=$D$29,1,0) -> 0 | E49: =IF(E$6>=$D$29,1,0) -> 0 | F49: =IF(F$6>=$D$29,1,0) -> 0 | G49: =IF(G$6>=$D$29,1,0) -> 0 | H49: =IF(H$6>=$D$29,1,0) -> 0 | I49: =IF(I$6>=$D$29,1,0) -> 1 | J49: =IF(J$6>=$D$29,1,0) -> 1 | K49: =IF(K$6>=$D$29,1,0) -> 1 | ... AA49: =IF(AA$6>=$D$29,1,0) -> 1
A50: Role FTE | B50: Customer Success #1 FTE | C50: FTE | D50: =IF($D$32="Deferred",0,IF(D$6>=$D$32,1,0)) -> 0 | E50: =IF($D$32="Deferred",0,IF(E$6>=$D$32,1,0)) -> 0 | F50: =IF($D$32="Deferred",0,IF(F$6>=$D$32,1,0)) -> 0 | G50: =IF($D$32="Deferred",0,IF(G$6>=$D$32,1,0)) -> 0 | H50: =IF($D$32="Deferred",0,IF(H$6>=$D$32,1,0)) -> 0 | I50: =IF($D$32="Deferred",0,IF(I$6>=$D$32,1,0)) -> 0 | J50: =IF($D$32="Deferred",0,IF(J$6>=$D$32,1,0)) -> 0 | K50: =IF($D$32="Deferred",0,IF(K$6>=$D$32,1,0)) -> 1 | ... AA50: =IF($D$32="Deferred",0,IF(AA$6>=$D$32,1,0)) -> 1
A51: Role FTE | B51: Product Manager FTE | C51: FTE | D51: =IF(D$6>=$D$33,1,0) -> 0 | E51: =IF(E$6>=$D$33,1,0) -> 0 | F51: =IF(F$6>=$D$33,1,0) -> 0 | G51: =IF(G$6>=$D$33,1,0) -> 0 | H51: =IF(H$6>=$D$33,1,0) -> 0 | I51: =IF(I$6>=$D$33,1,0) -> 0 | J51: =IF(J$6>=$D$33,1,0) -> 0 | K51: =IF(K$6>=$D$33,1,0) -> 0 | ... AA51: =IF(AA$6>=$D$33,1,0) -> 1
A52: Role FTE | B52: Data Engineer FTE | C52: FTE | D52: =IF(D$6>=$D$34,1,0) -> 0 | E52: =IF(E$6>=$D$34,1,0) -> 0 | F52: =IF(F$6>=$D$34,1,0) -> 0 | G52: =IF(G$6>=$D$34,1,0) -> 0 | H52: =IF(H$6>=$D$34,1,0) -> 0 | I52: =IF(I$6>=$D$34,1,0) -> 0 | J52: =IF(J$6>=$D$34,1,0) -> 0 | K52: =IF(K$6>=$D$34,1,0) -> 0 | ... AA52: =IF(AA$6>=$D$34,1,0) -> 1
A53: Role FTE | B53: AE #2 FTE | C53: FTE | D53: =IF(D$6>=$D$35,1,0) -> 0 | E53: =IF(E$6>=$D$35,1,0) -> 0 | F53: =IF(F$6>=$D$35,1,0) -> 0 | G53: =IF(G$6>=$D$35,1,0) -> 0 | H53: =IF(H$6>=$D$35,1,0) -> 0 | I53: =IF(I$6>=$D$35,1,0) -> 0 | J53: =IF(J$6>=$D$35,1,0) -> 0 | K53: =IF(K$6>=$D$35,1,0) -> 0 | ... AA53: =IF(AA$6>=$D$35,1,0) -> 1
A54: Role FTE | B54: Customer Success #2 FTE | C54: FTE | D54: =IF($D$38="Deferred",0,IF(D$6>=$D$38,1,0)) -> 0 | E54: =IF($D$38="Deferred",0,IF(E$6>=$D$38,1,0)) -> 0 | F54: =IF($D$38="Deferred",0,IF(F$6>=$D$38,1,0)) -> 0 | G54: =IF($D$38="Deferred",0,IF(G$6>=$D$38,1,0)) -> 0 | H54: =IF($D$38="Deferred",0,IF(H$6>=$D$38,1,0)) -> 0 | I54: =IF($D$38="Deferred",0,IF(I$6>=$D$38,1,0)) -> 0 | J54: =IF($D$38="Deferred",0,IF(J$6>=$D$38,1,0)) -> 0 | K54: =IF($D$38="Deferred",0,IF(K$6>=$D$38,1,0)) -> 0 | ... AA54: =IF($D$38="Deferred",0,IF(AA$6>=$D$38,1,0)) -> 1
A55: Role FTE | B55: AE #3 FTE | C55: FTE | D55: =IF(D$6>=$D$39,1,0) -> 0 | E55: =IF(E$6>=$D$39,1,0) -> 0 | F55: =IF(F$6>=$D$39,1,0) -> 0 | G55: =IF(G$6>=$D$39,1,0) -> 0 | H55: =IF(H$6>=$D$39,1,0) -> 0 | I55: =IF(I$6>=$D$39,1,0) -> 0 | J55: =IF(J$6>=$D$39,1,0) -> 0 | K55: =IF(K$6>=$D$39,1,0) -> 0 | ... AA55: =IF(AA$6>=$D$39,1,0) -> 1
A56: Role FTE | B56: CFO / Finance Hire FTE | C56: FTE | D56: =IF(D$6>=$D$41,1,0) -> 0 | E56: =IF(E$6>=$D$41,1,0) -> 0 | F56: =IF(F$6>=$D$41,1,0) -> 0 | G56: =IF(G$6>=$D$41,1,0) -> 0 | H56: =IF(H$6>=$D$41,1,0) -> 0 | I56: =IF(I$6>=$D$41,1,0) -> 0 | J56: =IF(J$6>=$D$41,1,0) -> 0 | K56: =IF(K$6>=$D$41,1,0) -> 0 | ... AA56: =IF(AA$6>=$D$41,1,0) -> 1
A58: § 5 DEPARTMENT FTE SUMMARY
A59: Department FTE | B59: R&D FTE | C59: FTE | D59: =SUM(D45,D46,D49,D51,D52) -> 1 | E59: =SUM(E45,E46,E49,E51,E52) -> 1 | F59: =SUM(F45,F46,F49,F51,F52) -> 2 | G59: =SUM(G45,G46,G49,G51,G52) -> 2 | H59: =SUM(H45,H46,H49,H51,H52) -> 2 | I59: =SUM(I45,I46,I49,I51,I52) -> 3 | J59: =SUM(J45,J46,J49,J51,J52) -> 3 | K59: =SUM(K45,K46,K49,K51,K52) -> 3 | ... AA59: =SUM(AA45,AA46,AA49,AA51,AA52) -> 5
A60: Department FTE | B60: Sales & Marketing FTE | C60: FTE | D60: =SUM(D47,D48,D53,D55) -> 0 | E60: =SUM(E47,E48,E53,E55) -> 0 | F60: =SUM(F47,F48,F53,F55) -> 0 | G60: =SUM(G47,G48,G53,G55) -> 1 | H60: =SUM(H47,H48,H53,H55) -> 2 | I60: =SUM(I47,I48,I53,I55) -> 2 | J60: =SUM(J47,J48,J53,J55) -> 2 | K60: =SUM(K47,K48,K53,K55) -> 2 | ... AA60: =SUM(AA47,AA48,AA53,AA55) -> 4
A61: Department FTE | B61: G&A FTE | C61: FTE | D61: =SUM(D44,D56) -> 1 | E61: =SUM(E44,E56) -> 1 | F61: =SUM(F44,F56) -> 1 | G61: =SUM(G44,G56) -> 1 | H61: =SUM(H44,H56) -> 1 | I61: =SUM(I44,I56) -> 1 | J61: =SUM(J44,J56) -> 1 | K61: =SUM(K44,K56) -> 1 | ... AA61: =SUM(AA44,AA56) -> 2
A62: Department FTE | B62: COGS / Customer Success FTE | C62: FTE | D62: =SUM(D50,D54) -> 0 | E62: =SUM(E50,E54) -> 0 | F62: =SUM(F50,F54) -> 0 | G62: =SUM(G50,G54) -> 0 | H62: =SUM(H50,H54) -> 0 | I62: =SUM(I50,I54) -> 0 | J62: =SUM(J50,J54) -> 0 | K62: =SUM(K50,K54) -> 1 | ... AA62: =SUM(AA50,AA54) -> 2
A63: Department FTE | B63: Total Department FTE | C63: FTE | D63: =SUM(D59:D62) -> 2 | E63: =SUM(E59:E62) -> 2 | F63: =SUM(F59:F62) -> 3 | G63: =SUM(G59:G62) -> 4 | H63: =SUM(H59:H62) -> 5 | I63: =SUM(I59:I62) -> 6 | J63: =SUM(J59:J62) -> 6 | K63: =SUM(K59:K62) -> 7 | ... AA63: =SUM(AA59:AA62) -> 13
A64: Department FTE | B64: Total Role FTE | C64: FTE | D64: =SUM(D44:D56) -> 2 | E64: =SUM(E44:E56) -> 2 | F64: =SUM(F44:F56) -> 3 | G64: =SUM(G44:G56) -> 4 | H64: =SUM(H44:H56) -> 5 | I64: =SUM(I44:I56) -> 6 | J64: =SUM(J44:J56) -> 6 | K64: =SUM(K44:K56) -> 7 | ... AA64: =SUM(AA44:AA56) -> 13
A66: § 6 SALARY BY ROLE
A67: Salary | B67: Founder / CEO ; Annual Salary | C67: $ | D67: =D44*INDEX('1. Assumptions'!$G:$G,MATCH($B67,'1. Assumptions'!$B:$B,0))/12 -> 10000 | E67: =E44*INDEX('1. Assumptions'!$G:$G,MATCH($B67,'1. Assumptions'!$B:$B,0))/12 -> 10000 | F67: =F44*INDEX('1. Assumptions'!$G:$G,MATCH($B67,'1. Assumptions'!$B:$B,0))/12 -> 10000 | G67: =G44*INDEX('1. Assumptions'!$G:$G,MATCH($B67,'1. Assumptions'!$B:$B,0))/12 -> 10000 | H67: =H44*INDEX('1. Assumptions'!$G:$G,MATCH($B67,'1. Assumptions'!$B:$B,0))/12 -> 10000 | I67: =I44*INDEX('1. Assumptions'!$G:$G,MATCH($B67,'1. Assumptions'!$B:$B,0))/12 -> 10000 | J67: =J44*INDEX('1. Assumptions'!$G:$G,MATCH($B67,'1. Assumptions'!$B:$B,0))/12 -> 10000 | K67: =K44*INDEX('1. Assumptions'!$G:$G,MATCH($B67,'1. Assumptions'!$B:$B,0))/12 -> 10000 | ... AA67: =AA44*INDEX('1. Assumptions'!$G:$G,MATCH($B67,'1. Assumptions'!$B:$B,0))/12 -> 10000
A68: Salary | B68: Founder / CTO ; Annual Salary | C68: $ | D68: =D45*INDEX('1. Assumptions'!$G:$G,MATCH($B68,'1. Assumptions'!$B:$B,0))/12 -> 10833.333 | E68: =E45*INDEX('1. Assumptions'!$G:$G,MATCH($B68,'1. Assumptions'!$B:$B,0))/12 -> 10833.333 | F68: =F45*INDEX('1. Assumptions'!$G:$G,MATCH($B68,'1. Assumptions'!$B:$B,0))/12 -> 10833.333 | G68: =G45*INDEX('1. Assumptions'!$G:$G,MATCH($B68,'1. Assumptions'!$B:$B,0))/12 -> 10833.333 | H68: =H45*INDEX('1. Assumptions'!$G:$G,MATCH($B68,'1. Assumptions'!$B:$B,0))/12 -> 10833.333 | I68: =I45*INDEX('1. Assumptions'!$G:$G,MATCH($B68,'1. Assumptions'!$B:$B,0))/12 -> 10833.333 | J68: =J45*INDEX('1. Assumptions'!$G:$G,MATCH($B68,'1. Assumptions'!$B:$B,0))/12 -> 10833.333 | K68: =K45*INDEX('1. Assumptions'!$G:$G,MATCH($B68,'1. Assumptions'!$B:$B,0))/12 -> 10833.333 | ... AA68: =AA45*INDEX('1. Assumptions'!$G:$G,MATCH($B68,'1. Assumptions'!$B:$B,0))/12 -> 10833.333
A69: Salary | B69: Full-Stack Engineer #1 ; Annual Salary | C69: $ | D69: =D46*INDEX('1. Assumptions'!$G:$G,MATCH($B69,'1. Assumptions'!$B:$B,0))/12 -> 0 | E69: =E46*INDEX('1. Assumptions'!$G:$G,MATCH($B69,'1. Assumptions'!$B:$B,0))/12 -> 0 | F69: =F46*INDEX('1. Assumptions'!$G:$G,MATCH($B69,'1. Assumptions'!$B:$B,0))/12 -> 12500 | G69: =G46*INDEX('1. Assumptions'!$G:$G,MATCH($B69,'1. Assumptions'!$B:$B,0))/12 -> 12500 | H69: =H46*INDEX('1. Assumptions'!$G:$G,MATCH($B69,'1. Assumptions'!$B:$B,0))/12 -> 12500 | I69: =I46*INDEX('1. Assumptions'!$G:$G,MATCH($B69,'1. Assumptions'!$B:$B,0))/12 -> 12500 | J69: =J46*INDEX('1. Assumptions'!$G:$G,MATCH($B69,'1. Assumptions'!$B:$B,0))/12 -> 12500 | K69: =K46*INDEX('1. Assumptions'!$G:$G,MATCH($B69,'1. Assumptions'!$B:$B,0))/12 -> 12500 | ... AA69: =AA46*INDEX('1. Assumptions'!$G:$G,MATCH($B69,'1. Assumptions'!$B:$B,0))/12 -> 12500
A70: Salary | B70: Head of Growth / AE #1 ; OTE (Base + Variable) | C70: $ | D70: =D47*INDEX('1. Assumptions'!$G:$G,MATCH($B70,'1. Assumptions'!$B:$B,0))/12 -> 0 | E70: =E47*INDEX('1. Assumptions'!$G:$G,MATCH($B70,'1. Assumptions'!$B:$B,0))/12 -> 0 | F70: =F47*INDEX('1. Assumptions'!$G:$G,MATCH($B70,'1. Assumptions'!$B:$B,0))/12 -> 0 | G70: =G47*INDEX('1. Assumptions'!$G:$G,MATCH($B70,'1. Assumptions'!$B:$B,0))/12 -> 12500 | H70: =H47*INDEX('1. Assumptions'!$G:$G,MATCH($B70,'1. Assumptions'!$B:$B,0))/12 -> 12500 | I70: =I47*INDEX('1. Assumptions'!$G:$G,MATCH($B70,'1. Assumptions'!$B:$B,0))/12 -> 12500 | J70: =J47*INDEX('1. Assumptions'!$G:$G,MATCH($B70,'1. Assumptions'!$B:$B,0))/12 -> 12500 | K70: =K47*INDEX('1. Assumptions'!$G:$G,MATCH($B70,'1. Assumptions'!$B:$B,0))/12 -> 12500 | ... AA70: =AA47*INDEX('1. Assumptions'!$G:$G,MATCH($B70,'1. Assumptions'!$B:$B,0))/12 -> 12500
A71: Salary | B71: Marketing Manager ; Annual Salary | C71: $ | D71: =D48*INDEX('1. Assumptions'!$G:$G,MATCH($B71,'1. Assumptions'!$B:$B,0))/12 -> 0 | E71: =E48*INDEX('1. Assumptions'!$G:$G,MATCH($B71,'1. Assumptions'!$B:$B,0))/12 -> 0 | F71: =F48*INDEX('1. Assumptions'!$G:$G,MATCH($B71,'1. Assumptions'!$B:$B,0))/12 -> 0 | G71: =G48*INDEX('1. Assumptions'!$G:$G,MATCH($B71,'1. Assumptions'!$B:$B,0))/12 -> 0 | H71: =H48*INDEX('1. Assumptions'!$G:$G,MATCH($B71,'1. Assumptions'!$B:$B,0))/12 -> 8333.3333 | I71: =I48*INDEX('1. Assumptions'!$G:$G,MATCH($B71,'1. Assumptions'!$B:$B,0))/12 -> 8333.3333 | J71: =J48*INDEX('1. Assumptions'!$G:$G,MATCH($B71,'1. Assumptions'!$B:$B,0))/12 -> 8333.3333 | K71: =K48*INDEX('1. Assumptions'!$G:$G,MATCH($B71,'1. Assumptions'!$B:$B,0))/12 -> 8333.3333 | ... AA71: =AA48*INDEX('1. Assumptions'!$G:$G,MATCH($B71,'1. Assumptions'!$B:$B,0))/12 -> 8333.3333
A72: Salary | B72: Full-Stack Engineer #2 ; Annual Salary | C72: $ | D72: =D49*INDEX('1. Assumptions'!$G:$G,MATCH($B72,'1. Assumptions'!$B:$B,0))/12 -> 0 | E72: =E49*INDEX('1. Assumptions'!$G:$G,MATCH($B72,'1. Assumptions'!$B:$B,0))/12 -> 0 | F72: =F49*INDEX('1. Assumptions'!$G:$G,MATCH($B72,'1. Assumptions'!$B:$B,0))/12 -> 0 | G72: =G49*INDEX('1. Assumptions'!$G:$G,MATCH($B72,'1. Assumptions'!$B:$B,0))/12 -> 0 | H72: =H49*INDEX('1. Assumptions'!$G:$G,MATCH($B72,'1. Assumptions'!$B:$B,0))/12 -> 0 | I72: =I49*INDEX('1. Assumptions'!$G:$G,MATCH($B72,'1. Assumptions'!$B:$B,0))/12 -> 12500 | J72: =J49*INDEX('1. Assumptions'!$G:$G,MATCH($B72,'1. Assumptions'!$B:$B,0))/12 -> 12500 | K72: =K49*INDEX('1. Assumptions'!$G:$G,MATCH($B72,'1. Assumptions'!$B:$B,0))/12 -> 12500 | ... AA72: =AA49*INDEX('1. Assumptions'!$G:$G,MATCH($B72,'1. Assumptions'!$B:$B,0))/12 -> 12500
A73: Salary | B73: Customer Success #1 ; Annual Salary | C73: $ | D73: =D50*INDEX('1. Assumptions'!$G:$G,MATCH($B73,'1. Assumptions'!$B:$B,0))/12 -> 0 | E73: =E50*INDEX('1. Assumptions'!$G:$G,MATCH($B73,'1. Assumptions'!$B:$B,0))/12 -> 0 | F73: =F50*INDEX('1. Assumptions'!$G:$G,MATCH($B73,'1. Assumptions'!$B:$B,0))/12 -> 0 | G73: =G50*INDEX('1. Assumptions'!$G:$G,MATCH($B73,'1. Assumptions'!$B:$B,0))/12 -> 0 | H73: =H50*INDEX('1. Assumptions'!$G:$G,MATCH($B73,'1. Assumptions'!$B:$B,0))/12 -> 0 | I73: =I50*INDEX('1. Assumptions'!$G:$G,MATCH($B73,'1. Assumptions'!$B:$B,0))/12 -> 0 | J73: =J50*INDEX('1. Assumptions'!$G:$G,MATCH($B73,'1. Assumptions'!$B:$B,0))/12 -> 0 | K73: =K50*INDEX('1. Assumptions'!$G:$G,MATCH($B73,'1. Assumptions'!$B:$B,0))/12 -> 7083.3333 | ... AA73: =AA50*INDEX('1. Assumptions'!$G:$G,MATCH($B73,'1. Assumptions'!$B:$B,0))/12 -> 7083.3333
A74: Salary | B74: Product Manager ; Annual Salary | C74: $ | D74: =D51*INDEX('1. Assumptions'!$G:$G,MATCH($B74,'1. Assumptions'!$B:$B,0))/12 -> 0 | E74: =E51*INDEX('1. Assumptions'!$G:$G,MATCH($B74,'1. Assumptions'!$B:$B,0))/12 -> 0 | F74: =F51*INDEX('1. Assumptions'!$G:$G,MATCH($B74,'1. Assumptions'!$B:$B,0))/12 -> 0 | G74: =G51*INDEX('1. Assumptions'!$G:$G,MATCH($B74,'1. Assumptions'!$B:$B,0))/12 -> 0 | H74: =H51*INDEX('1. Assumptions'!$G:$G,MATCH($B74,'1. Assumptions'!$B:$B,0))/12 -> 0 | I74: =I51*INDEX('1. Assumptions'!$G:$G,MATCH($B74,'1. Assumptions'!$B:$B,0))/12 -> 0 | J74: =J51*INDEX('1. Assumptions'!$G:$G,MATCH($B74,'1. Assumptions'!$B:$B,0))/12 -> 0 | K74: =K51*INDEX('1. Assumptions'!$G:$G,MATCH($B74,'1. Assumptions'!$B:$B,0))/12 -> 0 | ... AA74: =AA51*INDEX('1. Assumptions'!$G:$G,MATCH($B74,'1. Assumptions'!$B:$B,0))/12 -> 10833.333
A75: Salary | B75: Data Engineer ; Annual Salary | C75: $ | D75: =D52*INDEX('1. Assumptions'!$G:$G,MATCH($B75,'1. Assumptions'!$B:$B,0))/12 -> 0 | E75: =E52*INDEX('1. Assumptions'!$G:$G,MATCH($B75,'1. Assumptions'!$B:$B,0))/12 -> 0 | F75: =F52*INDEX('1. Assumptions'!$G:$G,MATCH($B75,'1. Assumptions'!$B:$B,0))/12 -> 0 | G75: =G52*INDEX('1. Assumptions'!$G:$G,MATCH($B75,'1. Assumptions'!$B:$B,0))/12 -> 0 | H75: =H52*INDEX('1. Assumptions'!$G:$G,MATCH($B75,'1. Assumptions'!$B:$B,0))/12 -> 0 | I75: =I52*INDEX('1. Assumptions'!$G:$G,MATCH($B75,'1. Assumptions'!$B:$B,0))/12 -> 0 | J75: =J52*INDEX('1. Assumptions'!$G:$G,MATCH($B75,'1. Assumptions'!$B:$B,0))/12 -> 0 | K75: =K52*INDEX('1. Assumptions'!$G:$G,MATCH($B75,'1. Assumptions'!$B:$B,0))/12 -> 0 | ... AA75: =AA52*INDEX('1. Assumptions'!$G:$G,MATCH($B75,'1. Assumptions'!$B:$B,0))/12 -> 11666.667
A76: Salary | B76: AE #2 ; OTE | C76: $ | D76: =D53*INDEX('1. Assumptions'!$G:$G,MATCH($B76,'1. Assumptions'!$B:$B,0))/12 -> 0 | E76: =E53*INDEX('1. Assumptions'!$G:$G,MATCH($B76,'1. Assumptions'!$B:$B,0))/12 -> 0 | F76: =F53*INDEX('1. Assumptions'!$G:$G,MATCH($B76,'1. Assumptions'!$B:$B,0))/12 -> 0 | G76: =G53*INDEX('1. Assumptions'!$G:$G,MATCH($B76,'1. Assumptions'!$B:$B,0))/12 -> 0 | H76: =H53*INDEX('1. Assumptions'!$G:$G,MATCH($B76,'1. Assumptions'!$B:$B,0))/12 -> 0 | I76: =I53*INDEX('1. Assumptions'!$G:$G,MATCH($B76,'1. Assumptions'!$B:$B,0))/12 -> 0 | J76: =J53*INDEX('1. Assumptions'!$G:$G,MATCH($B76,'1. Assumptions'!$B:$B,0))/12 -> 0 | K76: =K53*INDEX('1. Assumptions'!$G:$G,MATCH($B76,'1. Assumptions'!$B:$B,0))/12 -> 0 | ... AA76: =AA53*INDEX('1. Assumptions'!$G:$G,MATCH($B76,'1. Assumptions'!$B:$B,0))/12 -> 11666.667
A77: Salary | B77: Customer Success #2 ; Annual Salary | C77: $ | D77: =D54*INDEX('1. Assumptions'!$G:$G,MATCH($B77,'1. Assumptions'!$B:$B,0))/12 -> 0 | E77: =E54*INDEX('1. Assumptions'!$G:$G,MATCH($B77,'1. Assumptions'!$B:$B,0))/12 -> 0 | F77: =F54*INDEX('1. Assumptions'!$G:$G,MATCH($B77,'1. Assumptions'!$B:$B,0))/12 -> 0 | G77: =G54*INDEX('1. Assumptions'!$G:$G,MATCH($B77,'1. Assumptions'!$B:$B,0))/12 -> 0 | H77: =H54*INDEX('1. Assumptions'!$G:$G,MATCH($B77,'1. Assumptions'!$B:$B,0))/12 -> 0 | I77: =I54*INDEX('1. Assumptions'!$G:$G,MATCH($B77,'1. Assumptions'!$B:$B,0))/12 -> 0 | J77: =J54*INDEX('1. Assumptions'!$G:$G,MATCH($B77,'1. Assumptions'!$B:$B,0))/12 -> 0 | K77: =K54*INDEX('1. Assumptions'!$G:$G,MATCH($B77,'1. Assumptions'!$B:$B,0))/12 -> 0 | ... AA77: =AA54*INDEX('1. Assumptions'!$G:$G,MATCH($B77,'1. Assumptions'!$B:$B,0))/12 -> 7083.3333
A78: Salary | B78: AE #3 ; OTE | C78: $ | D78: =D55*INDEX('1. Assumptions'!$G:$G,MATCH($B78,'1. Assumptions'!$B:$B,0))/12 -> 0 | E78: =E55*INDEX('1. Assumptions'!$G:$G,MATCH($B78,'1. Assumptions'!$B:$B,0))/12 -> 0 | F78: =F55*INDEX('1. Assumptions'!$G:$G,MATCH($B78,'1. Assumptions'!$B:$B,0))/12 -> 0 | G78: =G55*INDEX('1. Assumptions'!$G:$G,MATCH($B78,'1. Assumptions'!$B:$B,0))/12 -> 0 | H78: =H55*INDEX('1. Assumptions'!$G:$G,MATCH($B78,'1. Assumptions'!$B:$B,0))/12 -> 0 | I78: =I55*INDEX('1. Assumptions'!$G:$G,MATCH($B78,'1. Assumptions'!$B:$B,0))/12 -> 0 | J78: =J55*INDEX('1. Assumptions'!$G:$G,MATCH($B78,'1. Assumptions'!$B:$B,0))/12 -> 0 | K78: =K55*INDEX('1. Assumptions'!$G:$G,MATCH($B78,'1. Assumptions'!$B:$B,0))/12 -> 0 | ... AA78: =AA55*INDEX('1. Assumptions'!$G:$G,MATCH($B78,'1. Assumptions'!$B:$B,0))/12 -> 11666.667
A79: Salary | B79: CFO / Finance Hire ; Annual Salary | C79: $ | D79: =D56*INDEX('1. Assumptions'!$G:$G,MATCH($B79,'1. Assumptions'!$B:$B,0))/12 -> 0 | E79: =E56*INDEX('1. Assumptions'!$G:$G,MATCH($B79,'1. Assumptions'!$B:$B,0))/12 -> 0 | F79: =F56*INDEX('1. Assumptions'!$G:$G,MATCH($B79,'1. Assumptions'!$B:$B,0))/12 -> 0 | G79: =G56*INDEX('1. Assumptions'!$G:$G,MATCH($B79,'1. Assumptions'!$B:$B,0))/12 -> 0 | H79: =H56*INDEX('1. Assumptions'!$G:$G,MATCH($B79,'1. Assumptions'!$B:$B,0))/12 -> 0 | I79: =I56*INDEX('1. Assumptions'!$G:$G,MATCH($B79,'1. Assumptions'!$B:$B,0))/12 -> 0 | J79: =J56*INDEX('1. Assumptions'!$G:$G,MATCH($B79,'1. Assumptions'!$B:$B,0))/12 -> 0 | K79: =K56*INDEX('1. Assumptions'!$G:$G,MATCH($B79,'1. Assumptions'!$B:$B,0))/12 -> 0 | ... AA79: =AA56*INDEX('1. Assumptions'!$G:$G,MATCH($B79,'1. Assumptions'!$B:$B,0))/12 -> 13333.333
A80: Salary | B80: Total Salary Expense | C80: $ | D80: =SUM(D67:D79) -> 20833.333 | E80: =SUM(E67:E79) -> 20833.333 | F80: =SUM(F67:F79) -> 33333.333 | G80: =SUM(G67:G79) -> 45833.333 | H80: =SUM(H67:H79) -> 54166.667 | I80: =SUM(I67:I79) -> 66666.667 | J80: =SUM(J67:J79) -> 66666.667 | K80: =SUM(K67:K79) -> 73750 | ... AA80: =SUM(AA67:AA79) -> 140000
A81: Benefits | B81: Benefits Load | C81: $ | D81: =D80*INDEX('1. Assumptions'!$G:$G,MATCH("Benefits Load (% of salary)",'1. Assumptions'!$B:$B,0)) -> 4166.6667 | E81: =E80*INDEX('1. Assumptions'!$G:$G,MATCH("Benefits Load (% of salary)",'1. Assumptions'!$B:$B,0)) -> 4166.6667 | F81: =F80*INDEX('1. Assumptions'!$G:$G,MATCH("Benefits Load (% of salary)",'1. Assumptions'!$B:$B,0)) -> 6666.6667 | G81: =G80*INDEX('1. Assumptions'!$G:$G,MATCH("Benefits Load (% of salary)",'1. Assumptions'!$B:$B,0)) -> 9166.6667 | H81: =H80*INDEX('1. Assumptions'!$G:$G,MATCH("Benefits Load (% of salary)",'1. Assumptions'!$B:$B,0)) -> 10833.333 | I81: =I80*INDEX('1. Assumptions'!$G:$G,MATCH("Benefits Load (% of salary)",'1. Assumptions'!$B:$B,0)) -> 13333.333 | J81: =J80*INDEX('1. Assumptions'!$G:$G,MATCH("Benefits Load (% of salary)",'1. Assumptions'!$B:$B,0)) -> 13333.333 | K81: =K80*INDEX('1. Assumptions'!$G:$G,MATCH("Benefits Load (% of salary)",'1. Assumptions'!$B:$B,0)) -> 14750 | ... AA81: =AA80*INDEX('1. Assumptions'!$G:$G,MATCH("Benefits Load (% of salary)",'1. Assumptions'!$B:$B,0)) -> 28000
A82: Tools | B82: Tools & Equipment ($/employee/year) | C82: $ | D82: =D64*INDEX('1. Assumptions'!$G:$G,MATCH($B82,'1. Assumptions'!$B:$B,0))/12 -> 333.33333 | E82: =E64*INDEX('1. Assumptions'!$G:$G,MATCH($B82,'1. Assumptions'!$B:$B,0))/12 -> 333.33333 | F82: =F64*INDEX('1. Assumptions'!$G:$G,MATCH($B82,'1. Assumptions'!$B:$B,0))/12 -> 500 | G82: =G64*INDEX('1. Assumptions'!$G:$G,MATCH($B82,'1. Assumptions'!$B:$B,0))/12 -> 666.66667 | H82: =H64*INDEX('1. Assumptions'!$G:$G,MATCH($B82,'1. Assumptions'!$B:$B,0))/12 -> 833.33333 | I82: =I64*INDEX('1. Assumptions'!$G:$G,MATCH($B82,'1. Assumptions'!$B:$B,0))/12 -> 1000 | J82: =J64*INDEX('1. Assumptions'!$G:$G,MATCH($B82,'1. Assumptions'!$B:$B,0))/12 -> 1000 | K82: =K64*INDEX('1. Assumptions'!$G:$G,MATCH($B82,'1. Assumptions'!$B:$B,0))/12 -> 1166.6667 | ... AA82: =AA64*INDEX('1. Assumptions'!$G:$G,MATCH($B82,'1. Assumptions'!$B:$B,0))/12 -> 2166.6667
A83: Payroll | B83: Total Fully Loaded Payroll | C83: $ | D83: =D80+D81+D82 -> 25333.333 | E83: =E80+E81+E82 -> 25333.333 | F83: =F80+F81+F82 -> 40500 | G83: =G80+G81+G82 -> 55666.667 | H83: =H80+H81+H82 -> 65833.333 | I83: =I80+I81+I82 -> 81000 | J83: =J80+J81+J82 -> 81000 | K83: =K80+K81+K82 -> 89666.667 | ... AA83: =AA80+AA81+AA82 -> 170166.67
A85: § 7 FULLY LOADED PAYROLL BY DEPARTMENT
A86: Department Payroll | B86: R&D Salary | C86: $ | D86: =SUM(D68,D69,D72,D74,D75) -> 10833.333 | E86: =SUM(E68,E69,E72,E74,E75) -> 10833.333 | F86: =SUM(F68,F69,F72,F74,F75) -> 23333.333 | G86: =SUM(G68,G69,G72,G74,G75) -> 23333.333 | H86: =SUM(H68,H69,H72,H74,H75) -> 23333.333 | I86: =SUM(I68,I69,I72,I74,I75) -> 35833.333 | J86: =SUM(J68,J69,J72,J74,J75) -> 35833.333 | K86: =SUM(K68,K69,K72,K74,K75) -> 35833.333 | ... AA86: =SUM(AA68,AA69,AA72,AA74,AA75) -> 58333.333
A87: Department Payroll | B87: Sales & Marketing Salary | C87: $ | D87: =SUM(D70,D71,D76,D78) -> 0 | E87: =SUM(E70,E71,E76,E78) -> 0 | F87: =SUM(F70,F71,F76,F78) -> 0 | G87: =SUM(G70,G71,G76,G78) -> 12500 | H87: =SUM(H70,H71,H76,H78) -> 20833.333 | I87: =SUM(I70,I71,I76,I78) -> 20833.333 | J87: =SUM(J70,J71,J76,J78) -> 20833.333 | K87: =SUM(K70,K71,K76,K78) -> 20833.333 | ... AA87: =SUM(AA70,AA71,AA76,AA78) -> 44166.667
A88: Department Payroll | B88: G&A Salary | C88: $ | D88: =SUM(D67,D79) -> 10000 | E88: =SUM(E67,E79) -> 10000 | F88: =SUM(F67,F79) -> 10000 | G88: =SUM(G67,G79) -> 10000 | H88: =SUM(H67,H79) -> 10000 | I88: =SUM(I67,I79) -> 10000 | J88: =SUM(J67,J79) -> 10000 | K88: =SUM(K67,K79) -> 10000 | ... AA88: =SUM(AA67,AA79) -> 23333.333
A89: Department Payroll | B89: CS Salary | C89: $ | D89: =SUM(D73,D77) -> 0 | E89: =SUM(E73,E77) -> 0 | F89: =SUM(F73,F77) -> 0 | G89: =SUM(G73,G77) -> 0 | H89: =SUM(H73,H77) -> 0 | I89: =SUM(I73,I77) -> 0 | J89: =SUM(J73,J77) -> 0 | K89: =SUM(K73,K77) -> 7083.3333 | ... AA89: =SUM(AA73,AA77) -> 14166.667
A90: Department Payroll | B90: R&D Fully Loaded Payroll | C90: $ | D90: =D86*(1+INDEX('1. Assumptions'!$G:$G,MATCH("Benefits Load (% of salary)",'1. Assumptions'!$B:$B,0)))+D59*INDEX('1. Assumptions'!$G:$G,MATCH($B$82,'1. Assumptions'!$B:$B,0))/12 -> 13166.667 | E90: =E86*(1+INDEX('1. Assumptions'!$G:$G,MATCH("Benefits Load (% of salary)",'1. Assumptions'!$B:$B,0)))+E59*INDEX('1. Assumptions'!$G:$G,MATCH($B$82,'1. Assumptions'!$B:$B,0))/12 -> 13166.667 | F90: =F86*(1+INDEX('1. Assumptions'!$G:$G,MATCH("Benefits Load (% of salary)",'1. Assumptions'!$B:$B,0)))+F59*INDEX('1. Assumptions'!$G:$G,MATCH($B$82,'1. Assumptions'!$B:$B,0))/12 -> 28333.333 | G90: =G86*(1+INDEX('1. Assumptions'!$G:$G,MATCH("Benefits Load (% of salary)",'1. Assumptions'!$B:$B,0)))+G59*INDEX('1. Assumptions'!$G:$G,MATCH($B$82,'1. Assumptions'!$B:$B,0))/12 -> 28333.333 | H90: =H86*(1+INDEX('1. Assumptions'!$G:$G,MATCH("Benefits Load (% of salary)",'1. Assumptions'!$B:$B,0)))+H59*INDEX('1. Assumptions'!$G:$G,MATCH($B$82,'1. Assumptions'!$B:$B,0))/12 -> 28333.333 | I90: =I86*(1+INDEX('1. Assumptions'!$G:$G,MATCH("Benefits Load (% of salary)",'1. Assumptions'!$B:$B,0)))+I59*INDEX('1. Assumptions'!$G:$G,MATCH($B$82,'1. Assumptions'!$B:$B,0))/12 -> 43500 | J90: =J86*(1+INDEX('1. Assumptions'!$G:$G,MATCH("Benefits Load (% of salary)",'1. Assumptions'!$B:$B,0)))+J59*INDEX('1. Assumptions'!$G:$G,MATCH($B$82,'1. Assumptions'!$B:$B,0))/12 -> 43500 | K90: =K86*(1+INDEX('1. Assumptions'!$G:$G,MATCH("Benefits Load (% of salary)",'1. Assumptions'!$B:$B,0)))+K59*INDEX('1. Assumptions'!$G:$G,MATCH($B$82,'1. Assumptions'!$B:$B,0))/12 -> 43500 | ... AA90: =AA86*(1+INDEX('1. Assumptions'!$G:$G,MATCH("Benefits Load (% of salary)",'1. Assumptions'!$B:$B,0)))+AA59*INDEX('1. Assumptions'!$G:$G,MATCH($B$82,'1. Assumptions'!$B:$B,0))/12 -> 70833.333
A91: Department Payroll | B91: Sales & Marketing Fully Loaded Payroll | C91: $ | D91: =D87*(1+INDEX('1. Assumptions'!$G:$G,MATCH("Benefits Load (% of salary)",'1. Assumptions'!$B:$B,0)))+D60*INDEX('1. Assumptions'!$G:$G,MATCH($B$82,'1. Assumptions'!$B:$B,0))/12 -> 0 | E91: =E87*(1+INDEX('1. Assumptions'!$G:$G,MATCH("Benefits Load (% of salary)",'1. Assumptions'!$B:$B,0)))+E60*INDEX('1. Assumptions'!$G:$G,MATCH($B$82,'1. Assumptions'!$B:$B,0))/12 -> 0 | F91: =F87*(1+INDEX('1. Assumptions'!$G:$G,MATCH("Benefits Load (% of salary)",'1. Assumptions'!$B:$B,0)))+F60*INDEX('1. Assumptions'!$G:$G,MATCH($B$82,'1. Assumptions'!$B:$B,0))/12 -> 0 | G91: =G87*(1+INDEX('1. Assumptions'!$G:$G,MATCH("Benefits Load (% of salary)",'1. Assumptions'!$B:$B,0)))+G60*INDEX('1. Assumptions'!$G:$G,MATCH($B$82,'1. Assumptions'!$B:$B,0))/12 -> 15166.667 | H91: =H87*(1+INDEX('1. Assumptions'!$G:$G,MATCH("Benefits Load (% of salary)",'1. Assumptions'!$B:$B,0)))+H60*INDEX('1. Assumptions'!$G:$G,MATCH($B$82,'1. Assumptions'!$B:$B,0))/12 -> 25333.333 | I91: =I87*(1+INDEX('1. Assumptions'!$G:$G,MATCH("Benefits Load (% of salary)",'1. Assumptions'!$B:$B,0)))+I60*INDEX('1. Assumptions'!$G:$G,MATCH($B$82,'1. Assumptions'!$B:$B,0))/12 -> 25333.333 | J91: =J87*(1+INDEX('1. Assumptions'!$G:$G,MATCH("Benefits Load (% of salary)",'1. Assumptions'!$B:$B,0)))+J60*INDEX('1. Assumptions'!$G:$G,MATCH($B$82,'1. Assumptions'!$B:$B,0))/12 -> 25333.333 | K91: =K87*(1+INDEX('1. Assumptions'!$G:$G,MATCH("Benefits Load (% of salary)",'1. Assumptions'!$B:$B,0)))+K60*INDEX('1. Assumptions'!$G:$G,MATCH($B$82,'1. Assumptions'!$B:$B,0))/12 -> 25333.333 | ... AA91: =AA87*(1+INDEX('1. Assumptions'!$G:$G,MATCH("Benefits Load (% of salary)",'1. Assumptions'!$B:$B,0)))+AA60*INDEX('1. Assumptions'!$G:$G,MATCH($B$82,'1. Assumptions'!$B:$B,0))/12 -> 53666.667
A92: Department Payroll | B92: G&A Fully Loaded Payroll | C92: $ | D92: =D88*(1+INDEX('1. Assumptions'!$G:$G,MATCH("Benefits Load (% of salary)",'1. Assumptions'!$B:$B,0)))+D61*INDEX('1. Assumptions'!$G:$G,MATCH("Tools & Equipment ($/employee/year)",'1. Assumptions'!$B:$B,0))/12 -> 12166.667 | E92: =E88*(1+INDEX('1. Assumptions'!$G:$G,MATCH("Benefits Load (% of salary)",'1. Assumptions'!$B:$B,0)))+E61*INDEX('1. Assumptions'!$G:$G,MATCH("Tools & Equipment ($/employee/year)",'1. Assumptions'!$B:$B,0))/12 -> 12166.667 | F92: =F88*(1+INDEX('1. Assumptions'!$G:$G,MATCH("Benefits Load (% of salary)",'1. Assumptions'!$B:$B,0)))+F61*INDEX('1. Assumptions'!$G:$G,MATCH("Tools & Equipment ($/employee/year)",'1. Assumptions'!$B:$B,0))/12 -> 12166.667 | G92: =G88*(1+INDEX('1. Assumptions'!$G:$G,MATCH("Benefits Load (% of salary)",'1. Assumptions'!$B:$B,0)))+G61*INDEX('1. Assumptions'!$G:$G,MATCH("Tools & Equipment ($/employee/year)",'1. Assumptions'!$B:$B,0))/12 -> 12166.667 | H92: =H88*(1+INDEX('1. Assumptions'!$G:$G,MATCH("Benefits Load (% of salary)",'1. Assumptions'!$B:$B,0)))+H61*INDEX('1. Assumptions'!$G:$G,MATCH("Tools & Equipment ($/employee/year)",'1. Assumptions'!$B:$B,0))/12 -> 12166.667 | I92: =I88*(1+INDEX('1. Assumptions'!$G:$G,MATCH("Benefits Load (% of salary)",'1. Assumptions'!$B:$B,0)))+I61*INDEX('1. Assumptions'!$G:$G,MATCH("Tools & Equipment ($/employee/year)",'1. Assumptions'!$B:$B,0))/12 -> 12166.667 | J92: =J88*(1+INDEX('1. Assumptions'!$G:$G,MATCH("Benefits Load (% of salary)",'1. Assumptions'!$B:$B,0)))+J61*INDEX('1. Assumptions'!$G:$G,MATCH("Tools & Equipment ($/employee/year)",'1. Assumptions'!$B:$B,0))/12 -> 12166.667 | K92: =K88*(1+INDEX('1. Assumptions'!$G:$G,MATCH("Benefits Load (% of salary)",'1. Assumptions'!$B:$B,0)))+K61*INDEX('1. Assumptions'!$G:$G,MATCH("Tools & Equipment ($/employee/year)",'1. Assumptions'!$B:$B,0))/12 -> 12166.667 | ... AA92: =AA88*(1+INDEX('1. Assumptions'!$G:$G,MATCH("Benefits Load (% of salary)",'1. Assumptions'!$B:$B,0)))+AA61*INDEX('1. Assumptions'!$G:$G,MATCH("Tools & Equipment ($/employee/year)",'1. Assumptions'!$B:$B,0))/12 -> 28333.333
A93: Department Payroll | B93: CS Fully Loaded Payroll | C93: $ | D93: =D89*(1+INDEX('1. Assumptions'!$G:$G,MATCH("Benefits Load (% of salary)",'1. Assumptions'!$B:$B,0)))+D62*INDEX('1. Assumptions'!$G:$G,MATCH("Tools & Equipment ($/employee/year)",'1. Assumptions'!$B:$B,0))/12 -> 0 | E93: =E89*(1+INDEX('1. Assumptions'!$G:$G,MATCH("Benefits Load (% of salary)",'1. Assumptions'!$B:$B,0)))+E62*INDEX('1. Assumptions'!$G:$G,MATCH("Tools & Equipment ($/employee/year)",'1. Assumptions'!$B:$B,0))/12 -> 0 | F93: =F89*(1+INDEX('1. Assumptions'!$G:$G,MATCH("Benefits Load (% of salary)",'1. Assumptions'!$B:$B,0)))+F62*INDEX('1. Assumptions'!$G:$G,MATCH("Tools & Equipment ($/employee/year)",'1. Assumptions'!$B:$B,0))/12 -> 0 | G93: =G89*(1+INDEX('1. Assumptions'!$G:$G,MATCH("Benefits Load (% of salary)",'1. Assumptions'!$B:$B,0)))+G62*INDEX('1. Assumptions'!$G:$G,MATCH("Tools & Equipment ($/employee/year)",'1. Assumptions'!$B:$B,0))/12 -> 0 | H93: =H89*(1+INDEX('1. Assumptions'!$G:$G,MATCH("Benefits Load (% of salary)",'1. Assumptions'!$B:$B,0)))+H62*INDEX('1. Assumptions'!$G:$G,MATCH("Tools & Equipment ($/employee/year)",'1. Assumptions'!$B:$B,0))/12 -> 0 | I93: =I89*(1+INDEX('1. Assumptions'!$G:$G,MATCH("Benefits Load (% of salary)",'1. Assumptions'!$B:$B,0)))+I62*INDEX('1. Assumptions'!$G:$G,MATCH("Tools & Equipment ($/employee/year)",'1. Assumptions'!$B:$B,0))/12 -> 0 | J93: =J89*(1+INDEX('1. Assumptions'!$G:$G,MATCH("Benefits Load (% of salary)",'1. Assumptions'!$B:$B,0)))+J62*INDEX('1. Assumptions'!$G:$G,MATCH("Tools & Equipment ($/employee/year)",'1. Assumptions'!$B:$B,0))/12 -> 0 | K93: =K89*(1+INDEX('1. Assumptions'!$G:$G,MATCH("Benefits Load (% of salary)",'1. Assumptions'!$B:$B,0)))+K62*INDEX('1. Assumptions'!$G:$G,MATCH("Tools & Equipment ($/employee/year)",'1. Assumptions'!$B:$B,0))/12 -> 8666.6667 | ... AA93: =AA89*(1+INDEX('1. Assumptions'!$G:$G,MATCH("Benefits Load (% of salary)",'1. Assumptions'!$B:$B,0)))+AA62*INDEX('1. Assumptions'!$G:$G,MATCH("Tools & Equipment ($/employee/year)",'1. Assumptions'!$B:$B,0))/12 -> 17333.333
A94: Department Payroll | B94: Total Fully Loaded Payroll by Dept | C94: $ | D94: =SUM(D90:D93) -> 25333.333 | E94: =SUM(E90:E93) -> 25333.333 | F94: =SUM(F90:F93) -> 40500 | G94: =SUM(G90:G93) -> 55666.667 | H94: =SUM(H90:H93) -> 65833.333 | I94: =SUM(I90:I93) -> 81000 | J94: =SUM(J90:J93) -> 81000 | K94: =SUM(K90:K93) -> 89666.667 | ... AA94: =SUM(AA90:AA93) -> 170166.67
A95: Payroll Classification | B95: COGS Payroll | C95: $ | D95: =D93 -> 0 | E95: =E93 -> 0 | F95: =F93 -> 0 | G95: =G93 -> 0 | H95: =H93 -> 0 | I95: =I93 -> 0 | J95: =J93 -> 0 | K95: =K93 -> 8666.6667 | ... AA95: =AA93 -> 17333.333
A96: Payroll Classification | B96: R&D OpEx Payroll | C96: $ | D96: =D90 -> 13166.667 | E96: =E90 -> 13166.667 | F96: =F90 -> 28333.333 | G96: =G90 -> 28333.333 | H96: =H90 -> 28333.333 | I96: =I90 -> 43500 | J96: =J90 -> 43500 | K96: =K90 -> 43500 | ... AA96: =AA90 -> 70833.333
A97: Payroll Classification | B97: Sales & Marketing OpEx Payroll | C97: $ | D97: =D91 -> 0 | E97: =E91 -> 0 | F97: =F91 -> 0 | G97: =G91 -> 15166.667 | H97: =H91 -> 25333.333 | I97: =I91 -> 25333.333 | J97: =J91 -> 25333.333 | K97: =K91 -> 25333.333 | ... AA97: =AA91 -> 53666.667
A98: Payroll Classification | B98: G&A OpEx Payroll | C98: $ | D98: =D92 -> 12166.667 | E98: =E92 -> 12166.667 | F98: =F92 -> 12166.667 | G98: =G92 -> 12166.667 | H98: =H92 -> 12166.667 | I98: =I92 -> 12166.667 | J98: =J92 -> 12166.667 | K98: =K92 -> 12166.667 | ... AA98: =AA92 -> 28333.333
A99: Payroll Classification | B99: Total OpEx Payroll | C99: $ | D99: =SUM(D96:D98) -> 25333.333 | E99: =SUM(E96:E98) -> 25333.333 | F99: =SUM(F96:F98) -> 40500 | G99: =SUM(G96:G98) -> 55666.667 | H99: =SUM(H96:H98) -> 65833.333 | I99: =SUM(I96:I98) -> 81000 | J99: =SUM(J96:J98) -> 81000 | K99: =SUM(K96:K98) -> 81000 | ... AA99: =SUM(AA96:AA98) -> 152833.33
A100: Payroll Classification | B100: Total Payroll Classification | C100: $ | D100: =D95+D99 -> 25333.333 | E100: =E95+E99 -> 25333.333 | F100: =F95+F99 -> 40500 | G100: =G95+G99 -> 55666.667 | H100: =H95+H99 -> 65833.333 | I100: =I95+I99 -> 81000 | J100: =J95+J99 -> 81000 | K100: =K95+K99 -> 89666.667 | ... AA100: =AA95+AA99 -> 170166.67
A102: § 8 SALES CAPACITY / AE RAMP
A103: Sales Capacity | B103: Active AE Count | C103: FTE | D103: =SUM(D47,D53,D55) -> 0 | E103: =SUM(E47,E53,E55) -> 0 | F103: =SUM(F47,F53,F55) -> 0 | G103: =SUM(G47,G53,G55) -> 1 | H103: =SUM(H47,H53,H55) -> 1 | I103: =SUM(I47,I53,I55) -> 1 | J103: =SUM(J47,J53,J55) -> 1 | K103: =SUM(K47,K53,K55) -> 1 | ... AA103: =SUM(AA47,AA53,AA55) -> 3
A104: Sales Capacity | B104: AE Ramp Month | C104: FTE | D104: =IF(D103=0,0,(D47*MAX(0,D$6-$D$27+1)+D53*MAX(0,D$6-$D$35+1)+D55*MAX(0,D$6-$D$39+1))/D103) -> 0 | E104: =IF(E103=0,0,(E47*MAX(0,E$6-$D$27+1)+E53*MAX(0,E$6-$D$35+1)+E55*MAX(0,E$6-$D$39+1))/E103) -> 0 | F104: =IF(F103=0,0,(F47*MAX(0,F$6-$D$27+1)+F53*MAX(0,F$6-$D$35+1)+F55*MAX(0,F$6-$D$39+1))/F103) -> 0 | G104: =IF(G103=0,0,(G47*MAX(0,G$6-$D$27+1)+G53*MAX(0,G$6-$D$35+1)+G55*MAX(0,G$6-$D$39+1))/G103) -> 1 | H104: =IF(H103=0,0,(H47*MAX(0,H$6-$D$27+1)+H53*MAX(0,H$6-$D$35+1)+H55*MAX(0,H$6-$D$39+1))/H103) -> 2 | I104: =IF(I103=0,0,(I47*MAX(0,I$6-$D$27+1)+I53*MAX(0,I$6-$D$35+1)+I55*MAX(0,I$6-$D$39+1))/I103) -> 3 | J104: =IF(J103=0,0,(J47*MAX(0,J$6-$D$27+1)+J53*MAX(0,J$6-$D$35+1)+J55*MAX(0,J$6-$D$39+1))/J103) -> 4 | K104: =IF(K103=0,0,(K47*MAX(0,K$6-$D$27+1)+K53*MAX(0,K$6-$D$35+1)+K55*MAX(0,K$6-$D$39+1))/K103) -> 5 | ... AA104: =IF(AA103=0,0,(AA47*MAX(0,AA$6-$D$27+1)+AA53*MAX(0,AA$6-$D$35+1)+AA55*MAX(0,AA$6-$D$39+1))/AA103) -> 16
A105: Sales Capacity | B105: AE Productivity % | C105: % | D105: =IF(D104=0,0,IF(D104<2,25%,IF(D104<3,50%,IF(D104<4,75%,100%)))) -> 0 | E105: =IF(E104=0,0,IF(E104<2,25%,IF(E104<3,50%,IF(E104<4,75%,100%)))) -> 0 | F105: =IF(F104=0,0,IF(F104<2,25%,IF(F104<3,50%,IF(F104<4,75%,100%)))) -> 0 | G105: =IF(G104=0,0,IF(G104<2,25%,IF(G104<3,50%,IF(G104<4,75%,100%)))) -> 0.25 | H105: =IF(H104=0,0,IF(H104<2,25%,IF(H104<3,50%,IF(H104<4,75%,100%)))) -> 0.5 | I105: =IF(I104=0,0,IF(I104<2,25%,IF(I104<3,50%,IF(I104<4,75%,100%)))) -> 0.75 | J105: =IF(J104=0,0,IF(J104<2,25%,IF(J104<3,50%,IF(J104<4,75%,100%)))) -> 1 | K105: =IF(K104=0,0,IF(K104<2,25%,IF(K104<3,50%,IF(K104<4,75%,100%)))) -> 1 | ... AA105: =IF(AA104=0,0,IF(AA104<2,25%,IF(AA104<3,50%,IF(AA104<4,75%,100%)))) -> 1
A106: Sales Capacity | B106: Effective AE Capacity | C106: FTE | D106: =D103*D105 -> 0 | E106: =E103*E105 -> 0 | F106: =F103*F105 -> 0 | G106: =G103*G105 -> 0.25 | H106: =H103*H105 -> 0.5 | I106: =I103*I105 -> 0.75 | J106: =J103*J105 -> 1 | K106: =K103*K105 -> 1 | ... AA106: =AA103*AA105 -> 3
A107: Sales Capacity | B107: Monthly New ARR Capacity | C107: $ | D107: =D106*INDEX('1. Assumptions'!$G:$G,MATCH("AE Annual Quota (full productivity)",'1. Assumptions'!$B:$B,0))*INDEX('1. Assumptions'!$G:$G,MATCH("AE Quota Attainment",'1. Assumptions'!$B:$B,0))/12 -> 0 | E107: =E106*INDEX('1. Assumptions'!$G:$G,MATCH("AE Annual Quota (full productivity)",'1. Assumptions'!$B:$B,0))*INDEX('1. Assumptions'!$G:$G,MATCH("AE Quota Attainment",'1. Assumptions'!$B:$B,0))/12 -> 0 | F107: =F106*INDEX('1. Assumptions'!$G:$G,MATCH("AE Annual Quota (full productivity)",'1. Assumptions'!$B:$B,0))*INDEX('1. Assumptions'!$G:$G,MATCH("AE Quota Attainment",'1. Assumptions'!$B:$B,0))/12 -> 0 | G107: =G106*INDEX('1. Assumptions'!$G:$G,MATCH("AE Annual Quota (full productivity)",'1. Assumptions'!$B:$B,0))*INDEX('1. Assumptions'!$G:$G,MATCH("AE Quota Attainment",'1. Assumptions'!$B:$B,0))/12 -> 7500 | H107: =H106*INDEX('1. Assumptions'!$G:$G,MATCH("AE Annual Quota (full productivity)",'1. Assumptions'!$B:$B,0))*INDEX('1. Assumptions'!$G:$G,MATCH("AE Quota Attainment",'1. Assumptions'!$B:$B,0))/12 -> 15000 | I107: =I106*INDEX('1. Assumptions'!$G:$G,MATCH("AE Annual Quota (full productivity)",'1. Assumptions'!$B:$B,0))*INDEX('1. Assumptions'!$G:$G,MATCH("AE Quota Attainment",'1. Assumptions'!$B:$B,0))/12 -> 22500 | J107: =J106*INDEX('1. Assumptions'!$G:$G,MATCH("AE Annual Quota (full productivity)",'1. Assumptions'!$B:$B,0))*INDEX('1. Assumptions'!$G:$G,MATCH("AE Quota Attainment",'1. Assumptions'!$B:$B,0))/12 -> 30000 | K107: =K106*INDEX('1. Assumptions'!$G:$G,MATCH("AE Annual Quota (full productivity)",'1. Assumptions'!$B:$B,0))*INDEX('1. Assumptions'!$G:$G,MATCH("AE Quota Attainment",'1. Assumptions'!$B:$B,0))/12 -> 30000 | ... AA107: =AA106*INDEX('1. Assumptions'!$G:$G,MATCH("AE Annual Quota (full productivity)",'1. Assumptions'!$B:$B,0))*INDEX('1. Assumptions'!$G:$G,MATCH("AE Quota Attainment",'1. Assumptions'!$B:$B,0))/12 -> 90000
A108: Sales Capacity | B108: Required New ARR from Revenue | C108: $ | D108: =N(D14)*INDEX('1. Assumptions'!$G:$G,MATCH("Enterprise Plan Price ($/mo)",'1. Assumptions'!$B:$B,0))*12 -> 0 | E108: =N(E14)*INDEX('1. Assumptions'!$G:$G,MATCH("Enterprise Plan Price ($/mo)",'1. Assumptions'!$B:$B,0))*12 -> 0 | F108: =N(F14)*INDEX('1. Assumptions'!$G:$G,MATCH("Enterprise Plan Price ($/mo)",'1. Assumptions'!$B:$B,0))*12 -> 0 | G108: =N(G14)*INDEX('1. Assumptions'!$G:$G,MATCH("Enterprise Plan Price ($/mo)",'1. Assumptions'!$B:$B,0))*12 -> 0 | H108: =N(H14)*INDEX('1. Assumptions'!$G:$G,MATCH("Enterprise Plan Price ($/mo)",'1. Assumptions'!$B:$B,0))*12 -> 0 | I108: =N(I14)*INDEX('1. Assumptions'!$G:$G,MATCH("Enterprise Plan Price ($/mo)",'1. Assumptions'!$B:$B,0))*12 -> 7188 | J108: =N(J14)*INDEX('1. Assumptions'!$G:$G,MATCH("Enterprise Plan Price ($/mo)",'1. Assumptions'!$B:$B,0))*12 -> 7691.16 | K108: =N(K14)*INDEX('1. Assumptions'!$G:$G,MATCH("Enterprise Plan Price ($/mo)",'1. Assumptions'!$B:$B,0))*12 -> 8229.5412 | ... AA108: =N(AA14)*INDEX('1. Assumptions'!$G:$G,MATCH("Enterprise Plan Price ($/mo)",'1. Assumptions'!$B:$B,0))*12 -> 24294.953
A109: Sales Capacity | B109: Sales Capacity Check | C109: Check | D109: =IF(D107>=D108,"OK","CAPACITY GAP") -> OK | E109: =IF(E107>=E108,"OK","CAPACITY GAP") -> OK | F109: =IF(F107>=F108,"OK","CAPACITY GAP") -> OK | G109: =IF(G107>=G108,"OK","CAPACITY GAP") -> OK | H109: =IF(H107>=H108,"OK","CAPACITY GAP") -> OK | I109: =IF(I107>=I108,"OK","CAPACITY GAP") -> OK | J109: =IF(J107>=J108,"OK","CAPACITY GAP") -> OK | K109: =IF(K107>=K108,"OK","CAPACITY GAP") -> OK | ... AA109: =IF(AA107>=AA108,"OK","CAPACITY GAP") -> OK
...

Sheet 5. COGS 
A1: LaunchPlan AI: COGS & Gross Margin
A3: Section | B3: Line Item | C3: =+'3. Revenue Model'!C2 -> Unit | D3: =+'3. Revenue Model'!D2 -> Month 1 | E3: =+'3. Revenue Model'!E2 -> Month 2 | F3: =+'3. Revenue Model'!F2 -> Month 3 | G3: =+'3. Revenue Model'!G2 -> Month 4 | H3: =+'3. Revenue Model'!H2 -> Month 5 | I3: =+'3. Revenue Model'!I2 -> Month 6 | J3: =+'3. Revenue Model'!J2 -> Month 7 | ... AC3: =+'3. Revenue Model'!AC2 -> Check / Source
A4: § 1 CONTROL & TIMELINE
A5: Control | B5: Selected Scenario | C5: Text | D5: =INDEX('1. Assumptions'!$G:$G,MATCH("Selected Scenario",'1. Assumptions'!$B:$B,0)) -> Base | E5: =INDEX('1. Assumptions'!$G:$G,MATCH("Selected Scenario",'1. Assumptions'!$B:$B,0)) -> Base | F5: =INDEX('1. Assumptions'!$G:$G,MATCH("Selected Scenario",'1. Assumptions'!$B:$B,0)) -> Base | G5: =INDEX('1. Assumptions'!$G:$G,MATCH("Selected Scenario",'1. Assumptions'!$B:$B,0)) -> Base | H5: =INDEX('1. Assumptions'!$G:$G,MATCH("Selected Scenario",'1. Assumptions'!$B:$B,0)) -> Base | I5: =INDEX('1. Assumptions'!$G:$G,MATCH("Selected Scenario",'1. Assumptions'!$B:$B,0)) -> Base | J5: =INDEX('1. Assumptions'!$G:$G,MATCH("Selected Scenario",'1. Assumptions'!$B:$B,0)) -> Base | K5: =INDEX('1. Assumptions'!$G:$G,MATCH("Selected Scenario",'1. Assumptions'!$B:$B,0)) -> Base | ... AA5: =INDEX('1. Assumptions'!$G:$G,MATCH("Selected Scenario",'1. Assumptions'!$B:$B,0)) -> Base
A6: Timeline | B6: Month Number | C6: Month | D6: =+'3. Revenue Model'!D5 -> 1 | E6: =+'3. Revenue Model'!E5 -> 2 | F6: =+'3. Revenue Model'!F5 -> 3 | G6: =+'3. Revenue Model'!G5 -> 4 | H6: =+'3. Revenue Model'!H5 -> 5 | I6: =+'3. Revenue Model'!I5 -> 6 | J6: =+'3. Revenue Model'!J5 -> 7 | K6: =+'3. Revenue Model'!K5 -> 8 | ... AA6: =+'3. Revenue Model'!AA5 -> 24 | AB6: Linked to Revenue Drivers timeline | AC6: Revenue Drivers
A7: Timeline | B7: Calendar Month | C7: Date | D7: =+'3. Revenue Model'!D6 -> 46023 | E7: =+'3. Revenue Model'!E6 -> 46054 | F7: =+'3. Revenue Model'!F6 -> 46082 | G7: =+'3. Revenue Model'!G6 -> 46113 | H7: =+'3. Revenue Model'!H6 -> 46143 | I7: =+'3. Revenue Model'!I6 -> 46174 | J7: =+'3. Revenue Model'!J6 -> 46204 | K7: =+'3. Revenue Model'!K6 -> 46235 | ... AA7: =+'3. Revenue Model'!AA6 -> 46722 | AB7: Linked to Revenue Drivers timeline | AC7: Revenue Drivers
A9: § 2 REVENUE DRIVERS LINKED FROM REVENUE
A10: Revenue Drivers | B10: Starter MRR | C10: $ | D10: =IFERROR(INDEX('3. Revenue Model'!$D:$AA,MATCH($B10,'3. Revenue Model'!$B:$B,0),MATCH(D$3,'3. Revenue Model'!$D$2:$AA$2,0)),"CHECK") -> 16366 | E10: =IFERROR(INDEX('3. Revenue Model'!$D:$AA,MATCH($B10,'3. Revenue Model'!$B:$B,0),MATCH(E$3,'3. Revenue Model'!$D$2:$AA$2,0)),"CHECK") -> 17340.12 | F10: =IFERROR(INDEX('3. Revenue Model'!$D:$AA,MATCH($B10,'3. Revenue Model'!$B:$B,0),MATCH(F$3,'3. Revenue Model'!$D$2:$AA$2,0)),"CHECK") -> 18292.053 | G10: =IFERROR(INDEX('3. Revenue Model'!$D:$AA,MATCH($B10,'3. Revenue Model'!$B:$B,0),MATCH(G$3,'3. Revenue Model'!$D$2:$AA$2,0)),"CHECK") -> 19258.163 | H10: =IFERROR(INDEX('3. Revenue Model'!$D:$AA,MATCH($B10,'3. Revenue Model'!$B:$B,0),MATCH(H$3,'3. Revenue Model'!$D$2:$AA$2,0)),"CHECK") -> 20268.972 | I10: =IFERROR(INDEX('3. Revenue Model'!$D:$AA,MATCH($B10,'3. Revenue Model'!$B:$B,0),MATCH(I$3,'3. Revenue Model'!$D$2:$AA$2,0)),"CHECK") -> 21350.699 | J10: =IFERROR(INDEX('3. Revenue Model'!$D:$AA,MATCH($B10,'3. Revenue Model'!$B:$B,0),MATCH(J$3,'3. Revenue Model'!$D$2:$AA$2,0)),"CHECK") -> 22526.491 | K10: =IFERROR(INDEX('3. Revenue Model'!$D:$AA,MATCH($B10,'3. Revenue Model'!$B:$B,0),MATCH(K$3,'3. Revenue Model'!$D$2:$AA$2,0)),"CHECK") -> 23817.396 | ... AA10: =IFERROR(INDEX('3. Revenue Model'!$D:$AA,MATCH($B10,'3. Revenue Model'!$B:$B,0),MATCH(AA$3,'3. Revenue Model'!$D$2:$AA$2,0)),"CHECK") -> 77848.623 | AB10: Linked from Revenue Drivers | AC10: Revenue Drivers
A11: Revenue Drivers | B11: Growth MRR | C11: $ | D11: =IFERROR(INDEX('3. Revenue Model'!$D:$AA,MATCH($B11,'3. Revenue Model'!$B:$B,0),MATCH(D$3,'3. Revenue Model'!$D$2:$AA$2,0)),"CHECK") -> 28242.95 | E11: =IFERROR(INDEX('3. Revenue Model'!$D:$AA,MATCH($B11,'3. Revenue Model'!$B:$B,0),MATCH(E$3,'3. Revenue Model'!$D$2:$AA$2,0)),"CHECK") -> 29099.309 | F11: =IFERROR(INDEX('3. Revenue Model'!$D:$AA,MATCH($B11,'3. Revenue Model'!$B:$B,0),MATCH(F$3,'3. Revenue Model'!$D$2:$AA$2,0)),"CHECK") -> 30036.001 | G11: =IFERROR(INDEX('3. Revenue Model'!$D:$AA,MATCH($B11,'3. Revenue Model'!$B:$B,0),MATCH(G$3,'3. Revenue Model'!$D$2:$AA$2,0)),"CHECK") -> 31052.592 | H11: =IFERROR(INDEX('3. Revenue Model'!$D:$AA,MATCH($B11,'3. Revenue Model'!$B:$B,0),MATCH(H$3,'3. Revenue Model'!$D$2:$AA$2,0)),"CHECK") -> 32151.091 | I11: =IFERROR(INDEX('3. Revenue Model'!$D:$AA,MATCH($B11,'3. Revenue Model'!$B:$B,0),MATCH(I$3,'3. Revenue Model'!$D$2:$AA$2,0)),"CHECK") -> 33335.541 | J11: =IFERROR(INDEX('3. Revenue Model'!$D:$AA,MATCH($B11,'3. Revenue Model'!$B:$B,0),MATCH(J$3,'3. Revenue Model'!$D$2:$AA$2,0)),"CHECK") -> 34611.72 | K11: =IFERROR(INDEX('3. Revenue Model'!$D:$AA,MATCH($B11,'3. Revenue Model'!$B:$B,0),MATCH(K$3,'3. Revenue Model'!$D$2:$AA$2,0)),"CHECK") -> 35986.922 | ... AA11: =IFERROR(INDEX('3. Revenue Model'!$D:$AA,MATCH($B11,'3. Revenue Model'!$B:$B,0),MATCH(AA$3,'3. Revenue Model'!$D$2:$AA$2,0)),"CHECK") -> 82479.309 | AB11: Linked from Revenue Drivers | AC11: Revenue Drivers
A12: Revenue Drivers | B12: Enterprise MRR | C12: $ | D12: =IFERROR(INDEX('3. Revenue Model'!$D:$AA,MATCH($B12,'3. Revenue Model'!$B:$B,0),MATCH(D$3,'3. Revenue Model'!$D$2:$AA$2,0)),"CHECK") -> 269.55 | E12: =IFERROR(INDEX('3. Revenue Model'!$D:$AA,MATCH($B12,'3. Revenue Model'!$B:$B,0),MATCH(E$3,'3. Revenue Model'!$D$2:$AA$2,0)),"CHECK") -> 549.77515 | F12: =IFERROR(INDEX('3. Revenue Model'!$D:$AA,MATCH($B12,'3. Revenue Model'!$B:$B,0),MATCH(F$3,'3. Revenue Model'!$D$2:$AA$2,0)),"CHECK") -> 834.83743 | G12: =IFERROR(INDEX('3. Revenue Model'!$D:$AA,MATCH($B12,'3. Revenue Model'!$B:$B,0),MATCH(G$3,'3. Revenue Model'!$D$2:$AA$2,0)),"CHECK") -> 1125.4791 | H12: =IFERROR(INDEX('3. Revenue Model'!$D:$AA,MATCH($B12,'3. Revenue Model'!$B:$B,0),MATCH(H$3,'3. Revenue Model'!$D$2:$AA$2,0)),"CHECK") -> 1422.4282 | I12: =IFERROR(INDEX('3. Revenue Model'!$D:$AA,MATCH($B12,'3. Revenue Model'!$B:$B,0),MATCH(I$3,'3. Revenue Model'!$D$2:$AA$2,0)),"CHECK") -> 2325.423 | J12: =IFERROR(INDEX('3. Revenue Model'!$D:$AA,MATCH($B12,'3. Revenue Model'!$B:$B,0),MATCH(J$3,'3. Revenue Model'!$D$2:$AA$2,0)),"CHECK") -> 3270.1049 | K12: =IFERROR(INDEX('3. Revenue Model'!$D:$AA,MATCH($B12,'3. Revenue Model'!$B:$B,0),MATCH(K$3,'3. Revenue Model'!$D$2:$AA$2,0)),"CHECK") -> 4259.7702 | ... AA12: =IFERROR(INDEX('3. Revenue Model'!$D:$AA,MATCH($B12,'3. Revenue Model'!$B:$B,0),MATCH(AA$3,'3. Revenue Model'!$D$2:$AA$2,0)),"CHECK") -> 30113.803 | AB12: Linked from Revenue Drivers | AC12: Revenue Drivers
A13: Revenue Drivers | B13: Ending Subscription MRR | C13: $ | D13: =IFERROR(INDEX('3. Revenue Model'!$D:$AA,MATCH($B13,'3. Revenue Model'!$B:$B,0),MATCH(D$3,'3. Revenue Model'!$D$2:$AA$2,0)),"CHECK") -> 44463.3 | E13: =IFERROR(INDEX('3. Revenue Model'!$D:$AA,MATCH($B13,'3. Revenue Model'!$B:$B,0),MATCH(E$3,'3. Revenue Model'!$D$2:$AA$2,0)),"CHECK") -> 46129.371 | F13: =IFERROR(INDEX('3. Revenue Model'!$D:$AA,MATCH($B13,'3. Revenue Model'!$B:$B,0),MATCH(F$3,'3. Revenue Model'!$D$2:$AA$2,0)),"CHECK") -> 47841.764 | G13: =IFERROR(INDEX('3. Revenue Model'!$D:$AA,MATCH($B13,'3. Revenue Model'!$B:$B,0),MATCH(G$3,'3. Revenue Model'!$D$2:$AA$2,0)),"CHECK") -> 49636.69 | H13: =IFERROR(INDEX('3. Revenue Model'!$D:$AA,MATCH($B13,'3. Revenue Model'!$B:$B,0),MATCH(H$3,'3. Revenue Model'!$D$2:$AA$2,0)),"CHECK") -> 51546.579 | I13: =IFERROR(INDEX('3. Revenue Model'!$D:$AA,MATCH($B13,'3. Revenue Model'!$B:$B,0),MATCH(I$3,'3. Revenue Model'!$D$2:$AA$2,0)),"CHECK") -> 54200.286 | J13: =IFERROR(INDEX('3. Revenue Model'!$D:$AA,MATCH($B13,'3. Revenue Model'!$B:$B,0),MATCH(J$3,'3. Revenue Model'!$D$2:$AA$2,0)),"CHECK") -> 57054.936 | K13: =IFERROR(INDEX('3. Revenue Model'!$D:$AA,MATCH($B13,'3. Revenue Model'!$B:$B,0),MATCH(K$3,'3. Revenue Model'!$D$2:$AA$2,0)),"CHECK") -> 60140.159 | ... AA13: =IFERROR(INDEX('3. Revenue Model'!$D:$AA,MATCH($B13,'3. Revenue Model'!$B:$B,0),MATCH(AA$3,'3. Revenue Model'!$D$2:$AA$2,0)),"CHECK") -> 170586.03 | AB13: Linked from Revenue Drivers | AC13: Revenue Drivers
A14: Revenue Drivers | B14: AI Usage Revenue | C14: $ | D14: =IFERROR(INDEX('3. Revenue Model'!$D:$AA,MATCH($B14,'3. Revenue Model'!$B:$B,0),MATCH(D$3,'3. Revenue Model'!$D$2:$AA$2,0)),"CHECK") -> 0 | E14: =IFERROR(INDEX('3. Revenue Model'!$D:$AA,MATCH($B14,'3. Revenue Model'!$B:$B,0),MATCH(E$3,'3. Revenue Model'!$D$2:$AA$2,0)),"CHECK") -> 0 | F14: =IFERROR(INDEX('3. Revenue Model'!$D:$AA,MATCH($B14,'3. Revenue Model'!$B:$B,0),MATCH(F$3,'3. Revenue Model'!$D$2:$AA$2,0)),"CHECK") -> 0 | G14: =IFERROR(INDEX('3. Revenue Model'!$D:$AA,MATCH($B14,'3. Revenue Model'!$B:$B,0),MATCH(G$3,'3. Revenue Model'!$D$2:$AA$2,0)),"CHECK") -> 0 | H14: =IFERROR(INDEX('3. Revenue Model'!$D:$AA,MATCH($B14,'3. Revenue Model'!$B:$B,0),MATCH(H$3,'3. Revenue Model'!$D$2:$AA$2,0)),"CHECK") -> 0 | I14: =IFERROR(INDEX('3. Revenue Model'!$D:$AA,MATCH($B14,'3. Revenue Model'!$B:$B,0),MATCH(I$3,'3. Revenue Model'!$D$2:$AA$2,0)),"CHECK") -> 0 | J14: =IFERROR(INDEX('3. Revenue Model'!$D:$AA,MATCH($B14,'3. Revenue Model'!$B:$B,0),MATCH(J$3,'3. Revenue Model'!$D$2:$AA$2,0)),"CHECK") -> 0 | K14: =IFERROR(INDEX('3. Revenue Model'!$D:$AA,MATCH($B14,'3. Revenue Model'!$B:$B,0),MATCH(K$3,'3. Revenue Model'!$D$2:$AA$2,0)),"CHECK") -> 0 | ... AA14: =IFERROR(INDEX('3. Revenue Model'!$D:$AA,MATCH($B14,'3. Revenue Model'!$B:$B,0),MATCH(AA$3,'3. Revenue Model'!$D$2:$AA$2,0)),"CHECK") -> 10962.866 | AB14: Linked from Revenue Drivers | AC14: Revenue Drivers
